Workbook
Name _C206: #REF!
Name _C207: #REF!
Name Bases: #REF!
Name DatosCompras: #REF!
Name Durations: #REF!
Name Fecha: #REF!
Name fecha2: #REF!
Name Filtros: #REF!
Name IQ_CH: 110000
Name IQ_CQ: 5000
Name IQ_CY: 10000
Name IQ_DAILY: 500000
Name IQ_FH: 100000
Name IQ_FQ: 500
Name IQ_FY: 1000
Name IQ_LTM: 2000
Name IQ_MONTH: 15000
Name IQ_NTM: 6000
Name IQ_WEEK: 50000
Name IQ_YTD: 3000
Name Nominales: #REF!
Name Pág1: #REF!
Name Pág2: #REF!
Name Portafolios: #REF!

Sheet Intro
B2: Grupo Coril
B3: Informe de Portafolios en Renta Variable
B5: Investment Team:
B7: Head of Investments:
F8: Victor Mendoza
F9: Portfolio Manager
F10: vmendoza@grupocoril.com
B12: Equity:
F13: Nabil Jarufe
F14: Analyst
F15: njarufe@grupocoril.com
B17: Fixed Income:
F18: Andru Ortega
F19: Assistant
F20: jortegar@grupocoril.com

Sheet Portada RV
B2: Grupo Coril
B3: Resumen de Rentabilidad en RV
B5: TC | C5: 3.7
B6: Fecha de Fin | C6: =+TODAY()-1 -> 46091
C8: Inversión | D8: P&L Total | E8: P&L Realizado | F8: P&L No Realizado | G8: Dividendos | H8: Retorno %
B9: PEN | C9: =+SUMIF(Stock!C:C,'Portada RV'!$B9,Stock!J:J) -> 2007058.2 | D9: =+SUMIF('P&L Total'!$C:$C,'Portada RV'!$B9,'P&L Total'!K:K) -> 440073.34 | E9: =+SUMIF(Ventas!E:E,'Portada RV'!B9,Ventas!L:L) -> 43711.25 | F9: =+D9-E9 -> 396362.09 | G9: =+SUMIF('P&L Total'!C:C,'Portada RV'!B9,'P&L Total'!I:I) -> 50329.098 | H9: =D9/C9 -> 0.21926287
B10: USD | C10: =+SUMIF(Stock!C:C,'Portada RV'!$B10,Stock!J:J) -> 6133797.7 | D10: =+SUMIF('P&L Total'!$C:$C,'Portada RV'!$B10,'P&L Total'!K:K) -> 129876.77 | E10: =+SUMIF(Ventas!E:E,'Portada RV'!B10,Ventas!L:L) -> 183413.15 | F10: =+D10-E10 -> -53536.383 | G10: =+SUMIF('P&L Total'!C:C,'Portada RV'!B10,'P&L Total'!I:I) -> 18849.479 | H10: =D10/C10 -> 0.021173957
C11: =+C10+C9/C5 -> 6676245.9 | E11: =+E10+E9/C5 -> 195227 | F11: =+F10+F9/3.7 -> 53588.505
B12: CxP PEN | C12: =+SUMIFS(Compras!L:L,Compras!O:O,"Pendiente",Compras!F:F,"PEN") -> 0
B13: CxC PEN | C13: =+SUMIFS(Ventas!J:J,Ventas!A:A,'Portada RV'!C6,Ventas!E:E,"PEN") -> 0
B14: CxP USD | C14: =+SUMIFS(Compras!L:L,Compras!O:O,"Pendiente",Compras!F:F,"USD") -> 99140.678
B15: CxC USD | C15: =+SUMIFS(Ventas!J:J,Ventas!A:A,'Portada RV'!C6,Ventas!E:E,"USD") -> 106656.37

Sheet P&L Total
A1: Stock | B1: Nombre | C1: Moneda | D1: Market price | E1: Stock inicial | F1: Stock final | G1: Compras | H1: Ventas | I1: Dividendos | J1: Valor stock final | K1: P&L Monto | L1: P&L %
A2: {=+_xlfn.UNIQUE(Tabla1[Identificador])} -> ITUB US Equity | B2: =+_xll.BDP($A2,"Name") -> ITAU UNIBANCO H-SPON PRF ADR | C2: =+INDEX(Tabla1[Moneda],MATCH('P&L Total'!A2,Tabla1[Identificador],0)) -> USD | D2: {=+IF(F2=0,"",_xll.BDP(A2,"PX_LAST"))} | E2: 0 | F2: =SUMIFS( Tabla1[Q], Tabla1[Identificador],A2, Tabla1[Stock],"stock" ) -> 0 | G2: =SUMIFS( Tabla1[Monto compra], Tabla1[Identificador],A2 ) -> 39868.251 | H2: =SUMIFS( Tabla2[Monto_venta], Tabla2[Identificador],A2 ) -> 46039.921 | I2: =+IFERROR(VLOOKUP(A2,Tabla3[[#All],[Identificador]:[Monto_mon_ins]],7,FALSE),"") -> 18.65535 | J2: =+IFERROR(D2*F2,"") | K2: =+IF(J2="",0,J2)-G2+H2+IF(I2="",0,I2) -> 6190.3244 | L2: =+K2/G2 -> 0.15526952
A3: EEM US Equity | B3: =+_xll.BDP($A3,"Name") -> ISHARES MSCI EMERGING MARKET | C3: =+INDEX(Tabla1[Moneda],MATCH('P&L Total'!A3,Tabla1[Identificador],0)) -> USD | D3: {=+IF(F3=0,"",_xll.BDP(A3,"PX_LAST"))} -> 58.68 | E3: 0 | F3: =SUMIFS( Tabla1[Q], Tabla1[Identificador],A3, Tabla1[Stock],"stock" ) -> 4425 | G3: =SUMIFS( Tabla1[Monto compra], Tabla1[Identificador],A3 ) -> 239499.39 | H3: =SUMIFS( Tabla2[Monto_venta], Tabla2[Identificador],A3 ) -> 0 | I3: =+IFERROR(VLOOKUP(A3,Tabla3[[#All],[Identificador]:[Monto_mon_ins]],7,FALSE),"") -> 3377.4255 | J3: =+IFERROR(D3*F3,"") -> 259659 | K3: =+IF(J3="",0,J3)-G3+H3+IF(I3="",0,I3) -> 23537.039 | L3: =+K3/G3 -> 0.098275989
A4: XLU US Equity | B4: =+_xll.BDP($A4,"Name") -> ST SR UTL SL SE SPDR ETF-USD | C4: =+INDEX(Tabla1[Moneda],MATCH('P&L Total'!A4,Tabla1[Identificador],0)) -> USD | D4: {=+IF(F4=0,"",_xll.BDP(A4,"PX_LAST"))} -> 46.56 | E4: 0 | F4: =SUMIFS( Tabla1[Q], Tabla1[Identificador],A4, Tabla1[Stock],"stock" ) -> 4123 | G4: =SUMIFS( Tabla1[Monto compra], Tabla1[Identificador],A4 ) -> 179688.62 | H4: =SUMIFS( Tabla2[Monto_venta], Tabla2[Identificador],A4 ) -> 0 | I4: =+IFERROR(VLOOKUP(A4,Tabla3[[#All],[Identificador]:[Monto_mon_ins]],7,FALSE),"") -> 531.4608 | J4: =+IFERROR(D4*F4,"") -> 191966.88 | K4: =+IF(J4="",0,J4)-G4+H4+IF(I4="",0,I4) -> 12809.723 | L4: =+K4/G4 -> 0.07128845
A5: XLI US Equity | B5: =+_xll.BDP($A5,"Name") -> SS INDUSTRIAL SELECT SECTOR | C5: =+INDEX(Tabla1[Moneda],MATCH('P&L Total'!A5,Tabla1[Identificador],0)) -> USD | D5: {=+IF(F5=0,"",_xll.BDP(A5,"PX_LAST"))} -> 170.02 | E5: 0 | F5: =SUMIFS( Tabla1[Q], Tabla1[Identificador],A5, Tabla1[Stock],"stock" ) -> 810 | G5: =SUMIFS( Tabla1[Monto compra], Tabla1[Identificador],A5 ) -> 129806.4 | H5: =SUMIFS( Tabla2[Monto_venta], Tabla2[Identificador],A5 ) -> 0 | I5: =+IFERROR(VLOOKUP(A5,Tabla3[[#All],[Identificador]:[Monto_mon_ins]],7,FALSE),"") -> 331.2748 | J5: =+IFERROR(D5*F5,"") -> 137716.2 | K5: =+IF(J5="",0,J5)-G5+H5+IF(I5="",0,I5) -> 8241.072 | L5: =+K5/G5 -> 0.063487408
A6: XLY US Equity | B6: =+_xll.BDP($A6,"Name") -> SS CONSUMER DISC SELECT SECT | C6: =+INDEX(Tabla1[Moneda],MATCH('P&L Total'!A6,Tabla1[Identificador],0)) -> USD | D6: {=+IF(F6=0,"",_xll.BDP(A6,"PX_LAST"))} -> 114.44 | E6: 0 | F6: =SUMIFS( Tabla1[Q], Tabla1[Identificador],A6, Tabla1[Stock],"stock" ) -> 1104 | G6: =SUMIFS( Tabla1[Monto compra], Tabla1[Identificador],A6 ) -> 129694.13 | H6: =SUMIFS( Tabla2[Monto_venta], Tabla2[Identificador],A6 ) -> 0 | I6: =+IFERROR(VLOOKUP(A6,Tabla3[[#All],[Identificador]:[Monto_mon_ins]],7,FALSE),"") -> 142.5425 | J6: =+IFERROR(D6*F6,"") -> 126341.76 | K6: =+IF(J6="",0,J6)-G6+H6+IF(I6="",0,I6) -> -3209.8275 | L6: =+K6/G6 -> -0.024749212
A7: PLTR US Equity | B7: =+_xll.BDP($A7,"Name") -> PALANTIR TECHNOLOGIES INC-A | C7: =+INDEX(Tabla1[Moneda],MATCH('P&L Total'!A7,Tabla1[Identificador],0)) -> USD | D7: {=+IF(F7=0,"",_xll.BDP(A7,"PX_LAST"))} | E7: 0 | F7: =SUMIFS( Tabla1[Q], Tabla1[Identificador],A7, Tabla1[Stock],"stock" ) -> 0 | G7: =SUMIFS( Tabla1[Monto compra], Tabla1[Identificador],A7 ) -> 887987.62 | H7: =SUMIFS( Tabla2[Monto_venta], Tabla2[Identificador],A7 ) -> 930751.55 | I7: =+IFERROR(VLOOKUP(A7,Tabla3[[#All],[Identificador]:[Monto_mon_ins]],7,FALSE),"") | J7: =+IFERROR(D7*F7,"") | K7: =+IF(J7="",0,J7)-G7+H7+IF(I7="",0,I7) -> 42763.93 | L7: =+K7/G7 -> 0.048158251
A8: SPY US Equity | B8: =+_xll.BDP($A8,"Name") -> SS SPDR S&P 500 ETF TRUST-US | C8: =+INDEX(Tabla1[Moneda],MATCH('P&L Total'!A8,Tabla1[Identificador],0)) -> USD | D8: {=+IF(F8=0,"",_xll.BDP(A8,"PX_LAST"))} | E8: 0 | F8: =SUMIFS( Tabla1[Q], Tabla1[Identificador],A8, Tabla1[Stock],"stock" ) -> 0 | G8: =SUMIFS( Tabla1[Monto compra], Tabla1[Identificador],A8 ) -> 208990.9 | H8: =SUMIFS( Tabla2[Monto_venta], Tabla2[Identificador],A8 ) -> 216710.2 | I8: =+IFERROR(VLOOKUP(A8,Tabla3[[#All],[Identificador]:[Monto_mon_ins]],7,FALSE),"") | J8: =+IFERROR(D8*F8,"") | K8: =+IF(J8="",0,J8)-G8+H8+IF(I8="",0,I8) -> 7719.291 | L8: =+K8/G8 -> 0.036936014
A9: FDX US Equity | B9: =+_xll.BDP($A9,"Name") -> FEDEX CORP | C9: =+INDEX(Tabla1[Moneda],MATCH('P&L Total'!A9,Tabla1[Identificador],0)) -> USD | D9: {=+IF(F9=0,"",_xll.BDP(A9,"PX_LAST"))} -> 359.47 | E9: 0 | F9: =SUMIFS( Tabla1[Q], Tabla1[Identificador],A9, Tabla1[Stock],"stock" ) -> 218 | G9: =SUMIFS( Tabla1[Monto compra], Tabla1[Identificador],A9 ) -> 49791.2 | H9: =SUMIFS( Tabla2[Monto_venta], Tabla2[Identificador],A9 ) -> 0 | I9: =+IFERROR(VLOOKUP(A9,Tabla3[[#All],[Identificador]:[Monto_mon_ins]],7,FALSE),"") -> 316.1 | J9: =+IFERROR(D9*F9,"") -> 78364.46 | K9: =+IF(J9="",0,J9)-G9+H9+IF(I9="",0,I9) -> 28889.36 | L9: =+K9/G9 -> 0.58021016
A10: XPEV US Equity | B10: =+_xll.BDP($A10,"Name") -> XPENG INC - ADR | C10: =+INDEX(Tabla1[Moneda],MATCH('P&L Total'!A10,Tabla1[Identificador],0)) -> USD | D10: {=+IF(F10=0,"",_xll.BDP(A10,"PX_LAST"))} | E10: 0 | F10: =SUMIFS( Tabla1[Q], Tabla1[Identificador],A10, Tabla1[Stock],"stock" ) -> 0 | G10: =SUMIFS( Tabla1[Monto compra], Tabla1[Identificador],A10 ) -> 54893.432 | H10: =SUMIFS( Tabla2[Monto_venta], Tabla2[Identificador],A10 ) -> 69350 | I10: =+IFERROR(VLOOKUP(A10,Tabla3[[#All],[Identificador]:[Monto_mon_ins]],7,FALSE),"") | J10: =+IFERROR(D10*F10,"") | K10: =+IF(J10="",0,J10)-G10+H10+IF(I10="",0,I10) -> 14456.568 | L10: =+K10/G10 -> 0.26335696
A11: EWP US Equity | B11: =+_xll.BDP($A11,"Name") -> ISHARES MSCI SPAIN ETF | C11: =+INDEX(Tabla1[Moneda],MATCH('P&L Total'!A11,Tabla1[Identificador],0)) -> USD | D11: {=+IF(F11=0,"",_xll.BDP(A11,"PX_LAST"))} | E11: 0 | F11: =SUMIFS( Tabla1[Q], Tabla1[Identificador],A11, Tabla1[Stock],"stock" ) -> 0 | G11: =SUMIFS( Tabla1[Monto compra], Tabla1[Identificador],A11 ) -> 49907.71 | H11: =SUMIFS( Tabla2[Monto_venta], Tabla2[Identificador],A11 ) -> 56736.033 | I11: =+IFERROR(VLOOKUP(A11,Tabla3[[#All],[Identificador]:[Monto_mon_ins]],7,FALSE),"") -> 763.32147 | J11: =+IFERROR(D11*F11,"") | K11: =+IF(J11="",0,J11)-G11+H11+IF(I11="",0,I11) -> 7591.6448 | L11: =+K11/G11 -> 0.15211367
A12: NIO US Equity | B12: =+_xll.BDP($A12,"Name") -> NIO INC - ADR | C12: =+INDEX(Tabla1[Moneda],MATCH('P&L Total'!A12,Tabla1[Identificador],0)) -> USD | D12: {=+IF(F12=0,"",_xll.BDP(A12,"PX_LAST"))} -> 5.7 | E12: 0 | F12: =SUMIFS( Tabla1[Q], Tabla1[Identificador],A12, Tabla1[Stock],"stock" ) -> 18368 | G12: =SUMIFS( Tabla1[Monto compra], Tabla1[Identificador],A12 ) -> 104519.95 | H12: =SUMIFS( Tabla2[Monto_venta], Tabla2[Identificador],A12 ) -> 0 | I12: =+IFERROR(VLOOKUP(A12,Tabla3[[#All],[Identificador]:[Monto_mon_ins]],7,FALSE),"") | J12: =+IFERROR(D12*F12,"") -> 104697.6 | K12: =+IF(J12="",0,J12)-G12+H12+IF(I12="",0,I12) -> 177.648 | L12: =+K12/G12 -> 0.0016996563
A13: PRU US Equity | B13: =+_xll.BDP($A13,"Name") -> PRUDENTIAL FINANCIAL INC | C13: =+INDEX(Tabla1[Moneda],MATCH('P&L Total'!A13,Tabla1[Identificador],0)) -> USD | D13: {=+IF(F13=0,"",_xll.BDP(A13,"PX_LAST"))} -> 95.47 | E13: 0 | F13: =SUMIFS( Tabla1[Q], Tabla1[Identificador],A13, Tabla1[Stock],"stock" ) -> 483 | G13: =SUMIFS( Tabla1[Monto compra], Tabla1[Identificador],A13 ) -> 49924.088 | H13: =SUMIFS( Tabla2[Monto_venta], Tabla2[Identificador],A13 ) -> 0 | I13: =+IFERROR(VLOOKUP(A13,Tabla3[[#All],[Identificador]:[Monto_mon_ins]],7,FALSE),"") -> 652.05 | J13: =+IFERROR(D13*F13,"") -> 46112.01 | K13: =+IF(J13="",0,J13)-G13+H13+IF(I13="",0,I13) -> -3160.0275 | L13: =+K13/G13 -> -0.06329665
A14: KMB US Equity | B14: =+_xll.BDP($A14,"Name") -> KIMBERLY-CLARK CORP | C14: =+INDEX(Tabla1[Moneda],MATCH('P&L Total'!A14,Tabla1[Identificador],0)) -> USD | D14: {=+IF(F14=0,"",_xll.BDP(A14,"PX_LAST"))} -> 101.71 | E14: 0 | F14: =SUMIFS( Tabla1[Q], Tabla1[Identificador],A14, Tabla1[Stock],"stock" ) -> 802 | G14: =SUMIFS( Tabla1[Monto compra], Tabla1[Identificador],A14 ) -> 91600.34 | H14: =SUMIFS( Tabla2[Monto_venta], Tabla2[Identificador],A14 ) -> 0 | I14: =+IFERROR(VLOOKUP(A14,Tabla3[[#All],[Identificador]:[Monto_mon_ins]],7,FALSE),"") -> 506.52 | J14: =+IFERROR(D14*F14,"") -> 81571.42 | K14: =+IF(J14="",0,J14)-G14+H14+IF(I14="",0,I14) -> -9522.3998 | L14: =+K14/G14 -> -0.10395594
... A58: EPU US Equity | B58: =+_xll.BDP($A58,"Name") -> ISHARES MSCI PERU AND GLOBAL | C58: =+INDEX(Tabla1[Moneda],MATCH('P&L Total'!A58,Tabla1[Identificador],0)) -> USD | D58: {=+IF(F58=0,"",_xll.BDP(A58,"PX_LAST"))} -> 86.87 | E58: 0 | F58: =SUMIFS( Tabla1[Q], Tabla1[Identificador],A58, Tabla1[Stock],"stock" ) -> 2369 | G58: =SUMIFS( Tabla1[Monto compra], Tabla1[Identificador],A58 ) -> 198753.77 | H58: =SUMIFS( Tabla2[Monto_venta], Tabla2[Identificador],A58 ) -> 0 | I58: =+IFERROR(VLOOKUP(A58,Tabla3[[#All],[Identificador]:[Monto_mon_ins]],7,FALSE),"") | J58: =+IFERROR(D58*F58,"") -> 205795.03 | K58: =+IF(J58="",0,J58)-G58+H58+IF(I58="",0,I58) -> 7041.2579 | L58: =+K58/G58 -> 0.03542704

Sheet Stock
A1: Stock | B1: ISIN | C1: Moneda | D1: Security Type | E1: Nombre | F1: Q | G1: Precio Promedio C | H1: P mercado | I1: P Anterior | J1: Monto compra | K1: Monto actual | L1: Monto Anterior | M1: % Allocation | N1: P&L % | O1: P&L 1d
A2: {=+_xlfn.UNIQUE(_xlfn._xlws.FILTER(Tabla1[Identificador],(Tabla1[Stock]="stock"),))} -> EEM US Equity | B2: {=_xll.BDP(A2,"ID_ISIN")} -> US4642872349 | C2: =+INDEX(Tabla1[Moneda],MATCH(A2,Tabla1[Identificador],0)) -> USD | D2: {=_xll.BDP(A2, "DS213")} -> ETP | E2: =+_xll.BDP($A2,"Name") -> ISHARES MSCI EMERGING MARKET | F2: =SUMIFS( Tabla1[Q], Tabla1[Identificador],A2, Tabla1[Stock],"stock" ) -> 4425 | G2: {=SUMPRODUCT( (Tabla1[Identificador]=A2)* (Tabla1[Stock]="stock")* Tabla1[Q]* Tabla1[P] ) /SUMIFS( Tabla1[Q], Tabla1[Identificador],A2, Tabla1[Stock],"stock" )} -> 54.124155 | H2: {=+_xll.BDP(A2,"PX_LAST")} -> 58.68 | I2: {=+_xll.BDP(A2,"PX_CLOSE_1D")} -> 58.45 | J2: =+F2*G2 -> 239499.39 | K2: =+H2*F2 -> 259659 | L2: =+I2*F2 -> 258641.25 | M2: =+IF(C2="USD",K2/SUMIF(C:C,C2,K:K),K2/SUMIF(C:C,C2,K:K)) -> 0.042838039 | N2: =+(H2*F2)/(F2*G2)-1 -> 0.084173968 | O2: {=+_xll.BDP(A2,"CURRENT_TRR_1D")/100} -> 0
A3: XLU US Equity | B3: {=_xll.BDP(A3,"ID_ISIN")} -> US81369Y8865 | C3: =+INDEX(Tabla1[Moneda],MATCH(A3,Tabla1[Identificador],0)) -> USD | D3: {=_xll.BDP(A3, "DS213")} -> ETP | E3: =+_xll.BDP($A3,"Name") -> ST SR UTL SL SE SPDR ETF-USD | F3: =SUMIFS( Tabla1[Q], Tabla1[Identificador],A3, Tabla1[Stock],"stock" ) -> 4123 | G3: {=SUMPRODUCT( (Tabla1[Identificador]=A3)* (Tabla1[Stock]="stock")* Tabla1[Q]* Tabla1[P] ) /SUMIFS( Tabla1[Q], Tabla1[Identificador],A3, Tabla1[Stock],"stock" )} -> 43.582008 | H3: {=+_xll.BDP(A3,"PX_LAST")} -> 46.56 | I3: {=+_xll.BDP(A3,"PX_CLOSE_1D")} -> 46.85 | J3: =+F3*G3 -> 179688.62 | K3: =+H3*F3 -> 191966.88 | L3: =+I3*F3 -> 193162.55 | M3: =+IF(C3="USD",K3/SUMIF(C:C,C3,K:K),K3/SUMIF(C:C,C3,K:K)) -> 0.031670324 | N3: =+(H3*F3)/(F3*G3)-1 -> 0.068330774 | O3: {=+_xll.BDP(A3,"CURRENT_TRR_1D")/100} -> 0
A4: XLI US Equity | B4: {=_xll.BDP(A4,"ID_ISIN")} -> US81369Y7040 | C4: =+INDEX(Tabla1[Moneda],MATCH(A4,Tabla1[Identificador],0)) -> USD | D4: {=_xll.BDP(A4, "DS213")} -> ETP | E4: =+_xll.BDP($A4,"Name") -> SS INDUSTRIAL SELECT SECTOR | F4: =SUMIFS( Tabla1[Q], Tabla1[Identificador],A4, Tabla1[Stock],"stock" ) -> 810 | G4: {=SUMPRODUCT( (Tabla1[Identificador]=A4)* (Tabla1[Stock]="stock")* Tabla1[Q]* Tabla1[P] ) /SUMIFS( Tabla1[Q], Tabla1[Identificador],A4, Tabla1[Stock],"stock" )} -> 160.25482 | H4: {=+_xll.BDP(A4,"PX_LAST")} -> 170.02 | I4: {=+_xll.BDP(A4,"PX_CLOSE_1D")} -> 170.94 | J4: =+F4*G4 -> 129806.4 | K4: =+H4*F4 -> 137716.2 | L4: =+I4*F4 -> 138461.4 | M4: =+IF(C4="USD",K4/SUMIF(C:C,C4,K:K),K4/SUMIF(C:C,C4,K:K)) -> 0.022720152 | N4: =+(H4*F4)/(F4*G4)-1 -> 0.060935339 | O4: {=+_xll.BDP(A4,"CURRENT_TRR_1D")/100} -> 0
A5: XLY US Equity | B5: {=_xll.BDP(A5,"ID_ISIN")} -> US81369Y4070 | C5: =+INDEX(Tabla1[Moneda],MATCH(A5,Tabla1[Identificador],0)) -> USD | D5: {=_xll.BDP(A5, "DS213")} -> ETP | E5: =+_xll.BDP($A5,"Name") -> SS CONSUMER DISC SELECT SECT | F5: =SUMIFS( Tabla1[Q], Tabla1[Identificador],A5, Tabla1[Stock],"stock" ) -> 1104 | G5: {=SUMPRODUCT( (Tabla1[Identificador]=A5)* (Tabla1[Stock]="stock")* Tabla1[Q]* Tabla1[P] ) /SUMIFS( Tabla1[Q], Tabla1[Identificador],A5, Tabla1[Stock],"stock" )} -> 117.47657 | H5: {=+_xll.BDP(A5,"PX_LAST")} -> 114.44 | I5: {=+_xll.BDP(A5,"PX_CLOSE_1D")} -> 114.59 | J5: =+F5*G5 -> 129694.13 | K5: =+H5*F5 -> 126341.76 | L5: =+I5*F5 -> 126507.36 | M5: =+IF(C5="USD",K5/SUMIF(C:C,C5,K:K),K5/SUMIF(C:C,C5,K:K)) -> 0.020843619 | N5: =+(H5*F5)/(F5*G5)-1 -> -0.025848279 | O5: {=+_xll.BDP(A5,"CURRENT_TRR_1D")/100} -> 0
A6: FDX US Equity | B6: {=_xll.BDP(A6,"ID_ISIN")} -> US31428X1063 | C6: =+INDEX(Tabla1[Moneda],MATCH(A6,Tabla1[Identificador],0)) -> USD | D6: {=_xll.BDP(A6, "DS213")} -> Common Stock | E6: =+_xll.BDP($A6,"Name") -> FEDEX CORP | F6: =SUMIFS( Tabla1[Q], Tabla1[Identificador],A6, Tabla1[Stock],"stock" ) -> 218 | G6: {=SUMPRODUCT( (Tabla1[Identificador]=A6)* (Tabla1[Stock]="stock")* Tabla1[Q]* Tabla1[P] ) /SUMIFS( Tabla1[Q], Tabla1[Identificador],A6, Tabla1[Stock],"stock" )} -> 228.4 | H6: {=+_xll.BDP(A6,"PX_LAST")} -> 359.47 | I6: {=+_xll.BDP(A6,"PX_CLOSE_1D")} -> 361.1 | J6: =+F6*G6 -> 49791.2 | K6: =+H6*F6 -> 78364.46 | L6: =+I6*F6 -> 78719.8 | M6: =+IF(C6="USD",K6/SUMIF(C:C,C6,K:K),K6/SUMIF(C:C,C6,K:K)) -> 0.012928417 | N6: =+(H6*F6)/(F6*G6)-1 -> 0.57386165 | O6: {=+_xll.BDP(A6,"CURRENT_TRR_1D")/100} -> 0
A7: NIO US Equity | B7: {=_xll.BDP(A7,"ID_ISIN")} -> US62914V1061 | C7: =+INDEX(Tabla1[Moneda],MATCH(A7,Tabla1[Identificador],0)) -> USD | D7: {=_xll.BDP(A7, "DS213")} -> ADR | E7: =+_xll.BDP($A7,"Name") -> NIO INC - ADR | F7: =SUMIFS( Tabla1[Q], Tabla1[Identificador],A7, Tabla1[Stock],"stock" ) -> 18368 | G7: {=SUMPRODUCT( (Tabla1[Identificador]=A7)* (Tabla1[Stock]="stock")* Tabla1[Q]* Tabla1[P] ) /SUMIFS( Tabla1[Q], Tabla1[Identificador],A7, Tabla1[Stock],"stock" )} -> 5.6903284 | H7: {=+_xll.BDP(A7,"PX_LAST")} -> 5.7 | I7: {=+_xll.BDP(A7,"PX_CLOSE_1D")} -> 4.94 | J7: =+F7*G7 -> 104519.95 | K7: =+H7*F7 -> 104697.6 | L7: =+I7*F7 -> 90737.92 | M7: =+IF(C7="USD",K7/SUMIF(C:C,C7,K:K),K7/SUMIF(C:C,C7,K:K)) -> 0.017272807 | N7: =+(H7*F7)/(F7*G7)-1 -> 0.0016996563 | O7: {=+_xll.BDP(A7,"CURRENT_TRR_1D")/100} -> 0
A8: PRU US Equity | B8: {=_xll.BDP(A8,"ID_ISIN")} -> US7443201022 | C8: =+INDEX(Tabla1[Moneda],MATCH(A8,Tabla1[Identificador],0)) -> USD | D8: {=_xll.BDP(A8, "DS213")} -> Common Stock | E8: =+_xll.BDP($A8,"Name") -> PRUDENTIAL FINANCIAL INC | F8: =SUMIFS( Tabla1[Q], Tabla1[Identificador],A8, Tabla1[Stock],"stock" ) -> 483 | G8: {=SUMPRODUCT( (Tabla1[Identificador]=A8)* (Tabla1[Stock]="stock")* Tabla1[Q]* Tabla1[P] ) /SUMIFS( Tabla1[Q], Tabla1[Identificador],A8, Tabla1[Stock],"stock" )} -> 103.3625 | H8: {=+_xll.BDP(A8,"PX_LAST")} -> 95.47 | I8: {=+_xll.BDP(A8,"PX_CLOSE_1D")} -> 95.93 | J8: =+F8*G8 -> 49924.088 | K8: =+H8*F8 -> 46112.01 | L8: =+I8*F8 -> 46334.19 | M8: =+IF(C8="USD",K8/SUMIF(C:C,C8,K:K),K8/SUMIF(C:C,C8,K:K)) -> 0.0076074702 | N8: =+(H8*F8)/(F8*G8)-1 -> -0.07635748 | O8: {=+_xll.BDP(A8,"CURRENT_TRR_1D")/100} -> 0
A9: KMB US Equity | B9: {=_xll.BDP(A9,"ID_ISIN")} -> US4943681035 | C9: =+INDEX(Tabla1[Moneda],MATCH(A9,Tabla1[Identificador],0)) -> USD | D9: {=_xll.BDP(A9, "DS213")} -> Common Stock | E9: =+_xll.BDP($A9,"Name") -> KIMBERLY-CLARK CORP | F9: =SUMIFS( Tabla1[Q], Tabla1[Identificador],A9, Tabla1[Stock],"stock" ) -> 802 | G9: {=SUMPRODUCT( (Tabla1[Identificador]=A9)* (Tabla1[Stock]="stock")* Tabla1[Q]* Tabla1[P] ) /SUMIFS( Tabla1[Q], Tabla1[Identificador],A9, Tabla1[Stock],"stock" )} -> 114.21489 | H9: {=+_xll.BDP(A9,"PX_LAST")} -> 101.71 | I9: {=+_xll.BDP(A9,"PX_CLOSE_1D")} -> 102.85 | J9: =+F9*G9 -> 91600.34 | K9: =+H9*F9 -> 81571.42 | L9: =+I9*F9 -> 82485.7 | M9: =+IF(C9="USD",K9/SUMIF(C:C,C9,K:K),K9/SUMIF(C:C,C9,K:K)) -> 0.013457495 | N9: =+(H9*F9)/(F9*G9)-1 -> -0.10948562 | O9: {=+_xll.BDP(A9,"CURRENT_TRR_1D")/100} -> 0
A10: UNH US Equity | B10: {=_xll.BDP(A10,"ID_ISIN")} -> US91324P1021 | C10: =+INDEX(Tabla1[Moneda],MATCH(A10,Tabla1[Identificador],0)) -> USD | D10: {=_xll.BDP(A10, "DS213")} -> Common Stock | E10: =+_xll.BDP($A10,"Name") -> UNITEDHEALTH GROUP INC | F10: =SUMIFS( Tabla1[Q], Tabla1[Identificador],A10, Tabla1[Stock],"stock" ) -> 437 | G10: {=SUMPRODUCT( (Tabla1[Identificador]=A10)* (Tabla1[Stock]="stock")* Tabla1[Q]* Tabla1[P] ) /SUMIFS( Tabla1[Q], Tabla1[Identificador],A10, Tabla1[Stock],"stock" )} -> 342.35101 | H10: {=+_xll.BDP(A10,"PX_LAST")} -> 282.34 | I10: {=+_xll.BDP(A10,"PX_CLOSE_1D")} -> 285.17 | J10: =+F10*G10 -> 149607.39 | K10: =+H10*F10 -> 123382.58 | L10: =+I10*F10 -> 124619.29 | M10: =+IF(C10="USD",K10/SUMIF(C:C,C10,K:K),K10/SUMIF(C:C,C10,K:K)) -> 0.020355419 | N10: =+(H10*F10)/(F10*G10)-1 -> -0.17529089 | O10: {=+_xll.BDP(A10,"CURRENT_TRR_1D")/100} -> 0
A11: KKR US Equity | B11: {=_xll.BDP(A11,"ID_ISIN")} -> US48251W1045 | C11: =+INDEX(Tabla1[Moneda],MATCH(A11,Tabla1[Identificador],0)) -> USD | D11: {=_xll.BDP(A11, "DS213")} -> Common Stock | E11: =+_xll.BDP($A11,"Name") -> KKR & CO INC | F11: =SUMIFS( Tabla1[Q], Tabla1[Identificador],A11, Tabla1[Stock],"stock" ) -> 341 | G11: {=SUMPRODUCT( (Tabla1[Identificador]=A11)* (Tabla1[Stock]="stock")* Tabla1[Q]* Tabla1[P] ) /SUMIFS( Tabla1[Q], Tabla1[Identificador],A11, Tabla1[Stock],"stock" )} -> 146.35 | H11: {=+_xll.BDP(A11,"PX_LAST")} -> 89.96 | I11: {=+_xll.BDP(A11,"PX_CLOSE_1D")} -> 90.94 | J11: =+F11*G11 -> 49905.35 | K11: =+H11*F11 -> 30676.36 | L11: =+I11*F11 -> 31010.54 | M11: =+IF(C11="USD",K11/SUMIF(C:C,C11,K:K),K11/SUMIF(C:C,C11,K:K)) -> 0.0050609265 | N11: =+(H11*F11)/(F11*G11)-1 -> -0.38530919 | O11: {=+_xll.BDP(A11,"CURRENT_TRR_1D")/100} -> 0
A12: EUFN US Equity | B12: {=_xll.BDP(A12,"ID_ISIN")} -> US4642891802 | C12: =+INDEX(Tabla1[Moneda],MATCH(A12,Tabla1[Identificador],0)) -> USD | D12: {=_xll.BDP(A12, "DS213")} -> ETP | E12: =+_xll.BDP($A12,"Name") -> ISHARES MSCI EUROPE FINANCIA | F12: =SUMIFS( Tabla1[Q], Tabla1[Identificador],A12, Tabla1[Stock],"stock" ) -> 4135 | G12: {=SUMPRODUCT( (Tabla1[Identificador]=A12)* (Tabla1[Stock]="stock")* Tabla1[Q]* Tabla1[P] ) /SUMIFS( Tabla1[Q], Tabla1[Identificador],A12, Tabla1[Stock],"stock" )} -> 33.794264 | H12: {=+_xll.BDP(A12,"PX_LAST")} -> 35.24 | I12: {=+_xll.BDP(A12,"PX_CLOSE_1D")} -> 35.2 | J12: =+F12*G12 -> 139739.28 | K12: =+H12*F12 -> 145717.4 | L12: =+I12*F12 -> 145552 | M12: =+IF(C12="USD",K12/SUMIF(C:C,C12,K:K),K12/SUMIF(C:C,C12,K:K)) -> 0.024040175 | N12: =+(H12*F12)/(F12*G12)-1 -> 0.042780512 | O12: {=+_xll.BDP(A12,"CURRENT_TRR_1D")/100} -> 0
A13: EZU US Equity | B13: {=_xll.BDP(A13,"ID_ISIN")} -> US4642866085 | C13: =+INDEX(Tabla1[Moneda],MATCH(A13,Tabla1[Identificador],0)) -> USD | D13: {=_xll.BDP(A13, "DS213")} -> ETP | E13: =+_xll.BDP($A13,"Name") -> ISHARES MSCI EUROZONE ETF | F13: =SUMIFS( Tabla1[Q], Tabla1[Identificador],A13, Tabla1[Stock],"stock" ) -> 2391 | G13: {=SUMPRODUCT( (Tabla1[Identificador]=A13)* (Tabla1[Stock]="stock")* Tabla1[Q]* Tabla1[P] ) /SUMIFS( Tabla1[Q], Tabla1[Identificador],A13, Tabla1[Stock],"stock" )} -> 62.629001 | H13: {=+_xll.BDP(A13,"PX_LAST")} -> 64.04 | I13: {=+_xll.BDP(A13,"PX_CLOSE_1D")} -> 63.87 | J13: =+F13*G13 -> 149745.94 | K13: =+H13*F13 -> 153119.64 | L13: =+I13*F13 -> 152713.17 | M13: =+IF(C13="USD",K13/SUMIF(C:C,C13,K:K),K13/SUMIF(C:C,C13,K:K)) -> 0.025261382 | N13: =+(H13*F13)/(F13*G13)-1 -> 0.022529476 | O13: {=+_xll.BDP(A13,"CURRENT_TRR_1D")/100} -> 0
A14: FERREYC1 pe Equity | B14: {=_xll.BDP(A14,"ID_ISIN")} -> PEP736001004 | C14: =+INDEX(Tabla1[Moneda],MATCH(A14,Tabla1[Identificador],0)) -> PEN | D14: {=_xll.BDP(A14, "DS213")} -> Common Stock | E14: =+_xll.BDP($A14,"Name") -> FERREYCORP SAA | F14: =SUMIFS( Tabla1[Q], Tabla1[Identificador],A14, Tabla1[Stock],"stock" ) -> 103492 | G14: {=SUMPRODUCT( (Tabla1[Identificador]=A14)* (Tabla1[Stock]="stock")* Tabla1[Q]* Tabla1[P] ) /SUMIFS( Tabla1[Q], Tabla1[Identificador],A14, Tabla1[Stock],"stock" )} -> 3.3176217 | H14: {=+_xll.BDP(A14,"PX_LAST")} -> 4.1 | I14: {=+_xll.BDP(A14,"PX_CLOSE_1D")} -> 4.05 | J14: =+F14*G14 -> 343347.3 | K14: =+H14*F14 -> 424317.2 | L14: =+I14*F14 -> 419142.6 | M14: =+IF(C14="USD",K14/SUMIF(C:C,C14,K:K),K14/SUMIF(C:C,C14,K:K)) -> 0.18032331 | N14: =+(H14*F14)/(F14*G14)-1 -> 0.23582507 | O14: {=+_xll.BDP(A14,"CURRENT_TRR_1D")/100} -> 0
... A49: EPU US Equity | B49: {=_xll.BDP(A49,"ID_ISIN")} -> US4642898427 | C49: =+INDEX(Tabla1[Moneda],MATCH(A49,Tabla1[Identificador],0)) -> USD | D49: {=_xll.BDP(A49, "DS213")} -> ETP | E49: =+_xll.BDP($A49,"Name") -> ISHARES MSCI PERU AND GLOBAL | F49: =SUMIFS( Tabla1[Q], Tabla1[Identificador],A49, Tabla1[Stock],"stock" ) -> 2369 | G49: {=SUMPRODUCT( (Tabla1[Identificador]=A49)* (Tabla1[Stock]="stock")* Tabla1[Q]* Tabla1[P] ) /SUMIFS( Tabla1[Q], Tabla1[Identificador],A49, Tabla1[Stock],"stock" )} -> 83.897751 | H49: {=+_xll.BDP(A49,"PX_LAST")} -> 86.87 | I49: {=+_xll.BDP(A49,"PX_CLOSE_1D")} -> 83.97 | J49: =+F49*G49 -> 198753.77 | K49: =+H49*F49 -> 205795.03 | L49: =+I49*F49 -> 198924.93 | M49: =+IF(C49="USD",K49/SUMIF(C:C,C49,K:K),K49/SUMIF(C:C,C49,K:K)) -> 0.033951666 | N49: =+(H49*F49)/(F49*G49)-1 -> 0.03542704 | O49: {=+_xll.BDP(A49,"CURRENT_TRR_1D")/100} -> 0

Sheet DATA
C2: FDX | D2: MINSURI1 | E2: SIDERC1 | F2: ORYGENC1 | G2: XPEV | H2: FERREYC1 | I2: TAN | J2: ITUB | K2: EWP | L2: EEM | M2: BAP | N2: EUFN | O2: EWZ | P2: ICLN | Q2: PFE | R2: BVN | S2: XLI | T2: EZU | U2: BIDU | V2: XLU | W2: PLTR | X2: EWL | Y2: EWQ | Z2: SMH | AA2: VOLCABC1 | AB2: INRETC1 | AC2: JAVA | AD2: SPY | AE2: CPACASC1 | AF2: JDOC | AG2: EWZS | AH2: QQQ | AI2: PRU | AJ2: DIS | AK2: XLY | AL2: AMZN | AM2: TQQQ | AN2: TCHI | AO2: CQQQ | AP2: AUNA | AQ2: KMB | AR2: CIB | AS2: NFLX | AT2: NIO | AU2: UNH | AV2: TTWO | AW2: KKR
B3: 45901 | C3: #N/A N/A | D3: 3.98 | E3: 1.76 | F3: 2.55 | G3: #N/A N/A | H3: 3.49 | I3: #N/A N/A | J3: #N/A N/A | K3: #N/A N/A | L3: #N/A N/A | M3: #N/A N/A | N3: #N/A N/A | O3: #N/A N/A | P3: #N/A N/A | Q3: #N/A N/A | R3: #N/A N/A | S3: #N/A N/A | T3: #N/A N/A | U3: #N/A N/A | V3: #N/A N/A | W3: #N/A N/A | X3: #N/A N/A | Y3: #N/A N/A | Z3: #N/A N/A | AA3: 0.376 | AB3: 27.5 | AC3: #N/A N/A | AD3: #N/A N/A | AE3: 4.61 | AF3: #N/A N/A | AG3: #N/A N/A | AH3: #N/A N/A | AI3: #N/A N/A | AJ3: #N/A N/A | AK3: #N/A N/A | AL3: #N/A N/A | AM3: #N/A N/A | AN3: #N/A N/A | AO3: #N/A N/A | AP3: #N/A N/A | AQ3: #N/A N/A | AR3: #N/A N/A | AS3: #N/A N/A | AT3: #N/A N/A | AU3: #N/A N/A | AV3: #N/A N/A | AW3: #N/A N/A
B4: 45902 | C4: 224.18 | D4: 3.99 | E4: 1.74 | F4: 2.55 | G4: 20.79 | H4: 3.47 | I4: 40.98 | J4: 6.8058 | K4: 47.02 | L4: 49.82 | M4: 260.11 | N4: 32.97 | O4: 29 | P4: 14.16 | Q4: 24.98 | R4: 19.64 | S4: 150.56 | T4: 59.035 | U4: 96.29 | V4: 42.02 | W4: 157.09 | X4: 54.67 | Y4: 42.29 | Z4: 286.48 | AA4: 0.384 | AB4: 27.94 | AC4: 67.81 | AD4: 640.27 | AE4: 4.73 | AF4: 51.593 | AG4: 13.1551 | AH4: 565.62 | AI4: 107.41 | AJ4: 118.27 | AK4: 115.005 | AL4: 225.34 | AM4: 43.54 | AN4: 23.51 | AO4: 52.31 | AP4: 6.33 | AQ4: 128.84 | AR4: 49.88 | AS4: 121.411 | AT4: 6.58 | AU4: 308.8 | AV4: 240.95 | AW4: 138.74
B5: 45903 | C5: 225.34 | D5: 4 | E5: 1.66 | F5: 2.56 | G5: 20.25 | H5: 3.48 | I5: 41.57 | J5: 6.7379 | K5: 47.05 | L5: 50.01 | M5: 261.56 | N5: 32.99 | O5: 28.99 | P5: 14.2 | Q5: 24.79 | R5: 19.94 | S5: 149.8 | T5: 59.15 | U5: 96.4 | V5: 41.915 | W5: 154.9 | X5: 55.08 | Y5: 42.54 | Z5: 286.43 | AA5: 0.4 | AB5: 27.9 | AC5: 67.64 | AD5: 643.74 | AE5: 4.73 | AF5: 51.6447 | AG5: 13.1886 | AH5: 570.07 | AI5: 107.43 | AJ5: 117.38 | AK5: 115.47 | AL5: 225.99 | AM5: 44.555 | AN5: 23.3932 | AO5: 51.79 | AP5: 6.34 | AQ5: 128 | AR5: 49.52 | AS5: 122.618 | AT5: 6.32 | AU5: 307.88 | AV5: 238.86 | AW5: 134.83
B6: 45904 | C6: 225.28 | D6: 4 | E6: #N/A N/A | F6: 2.54 | G6: 19.84 | H6: 3.48 | I6: 42.02 | J6: 6.7864 | K6: 47.48 | L6: 49.85 | M6: 259.98 | N6: 33.37 | O6: 29.17 | P6: 14.33 | Q6: 24.54 | R6: 19.82 | S6: 151.49 | T6: 59.48 | U6: 98.21 | V6: 41.865 | W6: 156.14 | X6: 55.71 | Y6: 42.56 | Z6: 289.86 | AA6: 0.4 | AB6: 27.5 | AC6: 68.25 | AD6: 649.12 | AE6: 4.75 | AF6: 51.7739 | AG6: 13.3765 | AH6: 575.23 | AI6: 108.84 | AJ6: 118.81 | AK6: 117.58 | AL6: 235.68 | AM6: 45.76 | AN6: 22.795 | AO6: 50.18 | AP6: 6.36 | AQ6: 129.17 | AR6: 50.54 | AS6: 125.748 | AT6: 6.13 | AU6: 310.38 | AV6: 240.65 | AW6: 137.35
B7: 45905 | C7: 227.72 | D7: 4 | E7: #N/A N/A | F7: 2.59 | G7: 19.83 | H7: 3.47 | I7: 44.04 | J7: 6.8932 | K7: 47.6 | L7: 50.45 | M7: 261.2 | N7: 33.31 | O7: 29.63 | P7: 14.68 | Q7: 24.88 | R7: 19.99 | S7: 150.93 | T7: 59.65 | U7: 101.96 | V7: 41.735 | W7: 153.11 | X7: 56.25 | Y7: 42.56 | Z7: 293.28 | AA7: 0.4 | AB7: 27.1 | AC7: 68.06 | AD7: 647.24 | AE7: 4.74 | AF7: 51.9817 | AG7: 13.7 | AH7: 576.06 | AI7: 105.71 | AJ7: 117.91 | AK7: 117.555 | AL7: 232.33 | AM7: 45.91 | AN7: 23.4718 | AO7: 51.68 | AP7: 6.36 | AQ7: 129.89 | AR7: 52.12 | AS7: 124.382 | AT7: 5.95 | AU7: 315.39 | AV7: 239.68 | AW7: 135.53
B8: 45906 | C8: #N/A N/A | D8: #N/A N/A | E8: #N/A N/A | F8: #N/A N/A | G8: #N/A N/A | H8: #N/A N/A | I8: #N/A N/A | J8: #N/A N/A | K8: #N/A N/A | L8: #N/A N/A | M8: #N/A N/A | N8: #N/A N/A | O8: #N/A N/A | P8: #N/A N/A | Q8: #N/A N/A | R8: #N/A N/A | S8: #N/A N/A | T8: #N/A N/A | U8: #N/A N/A | V8: #N/A N/A | W8: #N/A N/A | X8: #N/A N/A | Y8: #N/A N/A | Z8: #N/A N/A | AA8: #N/A N/A | AB8: #N/A N/A | AC8: #N/A N/A | AD8: #N/A N/A | AE8: #N/A N/A | AF8: #N/A N/A | AG8: #N/A N/A | AH8: #N/A N/A | AI8: #N/A N/A | AJ8: #N/A N/A | AK8: #N/A N/A | AL8: #N/A N/A | AM8: #N/A N/A | AN8: #N/A N/A | AO8: #N/A N/A | AP8: #N/A N/A | AQ8: #N/A N/A | AR8: #N/A N/A | AS8: #N/A N/A | AT8: #N/A N/A | AU8: #N/A N/A | AV8: #N/A N/A | AW8: #N/A N/A
B9: 45907 | C9: #N/A N/A | D9: #N/A N/A | E9: #N/A N/A | F9: #N/A N/A | G9: #N/A N/A | H9: #N/A N/A | I9: #N/A N/A | J9: #N/A N/A | K9: #N/A N/A | L9: #N/A N/A | M9: #N/A N/A | N9: #N/A N/A | O9: #N/A N/A | P9: #N/A N/A | Q9: #N/A N/A | R9: #N/A N/A | S9: #N/A N/A | T9: #N/A N/A | U9: #N/A N/A | V9: #N/A N/A | W9: #N/A N/A | X9: #N/A N/A | Y9: #N/A N/A | Z9: #N/A N/A | AA9: #N/A N/A | AB9: #N/A N/A | AC9: #N/A N/A | AD9: #N/A N/A | AE9: #N/A N/A | AF9: #N/A N/A | AG9: #N/A N/A | AH9: #N/A N/A | AI9: #N/A N/A | AJ9: #N/A N/A | AK9: #N/A N/A | AL9: #N/A N/A | AM9: #N/A N/A | AN9: #N/A N/A | AO9: #N/A N/A | AP9: #N/A N/A | AQ9: #N/A N/A | AR9: #N/A N/A | AS9: #N/A N/A | AT9: #N/A N/A | AU9: #N/A N/A | AV9: #N/A N/A | AW9: #N/A N/A
B10: 45908 | C10: 225 | D10: 4 | E10: #N/A N/A | F10: 2.54 | G10: 20.58 | H10: 3.48 | I10: 43.33 | J10: 6.8447 | K10: 48.07 | L10: 50.91 | M10: 263.5 | N10: 33.55 | O10: 29.58 | P10: 14.57 | Q10: 24.55 | R10: 20.02 | S10: 151.27 | T10: 60.21 | U10: 108.65 | V10: 41.31 | W10: 156.1 | X10: 56.33 | Y10: 42.99 | Z10: 296.52 | AA10: 0.383 | AB10: 27.5 | AC10: 68.05 | AD10: 648.83 | AE10: 4.73 | AF10: 52.0234 | AG10: 13.57 | AH10: 578.87 | AI10: 105.84 | AJ10: 118.84 | AK10: 118.01 | AL10: 235.84 | AM10: 46.565 | AN10: 23.7952 | AO10: 52.16 | AP10: 6.35 | AQ10: 129.78 | AR10: 52.34 | AS10: 124.476 | AT10: 6.17 | AU10: 320.25 | AV10: 248.78 | AW10: 138.69
B11: 45909 | C11: 225.75 | D11: 3.99 | E11: 1.75 | F11: 2.54 | G11: 20.75 | H11: 3.46 | I11: 41.97 | J11: 6.7864 | K11: 48.08 | L11: 51.19 | M11: 263.92 | N11: 33.57 | O11: 29.54 | P11: 14.39 | Q11: 24.71 | R11: 19.6 | S11: 150.25 | T11: 60.21 | U11: 108.47 | V11: 41.595 | W11: 162.36 | X11: 56.02 | Y11: 43.06 | Z11: 297.81 | AA11: 0.375 | AB11: 27.5 | AC11: 68.08 | AD11: 650.33 | AE11: 4.7 | AF11: 52.1809 | AG11: 13.49 | AH11: 580.51 | AI11: 105.54 | AJ11: 117.37 | AK11: 117.845 | AL11: 238.24 | AM11: 46.945 | AN11: 23.8 | AO11: 52.13 | AP11: 6.36 | AQ11: 130.97 | AR11: 53.29 | AS11: 126.325 | AT11: 6.28 | AU11: 347.92 | AV11: 247.86 | AW11: 137.39
B12: 45910 | C12: 225.69 | D12: 3.99 | E12: 1.77 | F12: 2.59 | G12: 20.1 | H12: 3.45 | I12: 41.91 | J12: 6.835 | K12: 48.47 | L12: 51.54 | M12: 264.18 | N12: 33.71 | O12: 29.79 | P12: 14.555 | Q12: 24.57 | R12: 20.04 | S12: 151.36 | T12: 59.95 | U12: 107.6 | V12: 42.31 | W12: 166.74 | X12: 55.62 | Y12: 42.9 | Z12: 300.83 | AA12: 0.392 | AB12: 27.45 | AC12: 68.11 | AD12: 652.21 | AE12: 4.65 | AF12: 51.6893 | AG12: 13.5454 | AH12: 580.7 | AI12: 105.67 | AJ12: 115.79 | AK12: 116.435 | AL12: 230.33 | AM12: 46.995 | AN12: 23.86 | AO12: 52.24 | AP12: 6.35 | AQ12: 128.01 | AR12: 53.59 | AS12: 124.771 | AT12: 5.72 | AU12: 346.78 | AV12: 244.04 | AW12: 139.29
B13: 45911 | C13: 228.81 | D13: 4.01 | E13: #N/A N/A | F13: 2.57 | G13: 20.58 | H13: 3.45 | I13: 41.86 | J13: 6.8738 | K13: 48.98 | L13: 52.29 | M13: 266.59 | N13: 34.1 | O13: 30.05 | P13: 14.69 | Q13: 24.86 | R13: 20.18 | S13: 152.8 | T13: 60.63 | U13: 111.82 | V13: 42.535 | W13: 164.36 | X13: 56.12 | Y13: 43.53 | Z13: 303.93 | AA13: 0.397 | AB13: 27.5 | AC13: 69.05 | AD13: 657.63 | AE13: 4.65 | AF13: 52.3269 | AG13: 13.73 | AH13: 584.08 | AI13: 106.99 | AJ13: 117.08 | AK13: 118.7 | AL13: 229.95 | AM13: 47.785 | AN13: 24.9417 | AO13: 54.65 | AP13: 6.37 | AQ13: 129.47 | AR13: 52.35 | AS13: 120.35 | AT13: 6.07 | AU13: 353.61 | AV13: 246.54 | AW13: 145.01
B14: 45912 | C14: 229.55 | D14: 4.01 | E14: 1.76 | F14: 2.57 | G14: 20.87 | H14: 3.37 | I14: 41.78 | J14: 6.767 | K14: 49 | L14: 52.26 | M14: 266.06 | N14: 34.1 | O14: 30.03 | P14: 14.63 | Q14: 23.87 | R14: 20.07 | S14: 151.58 | T14: 60.59 | U14: 114.78 | V14: 42.75 | W14: 171.43 | X14: 55.65 | Y14: 43.49 | Z14: 304.32 | AA14: 0.42 | AB14: 27.5 | AC14: 68.68 | AD14: 657.41 | AE14: 4.71 | AF14: 51.7648 | AG14: 13.78 | AH14: 586.66 | AI14: 106.9 | AJ14: 115.96 | AK14: 119.315 | AL14: 228.15 | AM14: 48.38 | AN14: 24.87 | AO14: 54.69 | AP14: 6.33 | AQ14: 127.99 | AR14: 51.87 | AS14: 118.844 | AT14: 6.22 | AU14: 352.51 | AV14: 246.26 | AW14: 143.34
B15: 45913 | C15: #N/A N/A | D15: #N/A N/A | E15: #N/A N/A | F15: #N/A N/A | G15: #N/A N/A | H15: #N/A N/A | I15: #N/A N/A | J15: #N/A N/A | K15: #N/A N/A | L15: #N/A N/A | M15: #N/A N/A | N15: #N/A N/A | O15: #N/A N/A | P15: #N/A N/A | Q15: #N/A N/A | R15: #N/A N/A | S15: #N/A N/A | T15: #N/A N/A | U15: #N/A N/A | V15: #N/A N/A | W15: #N/A N/A | X15: #N/A N/A | Y15: #N/A N/A | Z15: #N/A N/A | AA15: #N/A N/A | AB15: #N/A N/A | AC15: #N/A N/A | AD15: #N/A N/A | AE15: #N/A N/A | AF15: #N/A N/A | AG15: #N/A N/A | AH15: #N/A N/A | AI15: #N/A N/A | AJ15: #N/A N/A | AK15: #N/A N/A | AL15: #N/A N/A | AM15: #N/A N/A | AN15: #N/A N/A | AO15: #N/A N/A | AP15: #N/A N/A | AQ15: #N/A N/A | AR15: #N/A N/A | AS15: #N/A N/A | AT15: #N/A N/A | AU15: #N/A N/A | AV15: #N/A N/A | AW15: #N/A N/A
B16: 45914 | C16: #N/A N/A | D16: #N/A N/A | E16: #N/A N/A | F16: #N/A N/A | G16: #N/A N/A | H16: #N/A N/A | I16: #N/A N/A | J16: #N/A N/A | K16: #N/A N/A | L16: #N/A N/A | M16: #N/A N/A | N16: #N/A N/A | O16: #N/A N/A | P16: #N/A N/A | Q16: #N/A N/A | R16: #N/A N/A | S16: #N/A N/A | T16: #N/A N/A | U16: #N/A N/A | V16: #N/A N/A | W16: #N/A N/A | X16: #N/A N/A | Y16: #N/A N/A | Z16: #N/A N/A | AA16: #N/A N/A | AB16: #N/A N/A | AC16: #N/A N/A | AD16: #N/A N/A | AE16: #N/A N/A | AF16: #N/A N/A | AG16: #N/A N/A | AH16: #N/A N/A | AI16: #N/A N/A | AJ16: #N/A N/A | AK16: #N/A N/A | AL16: #N/A N/A | AM16: #N/A N/A | AN16: #N/A N/A | AO16: #N/A N/A | AP16: #N/A N/A | AQ16: #N/A N/A | AR16: #N/A N/A | AS16: #N/A N/A | AT16: #N/A N/A | AU16: #N/A N/A | AV16: #N/A N/A | AW16: #N/A N/A
B17: 45915 | C17: 225.69 | D17: 4.01 | E17: 1.76 | F17: 2.55 | G17: 21.33 | H17: 3.34 | I17: 42.35 | J17: 6.932 | K17: 49.23 | L17: 52.64 | M17: 265.64 | N17: 34.43 | O17: 30.51 | P17: 14.81 | Q17: 23.97 | R17: 20.65 | S17: 152.28 | T17: 61.17 | U17: 114.82 | V17: 42.85 | W17: 171.21 | X17: 55.56 | Y17: 43.89 | Z17: 307.17 | AA17: 0.411 | AB17: 27.39 | AC17: 68.72 | AD17: 660.91 | AE17: 4.73 | AF17: 51.349 | AG17: 13.98 | AH17: 591.68 | AI17: 105.45 | AJ17: 115.62 | AK17: 120.35 | AL17: 231.43 | AM17: 49.615 | AN17: 25.04 | AO17: 55 | AP17: 6.37 | AQ17: 125.47 | AR17: 51.79 | AS17: 120.226 | AT17: 6.49 | AU17: 347.89 | AV17: 247.25 | AW17: 144.65
B18: 45916 | C18: 227.7 | D18: 4.01 | E18: #N/A N/A | F18: 2.53 | G18: 21.45 | H18: 3.36 | I18: 42.67 | J18: 6.932 | K18: 48.95 | L18: 53.03 | M18: 270.79 | N18: 34.04 | O18: 30.69 | P18: 14.89 | Q18: 23.9 | R18: 20.11 | S18: 151.83 | T18: 61.01 | U18: 123.79 | V18: 42.07 | W18: 170.26 | X18: 55.48 | Y18: 43.82 | Z18: 307.21 | AA18: 0.416 | AB18: 27.39 | AC18: 68.53 | AD18: 660 | AE18: 4.75 | AF18: 51.3441 | AG18: 14.14 | AH18: 591.18 | AI18: 102.15 | AJ18: 115.23 | AK18: 121.09 | AL18: 234.05 | AM18: 49.48 | AN18: 25.36 | AO18: 55.96 | AP18: 6.36 | AQ18: 125.04 | AR18: 51.72 | AS18: 120.051 | AT18: 7.02 | AU18: 339.78 | AV18: 247.73 | AW18: 144.38
B19: 45917 | C19: 225.78 | D19: 4.03 | E19: 1.76 | F19: 2.55 | G19: 21.6 | H19: 3.36 | I19: 42.86 | J19: 7.0583 | K19: 48.75 | L19: 53.26 | M19: 278.29 | N19: 33.97 | O19: 30.94 | P19: 15.06 | Q19: 24.05 | R19: 19.82 | S19: 151.14 | T19: 60.69 | U19: 137.83 | V19: 42.175 | W19: 168.33 | X19: 55.29 | Y19: 43.53 | Z19: 305.25 | AA19: 0.412 | AB19: 27.3 | AC19: 68.74 | AD19: 659.18 | AE19: 4.74 | AF19: 51.3708 | AG19: 14.27 | AH19: 590 | AI19: 103.01 | AJ19: 116.1 | AK19: 120.785 | AL19: 231.62 | AM19: 49.165 | AN19: 26.055 | AO19: 57.67 | AP19: 6.35 | AQ19: 125.59 | AR19: 52.03 | AS19: 122.85 | AT19: 7.45 | AU19: 341.61 | AV19: 250.52 | AW19: 144.4
B20: 45918 | C20: 226.5 | D20: 4 | E20: #N/A N/A | F20: 2.55 | G20: 21.29 | H20: 3.34 | I20: 42.81 | J20: 7.0194 | K20: 48.66 | L20: 53.13 | M20: 261.91 | N20: 34.01 | O20: 30.82 | P20: 15.04 | Q20: 24.15 | R20: 20.02 | S20: 152.75 | T20: 61.18 | U20: 135.25 | V20: 42.205 | W20: 176.97 | X20: 55.21 | Y20: 43.84 | Z20: 316.97 | AA20: 0.401 | AB20: 26.9 | AC20: 69 | AD20: 662.26 | AE20: 4.72 | AF20: 51.5728 | AG20: 14.2 | AH20: 595.32 | AI20: 103.87 | AJ20: 114.86 | AK20: 120.24 | AL20: 231.23 | AM20: 50.49 | AN20: 25.8 | AO20: 57.39 | AP20: 6.345 | AQ20: 125.51 | AR20: 51.56 | AS20: 120.778 | AT20: 7.37 | AU20: 334.82 | AV20: 249.74 | AW20: 149.34
B21: 45919 | C21: 231.75 | D21: 3.99 | E21: #N/A N/A | F21: 2.5 | G21: 21.66 | H21: 3.37 | I21: 43.17 | J21: 7.1165 | K21: 48.83 | L21: 53.01 | M21: 262.61 | N21: 33.97 | O21: 30.93 | P21: 15.17 | Q21: 24.03 | R21: 20.91 | S21: 153.12 | T21: 61.05 | U21: 135.35 | V21: 42.475 | W21: 182.39 | X21: 55.26 | Y21: 43.68 | Z21: 315.71 | AA21: 0.418 | AB21: 26.85 | AC21: 68.81 | AD21: 663.7 | AE21: 4.73 | AF21: 51.4212 | AG21: 14.19 | AH21: 599.35 | AI21: 103.59 | AJ21: 113.76 | AK21: 120.695 | AL21: 231.48 | AM21: 51.49 | AN21: 25.6 | AO21: 56.86 | AP21: 6.45 | AQ21: 124.62 | AR21: 51.88 | AS21: 122.697 | AT21: 7.37 | AU21: 336.69 | AV21: 250.85 | AW21: 148.92
B22: 45920 | C22: #N/A N/A | D22: #N/A N/A | E22: #N/A N/A | F22: #N/A N/A | G22: #N/A N/A | H22: #N/A N/A | I22: #N/A N/A | J22: #N/A N/A | K22: #N/A N/A | L22: #N/A N/A | M22: #N/A N/A | N22: #N/A N/A | O22: #N/A N/A | P22: #N/A N/A | Q22: #N/A N/A | R22: #N/A N/A | S22: #N/A N/A | T22: #N/A N/A | U22: #N/A N/A | V22: #N/A N/A | W22: #N/A N/A | X22: #N/A N/A | Y22: #N/A N/A | Z22: #N/A N/A | AA22: #N/A N/A | AB22: #N/A N/A | AC22: #N/A N/A | AD22: #N/A N/A | AE22: #N/A N/A | AF22: #N/A N/A | AG22: #N/A N/A | AH22: #N/A N/A | AI22: #N/A N/A | AJ22: #N/A N/A | AK22: #N/A N/A | AL22: #N/A N/A | AM22: #N/A N/A | AN22: #N/A N/A | AO22: #N/A N/A | AP22: #N/A N/A | AQ22: #N/A N/A | AR22: #N/A N/A | AS22: #N/A N/A | AT22: #N/A N/A | AU22: #N/A N/A | AV22: #N/A N/A | AW22: #N/A N/A
B23: 45921 | C23: #N/A N/A | D23: #N/A N/A | E23: #N/A N/A | F23: #N/A N/A | G23: #N/A N/A | H23: #N/A N/A | I23: #N/A N/A | J23: #N/A N/A | K23: #N/A N/A | L23: #N/A N/A | M23: #N/A N/A | N23: #N/A N/A | O23: #N/A N/A | P23: #N/A N/A | Q23: #N/A N/A | R23: #N/A N/A | S23: #N/A N/A | T23: #N/A N/A | U23: #N/A N/A | V23: #N/A N/A | W23: #N/A N/A | X23: #N/A N/A | Y23: #N/A N/A | Z23: #N/A N/A | AA23: #N/A N/A | AB23: #N/A N/A | AC23: #N/A N/A | AD23: #N/A N/A | AE23: #N/A N/A | AF23: #N/A N/A | AG23: #N/A N/A | AH23: #N/A N/A | AI23: #N/A N/A | AJ23: #N/A N/A | AK23: #N/A N/A | AL23: #N/A N/A | AM23: #N/A N/A | AN23: #N/A N/A | AO23: #N/A N/A | AP23: #N/A N/A | AQ23: #N/A N/A | AR23: #N/A N/A | AS23: #N/A N/A | AT23: #N/A N/A | AU23: #N/A N/A | AV23: #N/A N/A | AW23: #N/A N/A
B24: 45922 | C24: 230.12 | D24: 4 | E24: #N/A N/A | F24: 2.5 | G24: 21.36 | H24: 3.37 | I24: 43.89 | J24: 7.0291 | K24: 48.43 | L24: 53.27 | M24: 266.77 | N24: 34.04 | O24: 30.79 | P24: 15.36 | Q24: 24.04 | R24: 21.53 | S24: 153 | T24: 61.18 | U24: 136.63 | V24: 42.6 | W24: 179.33 | X24: 55.57 | Y24: 43.78 | Z24: 322.17 | AA24: 0.44 | AB24: 26.8 | AC24: 68.83 | AD24: 666.84 | AE24: 4.73 | AF24: 51.6088 | AG24: 13.96 | AH24: 602.2 | AI24: 102.85 | AJ24: 112.56 | AK24: 120.09 | AL24: 227.63 | AM24: 52.36 | AN24: 25.97 | AO24: 57.84 | AP24: 6.39 | AQ24: 124.07 | AR24: 52.51 | AS24: 122.737 | AT24: 6.91 | AU24: 341.3 | AV24: 251.64 | AW24: 146.95
B25: 45923 | C25: 233.7 | D25: 4 | E25: 1.77 | F25: 2.49 | G25: 21.19 | H25: 3.36 | I25: 42.37 | J25: 7.1942 | K25: 48.55 | L25: 53.3 | M25: 265.55 | N25: 34.01 | O25: 31.32 | P25: 15.19 | Q25: 24.13 | R25: 22.05 | S25: 153.04 | T25: 61.33 | U25: 125.57 | V25: 42.82 | W25: 182.55 | X25: 55.24 | Y25: 43.89 | Z25: 321.7 | AA25: 0.455 | AB25: 26.71 | AC25: 68.62 | AD25: 663.21 | AE25: 4.73 | AF25: 51.4841 | AG25: 14.18 | AH25: 598.2 | AI25: 103.13 | AJ25: 112.25 | AK25: 118.96 | AL25: 220.71 | AM25: 51.305 | AN25: 25.5 | AO25: 56.28 | AP25: 6.46 | AQ25: 123.82 | AR25: 52.58 | AS25: 121.847 | AT25: 6.93 | AU25: 347.69 | AV25: 251.28 | AW25: 147.25
B26: 45924 | C26: 233.75 | D26: 4.01 | E26: #N/A N/A | F26: 2.5 | G26: 21.27 | H26: 3.37 | I26: 43.35 | J26: 7.0777 | K26: 48.57 | L26: 53.12 | M26: 266.11 | N26: 33.83 | O26: 31.05 | P26: 15.14 | Q26: 24.09 | R26: 22.86 | S26: 152.25 | T26: 61.02 | U26: 132.92 | V26: 43.125 | W26: 179.56 | X26: 54.51 | Y26: 43.41 | Z26: 321.11 | AA26: 0.45 | AB26: 26.5 | AC26: 68.42 | AD26: 661.1 | AE26: 4.72 | AF26: 51.2638 | AG26: 14.04 | AH26: 596.1 | AI26: 103.32 | AJ26: 113.43 | AK26: 119.8 | AL26: 220.21 | AM26: 50.705 | AN26: 26.08 | AO26: 57.63 | AP26: 6.63 | AQ26: 123.93 | AR26: 52.46 | AS26: 120.395 | AT26: 7.12 | AU26: 351.81 | AV26: 244.12 | AW26: 137.94
B27: 45925 | C27: 236.42 | D27: 4.02 | E27: 1.75 | F27: 2.5 | G27: 22.25 | H27: 3.35 | I27: 43.71 | J27: 6.9903 | K27: 48.25 | L27: 52.81 | M27: 262.74 | N27: 33.56 | O27: 30.58 | P27: 15.16 | Q27: 23.6 | R27: 22.92 | S27: 151.22 | T27: 60.54 | U27: 135.4 | V27: 42.71 | W27: 179.12 | X27: 53.86 | Y27: 43.05 | Z27: 321.06 | AA27: 0.438 | AB27: 26.44 | AC27: 68.07 | AD27: 658.05 | AE27: 4.7 | AF27: 50.3972 | AG27: 13.745 | AH27: 593.53 | AI27: 102.62 | AJ27: 112.99 | AK27: 118.11 | AL27: 218.15 | AM27: 50.025 | AN27: 26.35 | AO27: 58.24 | AP27: 6.71 | AQ27: 121.72 | AR27: 52.44 | AS27: 120.824 | AT27: 7.47 | AU27: 345.56 | AV27: 245.11 | AW27: 135.66
B28: 45926 | C28: 237.82 | D28: 4.01 | E28: 1.77 | F28: 2.48 | G28: 22.79 | H28: 3.32 | I28: 43.42 | J28: 7.0291 | K28: 49.04 | L28: 52.71 | M28: 263.66 | N28: 34.14 | O28: 30.73 | P28: 15.21 | Q28: 23.76 | R28: 23.24 | S28: 152.58 | T28: 61.28 | U28: 131.34 | V28: 43.405 | W28: 177.57 | X28: 54.26 | Y28: 43.59 | Z28: 321.82 | AA28: 0.457 | AB28: 26.27 | AC28: 68.56 | AD28: 661.82 | AE28: 4.73 | AF28: 50.9384 | AG28: 13.8654 | AH28: 595.97 | AI28: 104.41 | AJ28: 113.47 | AK28: 119.855 | AL28: 219.78 | AM28: 50.625 | AN28: 25.7407 | AO28: 57.1 | AP28: 6.66 | AQ28: 122.23 | AR28: 51.93 | AS28: 121.061 | AT28: 7.04 | AU28: 344.08 | AV28: 256.12 | AW28: 134.01
B29: 45927 | C29: #N/A N/A | D29: #N/A N/A | E29: #N/A N/A | F29: #N/A N/A | G29: #N/A N/A | H29: #N/A N/A | I29: #N/A N/A | J29: #N/A N/A | K29: #N/A N/A | L29: #N/A N/A | M29: #N/A N/A | N29: #N/A N/A | O29: #N/A N/A | P29: #N/A N/A | Q29: #N/A N/A | R29: #N/A N/A | S29: #N/A N/A | T29: #N/A N/A | U29: #N/A N/A | V29: #N/A N/A | W29: #N/A N/A | X29: #N/A N/A | Y29: #N/A N/A | Z29: #N/A N/A | AA29: #N/A N/A | AB29: #N/A N/A | AC29: #N/A N/A | AD29: #N/A N/A | AE29: #N/A N/A | AF29: #N/A N/A | AG29: #N/A N/A | AH29: #N/A N/A | AI29: #N/A N/A | AJ29: #N/A N/A | AK29: #N/A N/A | AL29: #N/A N/A | AM29: #N/A N/A | AN29: #N/A N/A | AO29: #N/A N/A | AP29: #N/A N/A | AQ29: #N/A N/A | AR29: #N/A N/A | AS29: #N/A N/A | AT29: #N/A N/A | AU29: #N/A N/A | AV29: #N/A N/A | AW29: #N/A N/A
B30: 45928 | C30: #N/A N/A | D30: #N/A N/A | E30: #N/A N/A | F30: #N/A N/A | G30: #N/A N/A | H30: #N/A N/A | I30: #N/A N/A | J30: #N/A N/A | K30: #N/A N/A | L30: #N/A N/A | M30: #N/A N/A | N30: #N/A N/A | O30: #N/A N/A | P30: #N/A N/A | Q30: #N/A N/A | R30: #N/A N/A | S30: #N/A N/A | T30: #N/A N/A | U30: #N/A N/A | V30: #N/A N/A | W30: #N/A N/A | X30: #N/A N/A | Y30: #N/A N/A | Z30: #N/A N/A | AA30: #N/A N/A | AB30: #N/A N/A | AC30: #N/A N/A | AD30: #N/A N/A | AE30: #N/A N/A | AF30: #N/A N/A | AG30: #N/A N/A | AH30: #N/A N/A | AI30: #N/A N/A | AJ30: #N/A N/A | AK30: #N/A N/A | AL30: #N/A N/A | AM30: #N/A N/A | AN30: #N/A N/A | AO30: #N/A N/A | AP30: #N/A N/A | AQ30: #N/A N/A | AR30: #N/A N/A | AS30: #N/A N/A | AT30: #N/A N/A | AU30: #N/A N/A | AV30: #N/A N/A | AW30: #N/A N/A
B31: 45929 | C31: 236.58 | D31: 4.02 | E31: 1.77 | F31: 2.5 | G31: 23.19 | H31: 3.35 | I31: 43.82 | J31: 7.1165 | K31: 48.92 | L31: 53.19 | M31: 267.47 | N31: 34.16 | O31: 30.99 | P31: 15.41 | Q31: 23.85 | R31: 24.33 | S31: 153.05 | T31: 61.52 | U31: 134.86 | V31: 43.53 | W31: 178.86 | X31: 54.57 | Y31: 43.78 | Z31: 322.66 | AA31: 0.472 | AB31: 26 | AC31: 68.76 | AD31: 663.68 | AE31: 4.72 | AF31: 51.2522 | AG31: 13.985 | AH31: 598.73 | AI31: 103.83 | AJ31: 114.78 | AK31: 120.38 | AL31: 222.17 | AM31: 51.3 | AN31: 26.34 | AO31: 58.2 | AP31: 6.7 | AQ31: 122.66 | AR31: 51.56 | AS31: 120.641 | AT31: 7.21 | AU31: 345.18 | AV31: 259.96 | AW31: 134.48
B32: 45930 | C32: 235.81 | D32: 4.01 | E32: 1.77 | F32: 2.49 | G32: 23.42 | H32: 3.31 | I32: 43.63 | J32: 7.1262 | K32: 49.5 | L32: 53.4 | M32: 266.28 | N32: 34.34 | O32: 31 | P32: 15.48 | Q32: 25.48 | R32: 24.33 | S32: 154.23 | T32: 61.94 | U32: 131.77 | V32: 43.605 | W32: 182.42 | X32: 55.24 | Y32: 43.93 | Z32: 326.36 | AA32: 0.48 | AB32: 26 | AC32: 68.96 | AD32: 666.18 | AE32: 4.73 | AF32: 52.4147 | AG32: 13.9 | AH32: 600.37 | AI32: 103.74 | AJ32: 114.5 | AK32: 119.82 | AL32: 219.57 | AM32: 51.7 | AN32: 26.5512 | AO32: 59.01 | AP32: 6.72 | AQ32: 124.34 | AR32: 51.94 | AS32: 119.892 | AT32: 7.62 | AU32: 345.3 | AV32: 258.36 | AW32: 129.95
B33: 45931 | C33: 239.55 | D33: 4.03 | E33: 1.8 | F33: 2.49 | G33: 23.7 | H33: 3.33 | I33: 45.08 | J33: 6.9806 | K33: 49.64 | L33: 53.82 | M33: 262.2 | N33: 34.44 | O33: 30.58 | P33: 15.88 | Q33: 27.21 | R33: 24.65 | S33: 153.8 | T33: 62.63 | U33: 137.44 | V33: 44.025 | W33: 184.95 | X33: 55.94 | Y33: 44.49 | Z33: 333.69 | AA33: 0.5 | AB33: 25.6 | AC33: 69.14 | AD33: 668.45 | AE33: 4.72 | AF33: 53.985 | AG33: 13.7849 | AH33: 603.25 | AI33: 102.99 | AJ33: 112.95 | AK33: 120.57 | AL33: 220.63 | AM33: 52.43 | AN33: 26.7565 | AO33: 59.71 | AP33: 6.75 | AQ33: 123.23 | AR33: 52.02 | AS33: 117.09 | AT33: 7.65 | AU33: 348.3 | AV33: 255.4 | AW33: 127.47
B34: 45932 | C34: 242.32 | D34: 4 | E34: 1.78 | F34: 2.49 | G34: 23.81 | H34: 3.33 | I34: 46.18 | J34: 6.9126 | K34: 49.36 | L34: 54.07 | M34: 259.09 | N34: 34.31 | O34: 30.24 | P34: 15.89 | Q34: 27.08 | R34: 24.93 | S34: 154.2 | T34: 63 | U34: 140.23 | V34: 43.945 | W34: 187.05 | X34: 56.25 | Y34: 44.77 | Z34: 338.24 | AA34: 0.498 | AB34: 25.5 | AC34: 69.09 | AD34: 669.22 | AE34: 4.72 | AF34: 53.8388 | AG34: 13.625 | AH34: 605.73 | AI34: 101.94 | AJ34: 112.14 | AK34: 119.7 | AL34: 222.41 | AM34: 53.07 | AN34: 27.27 | AO34: 60.41 | AP34: 6.75 | AQ34: 122.62 | AR34: 51.36 | AS34: 116.253 | AT34: 7.89 | AU34: 353.72 | AV34: 256.94 | AW34: 124.63
B35: 45933 | C35: 244.61 | D35: 3.99 | E35: 1.8 | F35: 2.48 | G35: 23.07 | H35: 3.34 | I35: 45.98 | J35: 6.9612 | K35: 49.65 | L35: 54.23 | M35: 266.19 | N35: 34.54 | O35: 30.33 | P35: 15.98 | Q35: 27.37 | R35: 24.49 | S35: 154.41 | T35: 63.11 | U35: 142 | V35: 44.455 | W35: 173.07 | X35: 56.66 | Y35: 44.91 | Z35: 336.68 | AA35: 0.51 | AB35: 25.5 | AC35: 69.46 | AD35: 669.21 | AE35: 4.72 | AF35: 54.4453 | AG35: 13.655 | AH35: 603.18 | AI35: 104.02 | AJ35: 112.47 | AK35: 118.93 | AL35: 219.51 | AM35: 52.35 | AN35: 27.0613 | AO35: 60.24 | AP35: 6.77 | AQ35: 122.58 | AR35: 52.17 | AS35: 115.332 | AT35: 7.7 | AU35: 360.2 | AV35: 257.68 | AW35: 127.65
B36: 45934 | C36: #N/A N/A | D36: #N/A N/A | E36: #N/A N/A | F36: #N/A N/A | G36: #N/A N/A | H36: #N/A N/A | I36: #N/A N/A | J36: #N/A N/A | K36: #N/A N/A | L36: #N/A N/A | M36: #N/A N/A | N36: #N/A N/A | O36: #N/A N/A | P36: #N/A N/A | Q36: #N/A N/A | R36: #N/A N/A | S36: #N/A N/A | T36: #N/A N/A | U36: #N/A N/A | V36: #N/A N/A | W36: #N/A N/A | X36: #N/A N/A | Y36: #N/A N/A | Z36: #N/A N/A | AA36: #N/A N/A | AB36: #N/A N/A | AC36: #N/A N/A | AD36: #N/A N/A | AE36: #N/A N/A | AF36: #N/A N/A | AG36: #N/A N/A | AH36: #N/A N/A | AI36: #N/A N/A | AJ36: #N/A N/A | AK36: #N/A N/A | AL36: #N/A N/A | AM36: #N/A N/A | AN36: #N/A N/A | AO36: #N/A N/A | AP36: #N/A N/A | AQ36: #N/A N/A | AR36: #N/A N/A | AS36: #N/A N/A | AT36: #N/A N/A | AU36: #N/A N/A | AV36: #N/A N/A | AW36: #N/A N/A
B37: 45935 | C37: #N/A N/A | D37: #N/A N/A | E37: #N/A N/A | F37: #N/A N/A | G37: #N/A N/A | H37: #N/A N/A | I37: #N/A N/A | J37: #N/A N/A | K37: #N/A N/A | L37: #N/A N/A | M37: #N/A N/A | N37: #N/A N/A | O37: #N/A N/A | P37: #N/A N/A | Q37: #N/A N/A | R37: #N/A N/A | S37: #N/A N/A | T37: #N/A N/A | U37: #N/A N/A | V37: #N/A N/A | W37: #N/A N/A | X37: #N/A N/A | Y37: #N/A N/A | Z37: #N/A N/A | AA37: #N/A N/A | AB37: #N/A N/A | AC37: #N/A N/A | AD37: #N/A N/A | AE37: #N/A N/A | AF37: #N/A N/A | AG37: #N/A N/A | AH37: #N/A N/A | AI37: #N/A N/A | AJ37: #N/A N/A | AK37: #N/A N/A | AL37: #N/A N/A | AM37: #N/A N/A | AN37: #N/A N/A | AO37: #N/A N/A | AP37: #N/A N/A | AQ37: #N/A N/A | AR37: #N/A N/A | AS37: #N/A N/A | AT37: #N/A N/A | AU37: #N/A N/A | AV37: #N/A N/A | AW37: #N/A N/A
B38: 45936 | C38: 247.03 | D38: 4.15 | E38: 1.78 | F38: 2.47 | G38: 23.63 | H38: 3.33 | I38: 46.24 | J38: 6.9223 | K38: 49.22 | L38: 54.48 | M38: 264.69 | N38: 34.3 | O38: 30.31 | P38: 16.08 | Q38: 26.43 | R38: 24.79 | S38: 155.13 | T38: 62.74 | U38: 144.91 | V38: 44.885 | W38: 179.53 | X38: 56.72 | Y38: 44.19 | Z38: 343.38 | AA38: 0.52 | AB38: 25.99 | AC38: 69.43 | AD38: 671.61 | AE38: 4.72 | AF38: 54.2478 | AG38: 13.59 | AH38: 607.71 | AI38: 103.22 | AJ38: 112.75 | AK38: 119.95 | AL38: 220.9 | AM38: 53.52 | AN38: 27.05 | AO38: 60.47 | AP38: 6.75 | AQ38: 120.54 | AR38: 52.16 | AS38: 116.331 | AT38: 7.59 | AU38: 358.77 | AV38: 256.98 | AW38: 126.87
B39: 45937 | C39: 242.33 | D39: 4.35 | E39: 1.78 | F39: 2.42 | G39: 23.67 | H39: 3.33 | I39: 45.68 | J39: 6.7379 | K39: 48.92 | L39: 54.06 | M39: 262.62 | N39: 33.99 | O39: 29.68 | P39: 15.89 | Q39: 26.27 | R39: 24.44 | S39: 154.25 | T39: 62.12 | U39: 138.94 | V39: 45.09 | W39: 182.17 | X39: 56.55 | Y39: 43.79 | Z39: 337.05 | AA39: 0.494 | AB39: 26.5 | AC39: 69.08 | AD39: 669.12 | AE39: 4.72 | AF39: 54.205 | AG39: 13.245 | AH39: 604.51 | AI39: 103.71 | AJ39: 112.53 | AK39: 117.85 | AL39: 221.78 | AM39: 52.655 | AN39: 26.68 | AO39: 59.65 | AP39: 6.61 | AQ39: 122.33 | AR39: 51.99 | AS39: 119.106 | AT39: 7.5 | AU39: 363.66 | AV39: 260.5 | AW39: 124.72
B40: 45938 | C40: 239.93 | D40: #N/A N/A | E40: #N/A N/A | F40: #N/A N/A | G40: 24.19 | H40: #N/A N/A | I40: 46.14 | J40: 6.7573 | K40: 49.33 | L40: 54.49 | M40: 264.5 | N40: 34.29 | O40: 29.87 | P40: 16.01 | Q40: 25.68 | R40: 26.26 | S40: 155.59 | T40: 62.52 | U40: 137.9 | V40: 45.4 | W40: 183.56 | X40: 56.83 | Y40: 44.3 | Z40: 346.07 | AA40: #N/A N/A | AB40: #N/A N/A | AC40: 69.2 | AD40: 673.11 | AE40: #N/A N/A | AF40: 54.2993 | AG40: 13.3239 | AH40: 611.44 | AI40: 102.89 | AJ40: 111.89 | AK40: 118.2 | AL40: 225.22 | AM40: 54.44 | AN40: 26.7774 | AO40: 59.67 | AP40: 6.47 | AQ40: 119.63 | AR40: 52.78 | AS40: 121.425 | AT40: 7.85 | AU40: 369.92 | AV40: 258.07 | AW40: 124.73
B41: 45939 | C41: 237 | D41: 4.5 | E41: 1.78 | F41: 2.47 | G41: 22.91 | H41: 3.31 | I41: 47.54 | J41: 6.7282 | K41: 48.67 | L41: 53.93 | M41: 261.24 | N41: 33.74 | O41: 29.67 | P41: 16.14 | Q41: 25.24 | R41: 24.93 | S41: 153.29 | T41: 61.92 | U41: 132.4 | V41: 45.285 | W41: 185.47 | X41: 56.36 | Y41: 43.89 | Z41: 345.21 | AA41: 0.497 | AB41: 27 | AC41: 68.69 | AD41: 671.16 | AE41: 4.7 | AF41: 54.2953 | AG41: 13.155 | AH41: 610.7 | AI41: 102.56 | AJ41: 110.99 | AK41: 117.61 | AL41: 227.74 | AM41: 54.225 | AN41: 26.58 | AO41: 58.86 | AP41: 6.58 | AQ41: 119.55 | AR41: 54.46 | AS41: 123.107 | AT41: 7.46 | AU41: 367.69 | AV41: 256.69 | AW41: 124.06
B42: 45940 | C42: 224.63 | D42: 4.49 | E42: #N/A N/A | F42: 2.42 | G42: 21.02 | H42: 3.32 | I42: 44.95 | J42: 6.5631 | K42: 48.33 | L42: 51.94 | M42: 254.99 | N42: 33.4 | O42: 28.79 | P42: 15.78 | Q42: 24.78 | R42: 24.59 | S42: 149.9 | T42: 61.02 | U42: 121.69 | V42: 45.1 | W42: 175.44 | X42: 56.1 | Y42: 43.29 | Z42: 325.34 | AA42: 0.485 | AB42: 26.8 | AC42: 67.15 | AD42: 653.02 | AE42: #N/A N/A | AF42: 53.6406 | AG42: 12.74 | AH42: 589.5 | AI42: 99.13 | AJ42: 109.19 | AK42: 114.375 | AL42: 216.37 | AM42: 48.535 | AN42: 24.59 | AO42: 54.27 | AP42: 6.55 | AQ42: 119.57 | AR42: 52.54 | AS42: 122.008 | AT42: 6.71 | AU42: 354.5 | AV42: 251.97 | AW42: 117.82
B43: 45941 | C43: #N/A N/A | D43: #N/A N/A | E43: #N/A N/A | F43: #N/A N/A | G43: #N/A N/A | H43: #N/A N/A | I43: #N/A N/A | J43: #N/A N/A | K43: #N/A N/A | L43: #N/A N/A | M43: #N/A N/A | N43: #N/A N/A | O43: #N/A N/A | P43: #N/A N/A | Q43: #N/A N/A | R43: #N/A N/A | S43: #N/A N/A | T43: #N/A N/A | U43: #N/A N/A | V43: #N/A N/A | W43: #N/A N/A | X43: #N/A N/A | Y43: #N/A N/A | Z43: #N/A N/A | AA43: #N/A N/A | AB43: #N/A N/A | AC43: #N/A N/A | AD43: #N/A N/A | AE43: #N/A N/A | AF43: #N/A N/A | AG43: #N/A N/A | AH43: #N/A N/A | AI43: #N/A N/A | AJ43: #N/A N/A | AK43: #N/A N/A | AL43: #N/A N/A | AM43: #N/A N/A | AN43: #N/A N/A | AO43: #N/A N/A | AP43: #N/A N/A | AQ43: #N/A N/A | AR43: #N/A N/A | AS43: #N/A N/A | AT43: #N/A N/A | AU43: #N/A N/A | AV43: #N/A N/A | AW43: #N/A N/A
B44: 45942 | C44: #N/A N/A | D44: #N/A N/A | E44: #N/A N/A | F44: #N/A N/A | G44: #N/A N/A | H44: #N/A N/A | I44: #N/A N/A | J44: #N/A N/A | K44: #N/A N/A | L44: #N/A N/A | M44: #N/A N/A | N44: #N/A N/A | O44: #N/A N/A | P44: #N/A N/A | Q44: #N/A N/A | R44: #N/A N/A | S44: #N/A N/A | T44: #N/A N/A | U44: #N/A N/A | V44: #N/A N/A | W44: #N/A N/A | X44: #N/A N/A | Y44: #N/A N/A | Z44: #N/A N/A | AA44: #N/A N/A | AB44: #N/A N/A | AC44: #N/A N/A | AD44: #N/A N/A | AE44: #N/A N/A | AF44: #N/A N/A | AG44: #N/A N/A | AH44: #N/A N/A | AI44: #N/A N/A | AJ44: #N/A N/A | AK44: #N/A N/A | AL44: #N/A N/A | AM44: #N/A N/A | AN44: #N/A N/A | AO44: #N/A N/A | AP44: #N/A N/A | AQ44: #N/A N/A | AR44: #N/A N/A | AS44: #N/A N/A | AT44: #N/A N/A | AU44: #N/A N/A | AV44: #N/A N/A | AW44: #N/A N/A
B45: 45943 | C45: 229.65 | D45: 4.53 | E45: 1.78 | F45: 2.5 | G45: 21.73 | H45: 3.39 | I45: 46.32 | J45: 6.6699 | K45: 48.73 | L45: 53.45 | M45: 258 | N45: 33.63 | O45: 29.18 | P45: 16.37 | Q45: 24.73 | R45: 25.64 | S45: 151.46 | T45: 61.48 | U45: 125.72 | V45: 45.445 | W45: 177.21 | X45: 56.08 | Y45: 43.35 | Z45: 339.75 | AA45: 0.51 | AB45: 26.9 | AC45: 67.91 | AD45: 663.04 | AE45: 4.81 | AF45: 53.7006 | AG45: 12.885 | AH45: 602.01 | AI45: 101.25 | AJ45: 110.27 | AK45: 116.93 | AL45: 220.07 | AM45: 51.615 | AN45: 25.47 | AO45: 56.61 | AP45: 6.56 | AQ45: 119.27 | AR45: 54.96 | AS45: 121.903 | AT45: 7.18 | AU45: 358.66 | AV45: 256.68 | AW45: 120.44
B46: 45944 | C46: 234.67 | D46: 4.49 | E46: 1.78 | F46: 2.5 | G46: 21.29 | H46: 3.37 | I46: 46.89 | J46: 6.6602 | K46: 49.12 | L46: 52.97 | M46: 253.95 | N46: 33.91 | O46: 29.1 | P46: 16.42 | Q46: 24.52 | R46: 25.28 | S46: 153.24 | T46: 61.83 | U46: 119.94 | V46: 45.85 | W46: 179.74 | X46: 56.33 | Y46: 44.13 | Z46: 333.5 | AA46: 0.51 | AB46: 26.5 | AC46: 68.41 | AD46: 662.23 | AE46: 4.82 | AF46: 53.8591 | AG46: 12.8588 | AH46: 598 | AI46: 103.7 | AJ46: 111.17 | AK46: 117.175 | AL46: 216.39 | AM46: 50.565 | AN46: 24.62 | AO46: 54.95 | AP46: 6.64 | AQ46: 120.17 | AR46: 54.55 | AS46: 121.535 | AT46: 6.8 | AU46: 359.93 | AV46: 257.72 | AW46: 125.98
B47: 45945 | C47: 235.8 | D47: 4.5 | E47: 1.77 | F47: 2.49 | G47: 21.64 | H47: 3.37 | I47: 48.93 | J47: 6.6699 | K47: 48.95 | L47: 53.84 | M47: 254.9 | N47: 33.7 | O47: 29.32 | P47: 16.87 | Q47: 24.39 | R47: 25.54 | S47: 152.6 | T47: 61.99 | U47: 121.58 | V47: 46.45 | W47: 179.62 | X47: 56.64 | Y47: 44.42 | Z47: 341.78 | AA47: 0.58 | AB47: 26.5 | AC47: 68.82 | AD47: 665.17 | AE47: 4.82 | AF47: 54.1192 | AG47: 13.1141 | AH47: 602.22 | AI47: 103.13 | AJ47: 111.71 | AK47: 117.345 | AL47: 215.57 | AM47: 51.6 | AN47: 25.08 | AO47: 55.55 | AP47: 6.58 | AQ47: 119.92 | AR47: 55.4 | AS47: 120.329 | AT47: 6.82 | AU47: 361.15 | AV47: 261.5 | AW47: 124.46
B48: 45946 | C48: 236.91 | D48: 4.55 | E48: 1.77 | F48: 2.5 | G48: 21.37 | H48: 3.35 | I48: 48.03 | J48: 6.6602 | K48: 49.43 | L48: 54.19 | M48: 252.65 | N48: 33.63 | O48: 29.24 | P48: 16.79 | Q48: 24.23 | R48: 26.76 | S48: 151.6 | T48: 62.58 | U48: 120.89 | V48: 45.945 | W48: 178.12 | X48: 57.47 | Y48: 45.15 | Z48: 343.3 | AA48: 0.59 | AB48: 26.43 | AC48: 68.19 | AD48: 660.64 | AE48: 4.82 | AF48: 54.2544 | AG48: 13.0175 | AH48: 599.99 | AI48: 99.85 | AJ48: 109.88 | AK48: 116.21 | AL48: 214.47 | AM48: 51.025 | AN48: 25.05 | AO48: 55.33 | AP48: 6.39 | AQ48: 119.7 | AR48: 56.31 | AS48: 118.359 | AT48: 6.83 | AU48: 356.67 | AV48: 259.23 | AW48: 117.52
B49: 45947 | C49: 237.8 | D49: 4.55 | E49: 1.77 | F49: 2.47 | G49: 21.2 | H49: 3.34 | I49: 46.56 | J49: 6.7282 | K49: 49.47 | L49: 54.18 | M49: 254.06 | N49: 33.23 | O49: 29.71 | P49: 16.53 | Q49: 24.51 | R49: 25.57 | S49: 151.73 | T49: 62.56 | U49: 120.01 | V49: 45.785 | W49: 178.15 | X49: 57.78 | Y49: 45.23 | Z49: 342.83 | AA49: 0.58 | AB49: 26.4 | AC49: 68.54 | AD49: 664.39 | AE49: 4.81 | AF49: 54.6271 | AG49: 13.17 | AH49: 603.93 | AI49: 100.67 | AJ49: 110.67 | AK49: 117.21 | AL49: 213.04 | AM49: 51.995 | AN49: 24.59 | AO49: 54.34 | AP49: 6.31 | AQ49: 121.44 | AR49: 57 | AS49: 119.936 | AT49: 6.75 | AU49: 356.6 | AV49: 261.35 | AW49: 117.6
B50: 45948 | C50: #N/A N/A | D50: #N/A N/A | E50: #N/A N/A | F50: #N/A N/A | G50: #N/A N/A | H50: #N/A N/A | I50: #N/A N/A | J50: #N/A N/A | K50: #N/A N/A | L50: #N/A N/A | M50: #N/A N/A | N50: #N/A N/A | O50: #N/A N/A | P50: #N/A N/A | Q50: #N/A N/A | R50: #N/A N/A | S50: #N/A N/A | T50: #N/A N/A | U50: #N/A N/A | V50: #N/A N/A | W50: #N/A N/A | X50: #N/A N/A | Y50: #N/A N/A | Z50: #N/A N/A | AA50: #N/A N/A | AB50: #N/A N/A | AC50: #N/A N/A | AD50: #N/A N/A | AE50: #N/A N/A | AF50: #N/A N/A | AG50: #N/A N/A | AH50: #N/A N/A | AI50: #N/A N/A | AJ50: #N/A N/A | AK50: #N/A N/A | AL50: #N/A N/A | AM50: #N/A N/A | AN50: #N/A N/A | AO50: #N/A N/A | AP50: #N/A N/A | AQ50: #N/A N/A | AR50: #N/A N/A | AS50: #N/A N/A | AT50: #N/A N/A | AU50: #N/A N/A | AV50: #N/A N/A | AW50: #N/A N/A
B51: 45949 | C51: #N/A N/A | D51: #N/A N/A | E51: #N/A N/A | F51: #N/A N/A | G51: #N/A N/A | H51: #N/A N/A | I51: #N/A N/A | J51: #N/A N/A | K51: #N/A N/A | L51: #N/A N/A | M51: #N/A N/A | N51: #N/A N/A | O51: #N/A N/A | P51: #N/A N/A | Q51: #N/A N/A | R51: #N/A N/A | S51: #N/A N/A | T51: #N/A N/A | U51: #N/A N/A | V51: #N/A N/A | W51: #N/A N/A | X51: #N/A N/A | Y51: #N/A N/A | Z51: #N/A N/A | AA51: #N/A N/A | AB51: #N/A N/A | AC51: #N/A N/A | AD51: #N/A N/A | AE51: #N/A N/A | AF51: #N/A N/A | AG51: #N/A N/A | AH51: #N/A N/A | AI51: #N/A N/A | AJ51: #N/A N/A | AK51: #N/A N/A | AL51: #N/A N/A | AM51: #N/A N/A | AN51: #N/A N/A | AO51: #N/A N/A | AP51: #N/A N/A | AQ51: #N/A N/A | AR51: #N/A N/A | AS51: #N/A N/A | AT51: #N/A N/A | AU51: #N/A N/A | AV51: #N/A N/A | AW51: #N/A N/A
B52: 45950 | C52: 239.81 | D52: 4.53 | E52: 1.75 | F52: 2.48 | G52: 21.46 | H52: 3.35 | I52: 47.24 | J52: 6.9126 | K52: 49.92 | L52: 54.92 | M52: 253.57 | N52: 33.36 | O52: 30.22 | P52: 16.6 | Q52: 24.69 | R52: 25.65 | S52: 153.52 | T52: 62.88 | U52: 122.12 | V52: 45.77 | W52: 181.59 | X52: 57.68 | Y52: 45.2 | Z52: 347.22 | AA52: 0.55 | AB52: 26.4 | AC52: 69.31 | AD52: 671.3 | AE52: 4.82 | AF52: 54.9584 | AG52: 13.435 | AH52: 611.54 | AI52: 101.52 | AJ52: 111.96 | AK52: 118.14 | AL52: 216.48 | AM52: 53.945 | AN52: 25.01 | AO52: 55.03 | AP52: 6.33 | AQ52: 120.7 | AR52: 55.66 | AS52: 123.856 | AT52: 7.06 | AU52: 364.48 | AV52: 262.29 | AW52: 120.11
B53: 45951 | C53: 242.84 | D53: 4.45 | E53: 1.82 | F53: 2.5 | G53: 21.48 | H53: 3.3 | I53: 46.81 | J53: 6.8252 | K53: 49.21 | L53: 54.31 | M53: 253.85 | N53: 33.08 | O53: 29.94 | P53: 16.34 | Q53: 24.85 | R53: 22.96 | S53: 154.88 | T53: 62.42 | U53: 119.14 | V53: 45.305 | W53: 181.51 | X53: 57.11 | Y53: 44.98 | Z53: 345.3 | AA53: 0.5 | AB53: 26.15 | AC53: 69.44 | AD53: 671.29 | AE53: 4.8 | AF53: 54.9825 | AG53: 13.35 | AH53: 611.38 | AI53: 101.86 | AJ53: 114.3 | AK53: 119.585 | AL53: 222.03 | AM53: 53.885 | AN53: 25.1353 | AO53: 55.02 | AP53: 6.36 | AQ53: 120.05 | AR53: 54.06 | AS53: 124.135 | AT53: 6.8 | AU53: 365.37 | AV53: 260.28 | AW53: 123.68
B54: 45952 | C54: 239.41 | D54: 4.35 | E54: 1.78 | F54: 2.46 | G54: 21.24 | H54: 3.3 | I54: 45.95 | J54: 6.8641 | K54: 49.34 | L54: 54.26 | M54: 253.04 | N54: 33.23 | O54: 30.03 | P54: 16.12 | Q54: 24.72 | R54: 22.9 | S54: 152.87 | T54: 62.23 | U54: 117.03 | V54: 45.2 | W54: 175.49 | X54: 57.14 | Y54: 44.91 | Z54: 338.6 | AA54: 0.496 | AB54: 26.2 | AC54: 69.04 | AD54: 667.8 | AE54: 4.82 | AF54: 55.0022 | AG54: 13.3053 | AH54: 605.49 | AI54: 102.09 | AJ54: 113.08 | AK54: 118.65 | AL54: 217.95 | AM54: 52.3 | AN54: 24.8532 | AO54: 54.62 | AP54: 6.26 | AQ54: 120.21 | AR54: 55.07 | AS54: 111.637 | AT54: 6.84 | AU54: 361.49 | AV54: 255.56 | AW54: 123.3
B55: 45953 | C55: 238.17 | D55: 4.35 | E55: 1.78 | F55: 2.45 | G55: 21.47 | H55: 3.32 | I55: 46.53 | J55: 6.8932 | K55: 49.57 | L55: 54.74 | M55: 257.93 | N55: 33.38 | O55: 30.47 | P55: 16.34 | Q55: 24.67 | R55: 22.91 | S55: 154.78 | T55: 62.68 | U55: 120.48 | V55: 45.165 | W55: 180.48 | X55: 57.17 | Y55: 45.27 | Z55: 344.8 | AA55: 0.54 | AB55: 25.9 | AC55: 69.48 | AD55: 671.76 | AE55: 4.82 | AF55: 54.9604 | AG55: 13.49 | AH55: 610.58 | AI55: 101.76 | AJ55: 113.03 | AK55: 119.185 | AL55: 221.09 | AM55: 53.61 | AN55: 25.0823 | AO55: 55.22 | AP55: 6.25 | AQ55: 118.76 | AR55: 55.84 | AS55: 111.359 | AT55: 6.89 | AU55: 360.45 | AV55: 254.53 | AW55: 120.96
B56: 45954 | C56: 241.15 | D56: 4.3 | E56: #N/A N/A | F56: 2.45 | G56: 21.62 | H56: 3.3 | I56: 48.1 | J56: 6.8641 | K56: 49.7 | L56: 55.1 | M56: 256.8 | N56: 33.55 | O56: 30.48 | P56: 16.7 | Q56: 24.76 | R56: 22.47 | S56: 154.91 | T56: 62.65 | U56: 122.76 | V56: 45.695 | W56: 184.63 | X56: 57.12 | Y56: 45.11 | Z56: 351.14 | AA56: 0.51 | AB56: 25.5 | AC56: 69.85 | AD56: 677.25 | AE56: 4.82 | AF56: 55.1192 | AG56: 13.5318 | AH56: 617.1 | AI56: 102.18 | AJ56: 111.68 | AK56: 118.83 | AL56: 224.21 | AM56: 55.28 | AN56: 25.67 | AO56: 56.55 | AP56: 6.16 | AQ56: 118.93 | AR56: 56.07 | AS56: 109.469 | AT56: 6.9 | AU56: 362.5 | AV56: 255.12 | AW56: 121.24
B57: 45955 | C57: #N/A N/A | D57: #N/A N/A | E57: #N/A N/A | F57: #N/A N/A | G57: #N/A N/A | H57: #N/A N/A | I57: #N/A N/A | J57: #N/A N/A | K57: #N/A N/A | L57: #N/A N/A | M57: #N/A N/A | N57: #N/A N/A | O57: #N/A N/A | P57: #N/A N/A | Q57: #N/A N/A | R57: #N/A N/A | S57: #N/A N/A | T57: #N/A N/A | U57: #N/A N/A | V57: #N/A N/A | W57: #N/A N/A | X57: #N/A N/A | Y57: #N/A N/A | Z57: #N/A N/A | AA57: #N/A N/A | AB57: #N/A N/A | AC57: #N/A N/A | AD57: #N/A N/A | AE57: #N/A N/A | AF57: #N/A N/A | AG57: #N/A N/A | AH57: #N/A N/A | AI57: #N/A N/A | AJ57: #N/A N/A | AK57: #N/A N/A | AL57: #N/A N/A | AM57: #N/A N/A | AN57: #N/A N/A | AO57: #N/A N/A | AP57: #N/A N/A | AQ57: #N/A N/A | AR57: #N/A N/A | AS57: #N/A N/A | AT57: #N/A N/A | AU57: #N/A N/A | AV57: #N/A N/A | AW57: #N/A N/A
B58: 45956 | C58: #N/A N/A | D58: #N/A N/A | E58: #N/A N/A | F58: #N/A N/A | G58: #N/A N/A | H58: #N/A N/A | I58: #N/A N/A | J58: #N/A N/A | K58: #N/A N/A | L58: #N/A N/A | M58: #N/A N/A | N58: #N/A N/A | O58: #N/A N/A | P58: #N/A N/A | Q58: #N/A N/A | R58: #N/A N/A | S58: #N/A N/A | T58: #N/A N/A | U58: #N/A N/A | V58: #N/A N/A | W58: #N/A N/A | X58: #N/A N/A | Y58: #N/A N/A | Z58: #N/A N/A | AA58: #N/A N/A | AB58: #N/A N/A | AC58: #N/A N/A | AD58: #N/A N/A | AE58: #N/A N/A | AF58: #N/A N/A | AG58: #N/A N/A | AH58: #N/A N/A | AI58: #N/A N/A | AJ58: #N/A N/A | AK58: #N/A N/A | AL58: #N/A N/A | AM58: #N/A N/A | AN58: #N/A N/A | AO58: #N/A N/A | AP58: #N/A N/A | AQ58: #N/A N/A | AR58: #N/A N/A | AS58: #N/A N/A | AT58: #N/A N/A | AU58: #N/A N/A | AV58: #N/A N/A | AW58: #N/A N/A
B59: 45957 | C59: 247.34 | D59: 4.23 | E59: #N/A N/A | F59: 2.45 | G59: 23.02 | H59: 3.32 | I59: 48.91 | J59: 6.932 | K59: 50.23 | L59: 55.71 | M59: 256.49 | N59: 33.94 | O59: 30.77 | P59: 16.75 | Q59: 24.77 | R59: 21.5 | S59: 155.79 | T59: 63.13 | U59: 128.66 | V59: 45.82 | W59: 189.18 | X59: 56.94 | Y59: 45.33 | Z59: 359.94 | AA59: 0.498 | AB59: 25.8 | AC59: 70.11 | AD59: 685.24 | AE59: 4.79 | AF59: 55.6716 | AG59: 13.7 | AH59: 628.09 | AI59: 102.21 | AJ59: 112.34 | AK59: 120.54 | AL59: 226.97 | AM59: 58.215 | AN59: 26.215 | AO59: 57.94 | AP59: 6.03 | AQ59: 120.62 | AR59: 56.92 | AS59: 109.456 | AT59: 7.04 | AU59: 365.98 | AV59: 254.27 | AW59: 122.26
B60: 45958 | C60: 249.55 | D60: 4.22 | E60: #N/A N/A | F60: 2.45 | G60: 23.34 | H60: 3.31 | I60: 48.45 | J60: 6.9612 | K60: 50.6 | L60: 55.69 | M60: 260.34 | N60: 34.04 | O60: 30.92 | P60: 16.89 | Q60: 24.5 | R60: 22.11 | S60: 154.68 | T60: 63.04 | U60: 126.82 | V60: 45.065 | W60: 189.6 | X60: 56.17 | Y60: 45.14 | Z60: 363.11 | AA60: 0.494 | AB60: 25.8 | AC60: 69.62 | AD60: 687.06 | AE60: 4.8 | AF60: 55.2555 | AG60: 13.645 | AH60: 632.92 | AI60: 101.45 | AJ60: 111.65 | AK60: 120.57 | AL60: 229.25 | AM60: 59.545 | AN60: 26.13 | AO60: 57.98 | AP60: 6.11 | AQ60: 120.66 | AR60: 56.73 | AS60: 110.25 | AT60: 7.09 | AU60: 367.84 | AV60: 251.57 | AW60: 120.61
B61: 45959 | C61: 249.64 | D61: 4.28 | E61: #N/A N/A | F61: 2.45 | G61: 23.18 | H61: 3.32 | I61: 48.6 | J61: 7.1359 | K61: 50.65 | L61: 56.01 | M61: 263.36 | N61: 34.06 | O61: 31.18 | P61: 17.32 | Q61: 24.29 | R61: 22.26 | S61: 155.08 | T61: 62.83 | U61: 127.6 | V61: 45.05 | W61: 198.81 | X61: 55.66 | Y61: 44.86 | Z61: 368.61 | AA61: 0.5 | AB61: 25.8 | AC61: 69.41 | AD61: 687.39 | AE61: 4.82 | AF61: 54.7414 | AG61: 13.6543 | AH61: 635.77 | AI61: 101.19 | AJ61: 110.24 | AK61: 119.575 | AL61: 230.3 | AM61: 60.305 | AN61: 26.365 | AO61: 58.39 | AP61: 5.92 | AQ61: 116.72 | AR61: 57.4 | AS61: 110.041 | AT61: 7.14 | AU61: 355.26 | AV61: 251.73 | AW61: 118.55
B62: 45960 | C62: 248.93 | D62: 4.37 | E62: 1.65 | F62: 2.44 | G62: 22.95 | H62: 3.32 | I62: 47.73 | J62: 7.1165 | K62: 50.28 | L62: 55.43 | M62: 260 | N62: 33.97 | O62: 31.05 | P62: 17.03 | Q62: 24.29 | R62: 22.73 | S62: 154.69 | T62: 62.42 | U62: 121.81 | V62: 44.86 | W62: 194.55 | X62: 55.6 | Y62: 44.44 | Z62: 363.73 | AA62: 0.51 | AB62: 25.8 | AC62: 69.07 | AD62: 679.83 | AE62: 4.82 | AF62: 54.9834 | AG62: 13.65 | AH62: 626.05 | AI62: 103.09 | AJ62: 111.84 | AK62: 116.875 | AL62: 222.86 | AM62: 57.545 | AN62: 25.7855 | AO62: 57.11 | AP62: 5.79 | AQ62: 120.21 | AR62: 57.87 | AS62: 108.9 | AT62: 7.01 | AU62: 344.75 | AV62: 252.78 | AW62: 118.11
B63: 45961 | C63: 253.82 | D63: 4.3 | E63: #N/A N/A | F63: 2.46 | G63: 23.49 | H63: 3.29 | I63: 49.12 | J63: 7.1456 | K63: 50.17 | L63: 55.3 | M63: 261 | N63: 33.85 | O63: 31.17 | P63: 17.3 | Q63: 24.65 | R63: 22.77 | S63: 155.06 | T63: 62.17 | U63: 120.87 | V63: 44.55 | W63: 200.47 | X63: 55.36 | Y63: 44.28 | Z63: 363.02 | AA63: 0.53 | AB63: 25.5 | AC63: 69.35 | AD63: 682.06 | AE63: 4.81 | AF63: 54.834 | AG63: 13.725 | AH63: 629.07 | AI63: 104 | AJ63: 112.62 | AK63: 119.965 | AL63: 244.22 | AM63: 58.36 | AN63: 25.345 | AO63: 56.11 | AP63: 5.91 | AQ63: 119.71 | AR63: 58.04 | AS63: 111.886 | AT63: 7.25 | AU63: 341.56 | AV63: 256.37 | AW63: 118.33
B64: 45962 | C64: #N/A N/A | D64: #N/A N/A | E64: #N/A N/A | F64: #N/A N/A | G64: #N/A N/A | H64: #N/A N/A | I64: #N/A N/A | J64: #N/A N/A | K64: #N/A N/A | L64: #N/A N/A | M64: #N/A N/A | N64: #N/A N/A | O64: #N/A N/A | P64: #N/A N/A | Q64: #N/A N/A | R64: #N/A N/A | S64: #N/A N/A | T64: #N/A N/A | U64: #N/A N/A | V64: #N/A N/A | W64: #N/A N/A | X64: #N/A N/A | Y64: #N/A N/A | Z64: #N/A N/A | AA64: #N/A N/A | AB64: #N/A N/A | AC64: #N/A N/A | AD64: #N/A N/A | AE64: #N/A N/A | AF64: #N/A N/A | AG64: #N/A N/A | AH64: #N/A N/A | AI64: #N/A N/A | AJ64: #N/A N/A | AK64: #N/A N/A | AL64: #N/A N/A | AM64: #N/A N/A | AN64: #N/A N/A | AO64: #N/A N/A | AP64: #N/A N/A | AQ64: #N/A N/A | AR64: #N/A N/A | AS64: #N/A N/A | AT64: #N/A N/A | AU64: #N/A N/A | AV64: #N/A N/A | AW64: #N/A N/A
B65: 45963 | C65: #N/A N/A | D65: #N/A N/A | E65: #N/A N/A | F65: #N/A N/A | G65: #N/A N/A | H65: #N/A N/A | I65: #N/A N/A | J65: #N/A N/A | K65: #N/A N/A | L65: #N/A N/A | M65: #N/A N/A | N65: #N/A N/A | O65: #N/A N/A | P65: #N/A N/A | Q65: #N/A N/A | R65: #N/A N/A | S65: #N/A N/A | T65: #N/A N/A | U65: #N/A N/A | V65: #N/A N/A | W65: #N/A N/A | X65: #N/A N/A | Y65: #N/A N/A | Z65: #N/A N/A | AA65: #N/A N/A | AB65: #N/A N/A | AC65: #N/A N/A | AD65: #N/A N/A | AE65: #N/A N/A | AF65: #N/A N/A | AG65: #N/A N/A | AH65: #N/A N/A | AI65: #N/A N/A | AJ65: #N/A N/A | AK65: #N/A N/A | AL65: #N/A N/A | AM65: #N/A N/A | AN65: #N/A N/A | AO65: #N/A N/A | AP65: #N/A N/A | AQ65: #N/A N/A | AR65: #N/A N/A | AS65: #N/A N/A | AT65: #N/A N/A | AU65: #N/A N/A | AV65: #N/A N/A | AW65: #N/A N/A
B66: 45964 | C66: 252.99 | D66: 4.27 | E66: 1.78 | F66: 2.47 | G66: 23.61 | H66: 3.27 | I66: 49.14 | J66: 7.2524 | K66: 50.13 | L66: 55.65 | M66: 260.45 | N66: 33.81 | O66: 31.52 | P66: 17.6 | Q66: 24.66 | R66: 21.92 | S66: 154.4 | T66: 62.145 | U66: 121.23 | V66: 44.575 | W66: 207.18 | X66: 55.12 | Y66: 44.07 | Z66: 366.1 | AA66: 0.495 | AB66: 25.5 | AC66: 69.31 | AD66: 683.34 | AE66: 4.81 | AF66: 54.5147 | AG66: 13.7 | AH66: 632.08 | AI66: 104.63 | AJ66: 112.12 | AK66: 121.09 | AL66: 254 | AM66: 59.16 | AN66: 25.2742 | AO66: 55.78 | AP66: 5.59 | AQ66: 102.27 | AR66: 57.95 | AS66: 110.009 | AT66: 7.42 | AU66: 333.79 | AV66: 255.65 | AW66: 117.63
B67: 45965 | C67: 251.88 | D67: 4.3 | E67: 1.7 | F67: 2.44 | G67: 22.69 | H67: 3.27 | I67: 47.93 | J67: 7.165 | K67: 49.73 | L67: 54.63 | M67: 257.38 | N67: 33.56 | O67: 31.18 | P67: 17.17 | Q67: 24.3 | R67: 21.16 | S67: 152.61 | T67: 61.42 | U67: 124.99 | V67: 44.415 | W67: 190.74 | X67: 55.06 | Y67: 43.63 | Z67: 352.76 | AA67: 0.47 | AB67: 25.5 | AC67: 68.98 | AD67: 675.24 | AE67: 4.81 | AF67: 54.548 | AG67: 13.5942 | AH67: 619.25 | AI67: 105.04 | AJ67: 111.47 | AK67: 119.08 | AL67: 249.32 | AM67: 55.54 | AN67: 24.8 | AO67: 54.78 | AP67: 5.6 | AQ67: 100.64 | AR67: 58.06 | AS67: 109.296 | AT67: 7.16 | AU67: 330.83 | AV67: 252.43 | AW67: 118.29
B68: 45966 | C68: 256.1 | D68: 4.4 | E68: 1.78 | F68: 2.43 | G68: 21.79 | H68: 3.24 | I68: 51.28 | J68: 7.2621 | K68: 50.4 | L68: 55.12 | M68: 258.82 | N68: 34 | O68: 32.1 | P68: 18.1 | Q68: 24.61 | R68: 21.68 | S68: 153.2 | T68: 61.93 | U68: 123.33 | V68: 44.425 | W68: 187.9 | X68: 55.4 | Y68: 43.88 | Z68: 359.5 | AA68: 0.477 | AB68: 25.5 | AC68: 69.27 | AD68: 677.58 | AE68: 4.81 | AF68: 54.5785 | AG68: 14.015 | AH68: 623.28 | AI68: 104.43 | AJ68: 111.36 | AK68: 120.53 | AL68: 250.2 | AM68: 56.62 | AN68: 25.074 | AO68: 55.35 | AP68: 5.43 | AQ68: 100.05 | AR68: 59.13 | AS68: 109.846 | AT68: 7.29 | AU68: 327.74 | AV68: 254.76 | AW68: 118.89
B69: 45967 | C69: 258.86 | D69: 4.45 | E69: 1.66 | F69: 2.42 | G69: 23.89 | H69: 3.27 | I69: 50.24 | J69: 7.2718 | K69: 50.65 | L69: 54.71 | M69: 258.84 | N69: 34.04 | O69: 32.04 | P69: 17.77 | Q69: 24.85 | R69: 21.7 | S69: 152.59 | T69: 61.55 | U69: 127.04 | V69: 44.23 | W69: 175.05 | X69: 55.22 | Y69: 43.42 | Z69: 351.09 | AA69: 0.465 | AB69: 25.1 | AC69: 69.07 | AD69: 670.31 | AE69: 4.81 | AF69: 54.7878 | AG69: 13.818 | AH69: 611.67 | AI69: 105.2 | AJ69: 110.49 | AK69: 117.745 | AL69: 243.04 | AM69: 53.445 | AN69: 25.345 | AO69: 56.05 | AP69: 5.53 | AQ69: 100.77 | AR69: 60.27 | AS69: 109.702 | AT69: 7.16 | AU69: 321.56 | AV69: 252.4 | AW69: 119.31
B70: 45968 | C70: 262.09 | D70: 4.45 | E70: #N/A N/A | F70: 2.41 | G70: 22.42 | H70: 3.26 | I70: 50.39 | J70: 7.3495 | K70: 50.52 | L70: 54.55 | M70: 259.52 | N70: 34.13 | O70: 32.3 | P70: 17.66 | Q70: 24.43 | R70: 22.37 | S70: 153.33 | T70: 61.77 | U70: 125.96 | V70: 44.845 | W70: 177.93 | X70: 55.74 | Y70: 43.78 | Z70: 348.12 | AA70: 0.442 | AB70: 25.08 | AC70: 69.52 | AD70: 670.97 | AE70: 4.81 | AF70: 54.9347 | AG70: 13.705 | AH70: 609.74 | AI70: 106.29 | AJ70: 110.74 | AK70: 117.93 | AL70: 244.41 | AM70: 52.89 | AN70: 25.035 | AO70: 55.08 | AP70: 5.42 | AQ70: 103.85 | AR70: 63.22 | AS70: 110.366 | AT70: 6.86 | AU70: 324.21 | AV70: 232 | AW70: 121.32
B71: 45969 | C71: #N/A N/A | D71: #N/A N/A | E71: #N/A N/A | F71: #N/A N/A | G71: #N/A N/A | H71: #N/A N/A | I71: #N/A N/A | J71: #N/A N/A | K71: #N/A N/A | L71: #N/A N/A | M71: #N/A N/A | N71: #N/A N/A | O71: #N/A N/A | P71: #N/A N/A | Q71: #N/A N/A | R71: #N/A N/A | S71: #N/A N/A | T71: #N/A N/A | U71: #N/A N/A | V71: #N/A N/A | W71: #N/A N/A | X71: #N/A N/A | Y71: #N/A N/A | Z71: #N/A N/A | AA71: #N/A N/A | AB71: #N/A N/A | AC71: #N/A N/A | AD71: #N/A N/A | AE71: #N/A N/A | AF71: #N/A N/A | AG71: #N/A N/A | AH71: #N/A N/A | AI71: #N/A N/A | AJ71: #N/A N/A | AK71: #N/A N/A | AL71: #N/A N/A | AM71: #N/A N/A | AN71: #N/A N/A | AO71: #N/A N/A | AP71: #N/A N/A | AQ71: #N/A N/A | AR71: #N/A N/A | AS71: #N/A N/A | AT71: #N/A N/A | AU71: #N/A N/A | AV71: #N/A N/A | AW71: #N/A N/A
B72: 45970 | C72: #N/A N/A | D72: #N/A N/A | E72: #N/A N/A | F72: #N/A N/A | G72: #N/A N/A | H72: #N/A N/A | I72: #N/A N/A | J72: #N/A N/A | K72: #N/A N/A | L72: #N/A N/A | M72: #N/A N/A | N72: #N/A N/A | O72: #N/A N/A | P72: #N/A N/A | Q72: #N/A N/A | R72: #N/A N/A | S72: #N/A N/A | T72: #N/A N/A | U72: #N/A N/A | V72: #N/A N/A | W72: #N/A N/A | X72: #N/A N/A | Y72: #N/A N/A | Z72: #N/A N/A | AA72: #N/A N/A | AB72: #N/A N/A | AC72: #N/A N/A | AD72: #N/A N/A | AE72: #N/A N/A | AF72: #N/A N/A | AG72: #N/A N/A | AH72: #N/A N/A | AI72: #N/A N/A | AJ72: #N/A N/A | AK72: #N/A N/A | AL72: #N/A N/A | AM72: #N/A N/A | AN72: #N/A N/A | AO72: #N/A N/A | AP72: #N/A N/A | AQ72: #N/A N/A | AR72: #N/A N/A | AS72: #N/A N/A | AT72: #N/A N/A | AU72: #N/A N/A | AV72: #N/A N/A | AW72: #N/A N/A
B73: 45971 | C73: 253.89 | D73: 4.45 | E73: 1.65 | F73: 2.4 | G73: 26.04 | H73: 3.27 | I73: 52.86 | J73: 7.4078 | K73: 51.26 | L73: 55.51 | M73: 259.01 | N73: 34.7 | O73: 32.72 | P73: 18.01 | Q73: 24.39 | R73: 23.34 | S73: 154.2 | T73: 62.54 | U73: 132.32 | V73: 44.83 | W73: 193.61 | X73: 56.36 | Y73: 44.19 | Z73: 358.79 | AA73: 0.46 | AB73: 25.45 | AC73: 70.06 | AD73: 681.44 | AE73: 4.8 | AF73: 55.505 | AG73: 13.9267 | AH73: 623.23 | AI73: 107 | AJ73: 112.24 | AK73: 119.48 | AL73: 248.4 | AM73: 56.355 | AN73: 25.245 | AO73: 55.91 | AP73: 5.2 | AQ73: 103.09 | AR73: 63.57 | AS73: 112.007 | AT73: 6.71 | AU73: 321.58 | AV73: 234.06 | AW73: 120.11
B74: 45972 | C74: 267.72 | D74: 4.45 | E74: 1.68 | F74: 2.4 | G74: 28.07 | H74: 3.3 | I74: 51.85 | J74: 7.6019 | K74: 51.9 | L74: 55.57 | M74: 258.16 | N74: 35.02 | O74: 33.49 | P74: 17.76 | Q74: 25.51 | R74: 23.38 | S74: 154.24 | T74: 63.09 | U74: 131.95 | V74: 44.855 | W74: 190.96 | X74: 57.67 | Y74: 44.71 | Z74: 351.05 | AA74: 0.465 | AB74: 25.43 | AC74: 70.51 | AD74: 683 | AE74: 4.76 | AF74: 56.7522 | AG74: 14.2335 | AH74: 621.57 | AI74: 106.74 | AJ74: 114.85 | AK74: 119.775 | AL74: 249.1 | AM74: 55.89 | AN74: 25.005 | AO74: 55.36 | AP74: 5.22 | AQ74: 103.03 | AR74: 63.83 | AS74: 113.644 | AT74: 6.63 | AU74: 327.45 | AV74: 240.7 | AW74: 121.36
B75: 45973 | C75: 268.67 | D75: 4.45 | E75: 1.73 | F75: 2.38 | G75: 27.28 | H75: 3.3 | I75: 50.57 | J75: 7.4175 | K75: 52.52 | L75: 55.58 | M75: 262.52 | N75: 35.38 | O75: 33.22 | P75: 17.66 | Q75: 25.87 | R75: 23.51 | S75: 154.39 | T75: 63.76 | U75: 128.94 | V75: 44.96 | W75: 184.17 | X75: 58.06 | Y75: 45.14 | Z75: 355.53 | AA75: 0.495 | AB75: 25.78 | AC75: 70.77 | AD75: 683.38 | AE75: 4.8 | AF75: 57.335 | AG75: 14.175 | AH75: 621.08 | AI75: 107.79 | AJ75: 116.65 | AK75: 118.97 | AL75: 244.2 | AM75: 55.775 | AN75: 24.765 | AO75: 54.93 | AP75: 5.23 | AQ75: 104.12 | AR75: 64.15 | AS75: 115.75 | AT75: 6.45 | AU75: 339.06 | AV75: 240.34 | AW75: 123.07
B76: 45974 | C76: 267.34 | D76: 4.47 | E76: 1.78 | F76: 2.34 | G76: 26.38 | H76: 3.3 | I76: 48.48 | J76: 7.3689 | K76: 52.21 | L76: 54.93 | M76: 252.15 | N76: 35.12 | O76: 32.98 | P76: 16.87 | Q76: 25.79 | R76: 23.6 | S76: 152 | T76: 63.34 | U76: 120.65 | V76: 44.34 | W76: 172.14 | X76: 57.85 | Y76: 45.04 | Z76: 344.82 | AA76: 0.484 | AB76: 25.75 | AC76: 69.87 | AD76: 672.04 | AE76: 4.81 | AF76: 57.1358 | AG76: 13.8524 | AH76: 608.4 | AI76: 107.85 | AJ76: 107.61 | AK76: 116 | AL76: 237.58 | AM76: 52.33 | AN76: 24.63 | AO76: 54.28 | AP76: 4.95 | AQ76: 104.45 | AR76: 62.69 | AS76: 115.423 | AT76: 6.24 | AU76: 332.52 | AV76: 237.55 | AW76: 120.75
B77: 45975 | C77: 267.56 | D77: 4.5 | E77: 1.7 | F77: 2.3 | G77: 25.01 | H77: 3.3 | I77: 49.51 | J77: 7.4175 | K77: 51.65 | L77: 54.96 | M77: 253.8 | N77: 34.65 | O77: 33.18 | P77: 17.02 | Q77: 25.06 | R77: 23.56 | S77: 152.01 | T77: 62.79 | U77: 116 | V77: 44.38 | W77: 174.01 | X77: 57.55 | Y77: 44.84 | Z77: 344.98 | AA77: 0.48 | AB77: 25.5 | AC77: 69.59 | AD77: 671.93 | AE77: 4.84 | AF77: 57.1479 | AG77: 13.965 | AH77: 608.86 | AI77: 107.16 | AJ77: 105.8 | AK77: 115.445 | AL77: 234.69 | AM77: 52.37 | AN77: 24.12 | AO77: 53.2 | AP77: 5.18 | AQ77: 104.015 | AR77: 62.94 | AS77: 111.217 | AT77: 6.16 | AU77: 321.86 | AV77: 235.03 | AW77: 119.92
B78: 45976 | C78: #N/A N/A | D78: #N/A N/A | E78: #N/A N/A | F78: #N/A N/A | G78: #N/A N/A | H78: #N/A N/A | I78: #N/A N/A | J78: #N/A N/A | K78: #N/A N/A | L78: #N/A N/A | M78: #N/A N/A | N78: #N/A N/A | O78: #N/A N/A | P78: #N/A N/A | Q78: #N/A N/A | R78: #N/A N/A | S78: #N/A N/A | T78: #N/A N/A | U78: #N/A N/A | V78: #N/A N/A | W78: #N/A N/A | X78: #N/A N/A | Y78: #N/A N/A | Z78: #N/A N/A | AA78: #N/A N/A | AB78: #N/A N/A | AC78: #N/A N/A | AD78: #N/A N/A | AE78: #N/A N/A | AF78: #N/A N/A | AG78: #N/A N/A | AH78: #N/A N/A | AI78: #N/A N/A | AJ78: #N/A N/A | AK78: #N/A N/A | AL78: #N/A N/A | AM78: #N/A N/A | AN78: #N/A N/A | AO78: #N/A N/A | AP78: #N/A N/A | AQ78: #N/A N/A | AR78: #N/A N/A | AS78: #N/A N/A | AT78: #N/A N/A | AU78: #N/A N/A | AV78: #N/A N/A | AW78: #N/A N/A
B79: 45977 | C79: #N/A N/A | D79: #N/A N/A | E79: #N/A N/A | F79: #N/A N/A | G79: #N/A N/A | H79: #N/A N/A | I79: #N/A N/A | J79: #N/A N/A | K79: #N/A N/A | L79: #N/A N/A | M79: #N/A N/A | N79: #N/A N/A | O79: #N/A N/A | P79: #N/A N/A | Q79: #N/A N/A | R79: #N/A N/A | S79: #N/A N/A | T79: #N/A N/A | U79: #N/A N/A | V79: #N/A N/A | W79: #N/A N/A | X79: #N/A N/A | Y79: #N/A N/A | Z79: #N/A N/A | AA79: #N/A N/A | AB79: #N/A N/A | AC79: #N/A N/A | AD79: #N/A N/A | AE79: #N/A N/A | AF79: #N/A N/A | AG79: #N/A N/A | AH79: #N/A N/A | AI79: #N/A N/A | AJ79: #N/A N/A | AK79: #N/A N/A | AL79: #N/A N/A | AM79: #N/A N/A | AN79: #N/A N/A | AO79: #N/A N/A | AP79: #N/A N/A | AQ79: #N/A N/A | AR79: #N/A N/A | AS79: #N/A N/A | AT79: #N/A N/A | AU79: #N/A N/A | AV79: #N/A N/A | AW79: #N/A N/A
B80: 45978 | C80: 264.73 | D80: 4.52 | E80: #N/A N/A | F80: 2.3 | G80: 22.43 | H80: 3.27 | I80: 48.76 | J80: 7.3398 | K80: 50.78 | L80: 54.31 | M80: 250.47 | N80: 33.99 | O80: 32.78 | P80: 16.8 | Q80: 25.08 | R80: 23.04 | S80: 150.52 | T80: 61.84 | U80: 114.11 | V80: 44.78 | W80: 171.25 | X80: 56.81 | Y80: 44.2 | Z80: 340.3 | AA80: 0.461 | AB80: 25.4 | AC80: 68.85 | AD80: 665.67 | AE80: 4.82 | AF80: 57.0894 | AG80: 13.7129 | AH80: 603.66 | AI80: 103.51 | AJ80: 105.69 | AK80: 114.36 | AL80: 232.87 | AM80: 51.025 | AN80: 23.8938 | AO80: 52.66 | AP80: 5 | AQ80: 103.66 | AR80: 62.53 | AS80: 110.29 | AT80: 6.08 | AU80: 320.52 | AV80: 233.58 | AW80: 114.02
B81: 45979 | C81: 263.08 | D81: 4.5 | E81: 1.77 | F81: 2.3 | G81: 22.62 | H81: 3.17 | I81: 48.22 | J81: 7.301 | K81: 49.99 | L81: 54.04 | M81: 251.66 | N81: 33.5 | O81: 32.71 | P81: 16.6 | Q81: 25.45 | R81: 23.08 | S81: 149.85 | T81: 61.07 | U81: 117.14 | V81: 44.61 | W81: 167.33 | X81: 56.58 | Y81: 43.63 | Z81: 333.29 | AA81: 0.455 | AB81: 25.1 | AC81: 68.67 | AD81: 660.08 | AE81: 4.82 | AF81: 57.3756 | AG81: 13.745 | AH81: 596.31 | AI81: 102.64 | AJ81: 106.28 | AK81: 112.25 | AL81: 222.55 | AM81: 49.18 | AN81: 23.8465 | AO81: 52.59 | AP81: 5.13 | AQ81: 103.25 | AR81: 62.77 | AS81: 114.09 | AT81: 5.98 | AU81: 313.58 | AV81: 239.09 | AW81: 114.18
B82: 45980 | C82: 262.57 | D82: 4.5 | E82: 1.78 | F82: 2.3 | G82: 21.17 | H82: 3.25 | I82: 47.62 | J82: 7.2427 | K82: 49.91 | L82: 53.85 | M82: 254.7 | N82: 33.41 | O82: 32.49 | P82: 16.56 | Q82: 24.88 | R82: 23.95 | S82: 150.35 | T82: 60.95 | U82: 115.49 | V82: 44.235 | W82: 165.42 | X82: 56.36 | Y82: 43.44 | Z82: 339.44 | AA82: 0.46 | AB82: 24.95 | AC82: 68.6 | AD82: 662.63 | AE82: 4.8 | AF82: 57.2684 | AG82: 13.645 | AH82: 599.87 | AI82: 103.56 | AJ82: 104.67 | AK82: 112.255 | AL82: 222.69 | AM82: 50.025 | AN82: 23.5438 | AO82: 51.87 | AP82: 4.92 | AQ82: 102.37 | AR82: 62.79 | AS82: 110 | AT82: 5.75 | AU82: 309.09 | AV82: 240.46 | AW82: 117.5
B83: 45981 | C83: 263.1 | D83: 4.5 | E83: 1.78 | F83: 2.38 | G83: 20.09 | H83: 3.24 | I83: 45.66 | J83: 7.1359 | K83: 49.37 | L83: 53.11 | M83: 248.31 | N83: 32.97 | O83: 31.9 | P83: 16.08 | Q83: 24.4 | R83: 22.78 | S83: 147.83 | T83: 60.08 | U83: 110.45 | V83: 44.01 | W83: 155.745 | X83: 55.69 | Y83: 42.99 | Z83: 325.1 | AA83: 0.46 | AB83: 24.75 | AC83: 67.82 | AD83: 652.53 | AE83: 4.8 | AF83: 57.0093 | AG83: 13.2722 | AH83: 585.67 | AI83: 104.12 | AJ83: 102.7 | AK83: 110.58 | AL83: 217.14 | AM83: 46.45 | AN83: 22.9911 | AO83: 50.52 | AP83: 4.83 | AQ83: 103.76 | AR83: 61.54 | AS83: 105.67 | AT83: 5.4 | AU83: 311.54 | AV83: 235.37 | AW83: 114.41
B84: 45982 | C84: 269.43 | D84: 4.51 | E84: #N/A N/A | F84: 2.34 | G84: 20.36 | H84: 3.24 | I84: 45.94 | J84: 7.165 | K84: 49.73 | L84: 53.1 | M84: 247.85 | N84: 33.58 | O84: 32.03 | P84: 16.07 | Q84: 25.04 | R84: 23.02 | S84: 149.63 | T84: 60.78 | U84: 110.95 | V84: 44.075 | W84: 154.85 | X84: 56.69 | Y84: 43.69 | Z84: 326.13 | AA84: 0.435 | AB84: 24.48 | AC84: 68.84 | AD84: 659.03 | AE84: 4.3 | AF84: 58.155 | AG84: 13.3371 | AH84: 590.07 | AI84: 106.75 | AJ84: 104.28 | AK84: 112.75 | AL84: 220.69 | AM84: 47.48 | AN84: 22.9 | AO84: 50.41 | AP84: 4.73 | AQ84: 105.18 | AR84: 60.62 | AS84: 104.31 | AT84: 5.58 | AU84: 319.97 | AV84: 235.47 | AW84: 118.67
B85: 45983 | C85: #N/A N/A | D85: #N/A N/A | E85: #N/A N/A | F85: #N/A N/A | G85: #N/A N/A | H85: #N/A N/A | I85: #N/A N/A | J85: #N/A N/A | K85: #N/A N/A | L85: #N/A N/A | M85: #N/A N/A | N85: #N/A N/A | O85: #N/A N/A | P85: #N/A N/A | Q85: #N/A N/A | R85: #N/A N/A | S85: #N/A N/A | T85: #N/A N/A | U85: #N/A N/A | V85: #N/A N/A | W85: #N/A N/A | X85: #N/A N/A | Y85: #N/A N/A | Z85: #N/A N/A | AA85: #N/A N/A | AB85: #N/A N/A | AC85: #N/A N/A | AD85: #N/A N/A | AE85: #N/A N/A | AF85: #N/A N/A | AG85: #N/A N/A | AH85: #N/A N/A | AI85: #N/A N/A | AJ85: #N/A N/A | AK85: #N/A N/A | AL85: #N/A N/A | AM85: #N/A N/A | AN85: #N/A N/A | AO85: #N/A N/A | AP85: #N/A N/A | AQ85: #N/A N/A | AR85: #N/A N/A | AS85: #N/A N/A | AT85: #N/A N/A | AU85: #N/A N/A | AV85: #N/A N/A | AW85: #N/A N/A
B86: 45984 | C86: #N/A N/A | D86: #N/A N/A | E86: #N/A N/A | F86: #N/A N/A | G86: #N/A N/A | H86: #N/A N/A | I86: #N/A N/A | J86: #N/A N/A | K86: #N/A N/A | L86: #N/A N/A | M86: #N/A N/A | N86: #N/A N/A | O86: #N/A N/A | P86: #N/A N/A | Q86: #N/A N/A | R86: #N/A N/A | S86: #N/A N/A | T86: #N/A N/A | U86: #N/A N/A | V86: #N/A N/A | W86: #N/A N/A | X86: #N/A N/A | Y86: #N/A N/A | Z86: #N/A N/A | AA86: #N/A N/A | AB86: #N/A N/A | AC86: #N/A N/A | AD86: #N/A N/A | AE86: #N/A N/A | AF86: #N/A N/A | AG86: #N/A N/A | AH86: #N/A N/A | AI86: #N/A N/A | AJ86: #N/A N/A | AK86: #N/A N/A | AL86: #N/A N/A | AM86: #N/A N/A | AN86: #N/A N/A | AO86: #N/A N/A | AP86: #N/A N/A | AQ86: #N/A N/A | AR86: #N/A N/A | AS86: #N/A N/A | AT86: #N/A N/A | AU86: #N/A N/A | AV86: #N/A N/A | AW86: #N/A N/A
B87: 45985 | C87: 266.98 | D87: 4.15 | E87: #N/A N/A | F87: 2.29 | G87: 20.93 | H87: 3.18 | I87: 46.46 | J87: 7.165 | K87: 49.94 | L87: 53.66 | M87: 253.78 | N87: 33.54 | O87: 32.2 | P87: 16.29 | Q87: 25.22 | R87: 23.62 | S87: 150 | T87: 60.7 | U87: 119.21 | V87: 44.575 | W87: 162.25 | X87: 56.39 | Y87: 43.33 | Z87: 339.12 | AA87: 0.44 | AB87: 24 | AC87: 69.39 | AD87: 668.73 | AE87: 4.29 | AF87: 58.2608 | AG87: 13.5133 | AH87: 605.16 | AI87: 107.19 | AJ87: 101.94 | AK87: 114.255 | AL87: 226.28 | AM87: 51.08 | AN87: 23.2841 | AO87: 51.83 | AP87: 4.74 | AQ87: 105.03 | AR87: 60.64 | AS87: 106.97 | AT87: 5.75 | AU87: 319.05 | AV87: 239.07 | AW87: 117.85
B88: 45986 | C88: 273.87 | D88: 4.25 | E88: 1.7 | F88: 2.29 | G88: 21.62 | H88: 3.26 | I88: 47.08 | J88: 7.2039 | K88: 50.84 | L88: 53.85 | M88: 251.65 | N88: 34.27 | O88: 32.55 | P88: 16.43 | Q88: 25.72 | R88: 23.38 | S88: 151.92 | T88: 61.76 | U88: 117.88 | V88: 44.405 | W88: 163.55 | X88: 57.26 | Y88: 44.06 | Z88: 340.01 | AA88: 0.47 | AB88: 24.2 | AC88: 70.46 | AD88: 675.02 | AE88: #N/A N/A | AF88: 59.4482 | AG88: 13.5851 | AH88: 608.89 | AI88: 108.35 | AJ88: 103.31 | AK88: 116.7 | AL88: 229.67 | AM88: 52.01 | AN88: 23.535 | AO88: 52.44 | AP88: 4.64 | AQ88: 106.01 | AR88: 60.49 | AS88: 104.4 | AT88: 5.5 | AU88: 326.28 | AV88: 241.84 | AW88: 120.81
B89: 45987 | C89: 275.83 | D89: 4.3 | E89: 1.78 | F89: 2.46 | G89: 21.14 | H89: 3.25 | I89: 47.9 | J89: 7.4369 | K89: 51.59 | L89: 54.24 | M89: 255.87 | N89: 34.75 | O89: 33.47 | P89: 16.8 | Q89: 25.71 | R89: 24.28 | S89: 152.8 | T89: 62.42 | U89: 116.34 | V89: 44.995 | W89: 165.77 | X89: 57.55 | Y89: 44.43 | Z89: 347.71 | AA89: 0.52 | AB89: 25 | AC89: 70.84 | AD89: 679.68 | AE89: 4.26 | AF89: 59.4217 | AG89: 13.9754 | AH89: 614.27 | AI89: 107.97 | AJ89: 103.43 | AK89: 117.5 | AL89: 229.16 | AM89: 53.37 | AN89: 23.5949 | AO89: 52.3 | AP89: 4.78 | AQ89: 108.29 | AR89: 62.7 | AS89: 106.14 | AT89: 5.46 | AU89: 329.71 | AV89: 243.63 | AW89: 120.83
B90: 45988 | C90: #N/A N/A | D90: 4.29 | E90: 1.77 | F90: 2.43 | G90: #N/A N/A | H90: 3.34 | I90: #N/A N/A | J90: #N/A N/A | K90: #N/A N/A | L90: #N/A N/A | M90: #N/A N/A | N90: #N/A N/A | O90: #N/A N/A | P90: #N/A N/A | Q90: #N/A N/A | R90: #N/A N/A | S90: #N/A N/A | T90: #N/A N/A | U90: #N/A N/A | V90: #N/A N/A | W90: #N/A N/A | X90: #N/A N/A | Y90: #N/A N/A | Z90: #N/A N/A | AA90: 0.53 | AB90: 24.7 | AC90: #N/A N/A | AD90: #N/A N/A | AE90: #N/A N/A | AF90: #N/A N/A | AG90: #N/A N/A | AH90: #N/A N/A | AI90: #N/A N/A | AJ90: #N/A N/A | AK90: #N/A N/A | AL90: #N/A N/A | AM90: #N/A N/A | AN90: #N/A N/A | AO90: #N/A N/A | AP90: #N/A N/A | AQ90: #N/A N/A | AR90: #N/A N/A | AS90: #N/A N/A | AT90: #N/A N/A | AU90: #N/A N/A | AV90: #N/A N/A | AW90: #N/A N/A
B91: 45989 | C91: 275.68 | D91: 4.4 | E91: 1.83 | F91: 2.4 | G91: 21.83 | H91: 3.35 | I91: 48.91 | J91: 7.5728 | K91: 51.66 | L91: 54.32 | M91: 257.21 | N91: 35 | O91: 33.61 | P91: 16.99 | Q91: 25.74 | R91: 24.78 | S91: 153.69 | T91: 62.66 | U91: 116.89 | V91: 45.315 | W91: 168.45 | X91: 57.82 | Y91: 44.57 | Z91: 352.28 | AA91: 0.55 | AB91: 24.75 | AC91: 71.32 | AD91: 683.39 | AE91: 4.35 | AF91: 59.3027 | AG91: 14.1595 | AH91: 619.25 | AI91: 108.25 | AJ91: 104.47 | AK91: 118.23 | AL91: 233.22 | AM91: 54.54 | AN91: 23.7903 | AO91: 52.62 | AP91: 4.63 | AQ91: 109.12 | AR91: 63.06 | AS91: 107.58 | AT91: 5.5 | AU91: 329.77 | AV91: 246.07 | AW91: 122.31
B92: 45990 | C92: #N/A N/A | D92: #N/A N/A | E92: #N/A N/A | F92: #N/A N/A | G92: #N/A N/A | H92: #N/A N/A | I92: #N/A N/A | J92: #N/A N/A | K92: #N/A N/A | L92: #N/A N/A | M92: #N/A N/A | N92: #N/A N/A | O92: #N/A N/A | P92: #N/A N/A | Q92: #N/A N/A | R92: #N/A N/A | S92: #N/A N/A | T92: #N/A N/A | U92: #N/A N/A | V92: #N/A N/A | W92: #N/A N/A | X92: #N/A N/A | Y92: #N/A N/A | Z92: #N/A N/A | AA92: #N/A N/A | AB92: #N/A N/A | AC92: #N/A N/A | AD92: #N/A N/A | AE92: #N/A N/A | AF92: #N/A N/A | AG92: #N/A N/A | AH92: #N/A N/A | AI92: #N/A N/A | AJ92: #N/A N/A | AK92: #N/A N/A | AL92: #N/A N/A | AM92: #N/A N/A | AN92: #N/A N/A | AO92: #N/A N/A | AP92: #N/A N/A | AQ92: #N/A N/A | AR92: #N/A N/A | AS92: #N/A N/A | AT92: #N/A N/A | AU92: #N/A N/A | AV92: #N/A N/A | AW92: #N/A N/A
B93: 45991 | C93: #N/A N/A | D93: #N/A N/A | E93: #N/A N/A | F93: #N/A N/A | G93: #N/A N/A | H93: #N/A N/A | I93: #N/A N/A | J93: #N/A N/A | K93: #N/A N/A | L93: #N/A N/A | M93: #N/A N/A | N93: #N/A N/A | O93: #N/A N/A | P93: #N/A N/A | Q93: #N/A N/A | R93: #N/A N/A | S93: #N/A N/A | T93: #N/A N/A | U93: #N/A N/A | V93: #N/A N/A | W93: #N/A N/A | X93: #N/A N/A | Y93: #N/A N/A | Z93: #N/A N/A | AA93: #N/A N/A | AB93: #N/A N/A | AC93: #N/A N/A | AD93: #N/A N/A | AE93: #N/A N/A | AF93: #N/A N/A | AG93: #N/A N/A | AH93: #N/A N/A | AI93: #N/A N/A | AJ93: #N/A N/A | AK93: #N/A N/A | AL93: #N/A N/A | AM93: #N/A N/A | AN93: #N/A N/A | AO93: #N/A N/A | AP93: #N/A N/A | AQ93: #N/A N/A | AR93: #N/A N/A | AS93: #N/A N/A | AT93: #N/A N/A | AU93: #N/A N/A | AV93: #N/A N/A | AW93: #N/A N/A
B94: 45992 | C94: 273.34 | D94: 4.52 | E94: 1.83 | F94: 2.42 | G94: 21.35 | H94: 3.37 | I94: 47.64 | J94: 7.466 | K94: 51.57 | L94: 54.28 | M94: 254.95 | N94: 34.83 | O94: 33.4 | P94: 16.55 | Q94: 25.27 | R94: 25.22 | S94: 151.44 | T94: 62.58 | U94: 119.71 | V94: 44.255 | W94: 167.49 | X94: 57.42 | Y94: 44.41 | Z94: 352.96 | AA94: 0.53 | AB94: 24.32 | AC94: 70.78 | AD94: 680.27 | AE94: 4.4 | AF94: 58.364 | AG94: 14.05 | AH94: 617.17 | AI94: 108.22 | AJ94: 106.77 | AK94: 118.3 | AL94: 233.88 | AM94: 54.05 | AN94: 24.16 | AO94: 52.97 | AP94: 4.82 | AQ94: 108.54 | AR94: 62.3 | AS94: 109.13 | AT94: 5.18 | AU94: 323.21 | AV94: 249.34 | AW94: 122.19
B95: 45993 | C95: 270.37 | D95: 4.5 | E95: #N/A N/A | F95: 2.42 | G95: 19.66 | H95: 3.41 | I95: 47.63 | J95: 7.6602 | K95: 52.02 | L95: 54.3 | M95: 261.23 | N95: 35.21 | O95: 34.03 | P95: 16.72 | Q95: 25.15 | R95: 25.03 | S95: 152.76 | T95: 62.95 | U95: 118.99 | V95: 43.94 | W95: 170.69 | X95: 57.94 | Y95: 44.44 | Z95: 359.43 | AA95: 0.53 | AB95: 24.75 | AC95: 70.79 | AD95: 681.53 | AE95: 4.41 | AF95: 58.1702 | AG95: 14.3 | AH95: 622 | AI95: 107.85 | AJ95: 104.83 | AK95: 118.22 | AL95: 234.42 | AM95: 55.3 | AN95: 23.925 | AO95: 52.31 | AP95: 4.79 | AQ95: 106.95 | AR95: 64.07 | AS95: 109.35 | AT95: 5.03 | AU95: 324.54 | AV95: 246.83 | AW95: 122.68
B96: 45994 | C96: 270.45 | D96: 4.56 | E96: #N/A N/A | F96: 2.42 | G96: 18.87 | H96: 3.41 | I96: 47.38 | J96: 7.6893 | K96: 52.41 | L96: 54.34 | M96: 263.16 | N96: 35.12 | O96: 34.2 | P96: 16.64 | Q96: 25.57 | R96: 25.2 | S96: 154.21 | T96: 63.38 | U96: 117.28 | V96: 43.8 | W96: 176.08 | X96: 58.07 | Y96: 44.79 | Z96: 364.37 | AA96: 0.53 | AB96: 24.75 | AC96: 71.59 | AD96: 683.89 | AE96: 4.42 | AF96: 58.3037 | AG96: 14.34 | AH96: 623.52 | AI96: 109.57 | AJ96: 105.74 | AK96: 119.495 | AL96: 232.38 | AM96: 55.69 | AN96: 23.7113 | AO96: 51.65 | AP96: 4.91 | AQ96: 106.13 | AR96: 64.05 | AS96: 103.96 | AT96: 4.79 | AU96: 339.71 | AV96: 244.95 | AW96: 126.48
B97: 45995 | C97: 274.05 | D97: 4.58 | E97: 1.82 | F97: 2.41 | G97: 19.5 | H97: 3.44 | I97: 48.04 | J97: 7.835 | K97: 52.49 | L97: 54.33 | M97: 277.65 | N97: 35.2 | O97: 34.72 | P97: 16.97 | Q97: 25.7 | R97: 25.31 | S97: 155.01 | T97: 63.35 | U97: 118.72 | V97: 43.71 | W97: 177.92 | X97: 57.91 | Y97: 44.75 | Z97: 361.6 | AA97: 0.53 | AB97: 24.35 | AC97: 71.54 | AD97: 684.39 | AE97: 4.43 | AF97: 58.1692 | AG97: 14.59 | AH97: 622.94 | AI97: 110.25 | AJ97: 105.47 | AK97: 119.07 | AL97: 229.11 | AM97: 55.51 | AN97: 23.8527 | AO97: 52.18 | AP97: 4.96 | AQ97: 104.94 | AR97: 64.4 | AS97: 103.22 | AT97: 5.01 | AU97: 333.49 | AV97: 247.51 | AW97: 128.43
B98: 45996 | C98: 274.29 | D98: 4.54 | E98: 1.82 | F98: 2.39 | G98: 20 | H98: 3.47 | I98: 47.69 | J98: 7.3301 | K98: 52.29 | L98: 54.74 | M98: 272.3 | N98: 35.11 | O98: 32.53 | P98: 16.87 | Q98: 26.03 | R98: 25.25 | S98: 154.58 | T98: 63.34 | U98: 125.66 | V98: 43.3 | W98: 181.76 | X98: 58.03 | Y98: 44.62 | Z98: 364.42 | AA98: 0.54 | AB98: 24.85 | AC98: 71.68 | AD98: 685.69 | AE98: 4.35 | AF98: 58.0071 | AG98: 13.42 | AH98: 625.48 | AI98: 111.68 | AJ98: 105.3 | AK98: 119.73 | AL98: 229.53 | AM98: 56.15 | AN98: 24.19 | AO98: 52.92 | AP98: 4.97 | AQ98: 102.96 | AR98: 62.41 | AS98: 100.24 | AT98: 5.04 | AU98: 330.91 | AV98: 247.88 | AW98: 129.42
B99: 45997 | C99: #N/A N/A | D99: #N/A N/A | E99: #N/A N/A | F99: #N/A N/A | G99: #N/A N/A | H99: #N/A N/A | I99: #N/A N/A | J99: #N/A N/A | K99: #N/A N/A | L99: #N/A N/A | M99: #N/A N/A | N99: #N/A N/A | O99: #N/A N/A | P99: #N/A N/A | Q99: #N/A N/A | R99: #N/A N/A | S99: #N/A N/A | T99: #N/A N/A | U99: #N/A N/A | V99: #N/A N/A | W99: #N/A N/A | X99: #N/A N/A | Y99: #N/A N/A | Z99: #N/A N/A | AA99: #N/A N/A | AB99: #N/A N/A | AC99: #N/A N/A | AD99: #N/A N/A | AE99: #N/A N/A | AF99: #N/A N/A | AG99: #N/A N/A | AH99: #N/A N/A | AI99: #N/A N/A | AJ99: #N/A N/A | AK99: #N/A N/A | AL99: #N/A N/A | AM99: #N/A N/A | AN99: #N/A N/A | AO99: #N/A N/A | AP99: #N/A N/A | AQ99: #N/A N/A | AR99: #N/A N/A | AS99: #N/A N/A | AT99: #N/A N/A | AU99: #N/A N/A | AV99: #N/A N/A | AW99: #N/A N/A
B100: 45998 | C100: #N/A N/A | D100: #N/A N/A | E100: #N/A N/A | F100: #N/A N/A | G100: #N/A N/A | H100: #N/A N/A | I100: #N/A N/A | J100: #N/A N/A | K100: #N/A N/A | L100: #N/A N/A | M100: #N/A N/A | N100: #N/A N/A | O100: #N/A N/A | P100: #N/A N/A | Q100: #N/A N/A | R100: #N/A N/A | S100: #N/A N/A | T100: #N/A N/A | U100: #N/A N/A | V100: #N/A N/A | W100: #N/A N/A | X100: #N/A N/A | Y100: #N/A N/A | Z100: #N/A N/A | AA100: #N/A N/A | AB100: #N/A N/A | AC100: #N/A N/A | AD100: #N/A N/A | AE100: #N/A N/A | AF100: #N/A N/A | AG100: #N/A N/A | AH100: #N/A N/A | AI100: #N/A N/A | AJ100: #N/A N/A | AK100: #N/A N/A | AL100: #N/A N/A | AM100: #N/A N/A | AN100: #N/A N/A | AO100: #N/A N/A | AP100: #N/A N/A | AQ100: #N/A N/A | AR100: #N/A N/A | AS100: #N/A N/A | AT100: #N/A N/A | AU100: #N/A N/A | AV100: #N/A N/A | AW100: #N/A N/A
B101: 45999 | C101: 276.64 | D101: #N/A N/A | E101: #N/A N/A | F101: #N/A N/A | G101: 20.52 | H101: #N/A N/A | I101: 47.59 | J101: 7.3495 | K101: 52.31 | L101: 54.62 | M101: 269.34 | N101: 35.15 | O101: 32.75 | P101: 16.7 | Q101: 25.77 | R101: 24.88 | S101: 154.39 | T101: 63.38 | U101: 130.06 | V101: 42.72 | W101: 181.49 | X101: 57.76 | Y101: 44.65 | Z101: 368.55 | AA101: #N/A N/A | AB101: #N/A N/A | AC101: 71.24 | AD101: 683.63 | AE101: #N/A N/A | AF101: 57.5333 | AG101: 13.4481 | AH101: 624.28 | AI101: 111.33 | AJ101: 107.63 | AK101: 117.99 | AL101: 226.89 | AM101: 55.8 | AN101: 24.36 | AO101: 53.35 | AP101: 4.79 | AQ101: 101.85 | AR101: 62.41 | AS101: 96.79 | AT101: 5.1 | AU101: 323.62 | AV101: 247.28 | AW101: 130.24
...

Sheet BP
C2: FDX | D2: MINSURI1 | E2: SIDERC1 | F2: ORYGENC1 | G2: XPEV | H2: FERREYC1 | I2: TAN | J2: ITUB | K2: EWP | L2: EEM | M2: BAP | N2: EUFN | O2: EWZ | P2: ICLN | Q2: PFE | R2: BVN | S2: XLI | T2: EZU | U2: BIDU | V2: XLU | W2: PLTR | X2: EWL | Y2: EWQ | Z2: SMH | AA2: VOLCABC1 | AB2: INRETC1 | AC2: JAVA | AD2: SPY | AE2: CPACASC1 | AF2: JDOC | AG2: EWZS | AH2: QQQ | AI2: PRU | AJ2: DIS | AK2: XLY | AL2: AMZN | AM2: TQQQ | AN2: TCHI | AO2: CQQQ | AP2: AUNA | AQ2: KMB | AR2: CIB | AS2: NFLX | AT2: NIO | AU2: UNH | AV2: TTWO | AW2: KKR
B3: 45901 | C3: {=_xll.BDH(C$2 & " US Equity","PX_LAST",$B3,$B3)} -> #N/A N/A | D3: {=_xll.BDH(D$2 & " PE Equity","PX_LAST",$B3,$B3)} -> 3.98 | E3: {=_xll.BDH(E$2 & " PE Equity","PX_LAST",$B3,$B3)} -> 1.76 | F3: {=_xll.BDH(F$2 & " PE Equity","PX_LAST",$B3,$B3)} -> 2.55 | G3: {=_xll.BDH(G$2 & " US Equity","PX_LAST",$B3,$B3)} -> #N/A N/A | H3: {=_xll.BDH(H$2 & " PE Equity","PX_LAST",$B3,$B3)} -> 3.49 | I3: {=_xll.BDH(I$2 & " US Equity","PX_LAST",$B3,$B3)} -> #N/A N/A | J3: {=_xll.BDH(J$2 & " US Equity","PX_LAST",$B3,$B3)} -> #N/A N/A | K3: {=_xll.BDH(K$2 & " US Equity","PX_LAST",$B3,$B3)} -> #N/A N/A | L3: {=_xll.BDH(L$2 & " US Equity","PX_LAST",$B3,$B3)} -> #N/A N/A | M3: {=_xll.BDH(M$2 & " US Equity","PX_LAST",$B3,$B3)} -> #N/A N/A | N3: {=_xll.BDH(N$2 & " US Equity","PX_LAST",$B3,$B3)} -> #N/A N/A | O3: {=_xll.BDH(O$2 & " US Equity","PX_LAST",$B3,$B3)} -> #N/A N/A | P3: {=_xll.BDH(P$2 & " US Equity","PX_LAST",$B3,$B3)} -> #N/A N/A | ... Z3: {=_xll.BDH(Z$2 & " US Equity","PX_LAST",$B3,$B3)} -> #N/A N/A | AA3: {=_xll.BDH(AA$2 & " PE Equity","PX_LAST",$B3,$B3)} -> 0.376 | AB3: {=_xll.BDH(AB$2 & " PE Equity","PX_LAST",$B3,$B3)} -> 27.5 | AC3: {=_xll.BDH(AC$2 & " US Equity","PX_LAST",$B3,$B3)} -> #N/A N/A | AD3: {=_xll.BDH(AD$2 & " US Equity","PX_LAST",$B3,$B3)} -> #N/A N/A | AE3: {=_xll.BDH(AE$2 & " PE Equity","PX_LAST",$B3,$B3)} -> #N/A Connection | AF3: {=_xll.BDH(AF$2 & " US Equity","PX_LAST",$B3,$B3)} -> #N/A N/A | AG3: {=_xll.BDH(AG$2 & " US Equity","PX_LAST",$B3,$B3)} -> #N/A N/A | AH3: {=_xll.BDH(AH$2 & " US Equity","PX_LAST",$B3,$B3)} -> #N/A N/A | AI3: {=_xll.BDH(AI$2 & " US Equity","PX_LAST",$B3,$B3)} -> #N/A N/A | AJ3: {=_xll.BDH(AJ$2 & " US Equity","PX_LAST",$B3,$B3)} -> #N/A N/A | AK3: {=_xll.BDH(AK$2 & " US Equity","PX_LAST",$B3,$B3)} -> #N/A N/A | AL3: {=_xll.BDH(AL$2 & " US Equity","PX_LAST",$B3,$B3)} -> #N/A N/A | AM3: {=_xll.BDH(AM$2 & " US Equity","PX_LAST",$B3,$B3)} -> #N/A N/A | ... AW3: {=_xll.BDH(AW$2 & " US Equity","PX_LAST",$B3,$B3)} -> #N/A N/A
B4: 45902 | C4: {=_xll.BDH(C$2 & " US Equity","PX_LAST",$B4,$B4)} -> 224.18 | D4: {=_xll.BDH(D$2 & " PE Equity","PX_LAST",$B4,$B4)} -> 3.99 | E4: {=_xll.BDH(E$2 & " PE Equity","PX_LAST",$B4,$B4)} -> 1.74 | F4: {=_xll.BDH(F$2 & " PE Equity","PX_LAST",$B4,$B4)} -> 2.55 | G4: {=_xll.BDH(G$2 & " US Equity","PX_LAST",$B4,$B4)} -> 20.79 | H4: {=_xll.BDH(H$2 & " PE Equity","PX_LAST",$B4,$B4)} -> 3.47 | I4: {=_xll.BDH(I$2 & " US Equity","PX_LAST",$B4,$B4)} -> 40.98 | J4: {=_xll.BDH(J$2 & " US Equity","PX_LAST",$B4,$B4)} -> 6.8058 | K4: {=_xll.BDH(K$2 & " US Equity","PX_LAST",$B4,$B4)} -> 47.02 | L4: {=_xll.BDH(L$2 & " US Equity","PX_LAST",$B4,$B4)} -> 49.82 | M4: {=_xll.BDH(M$2 & " US Equity","PX_LAST",$B4,$B4)} -> 260.11 | N4: {=_xll.BDH(N$2 & " US Equity","PX_LAST",$B4,$B4)} -> 32.97 | O4: {=_xll.BDH(O$2 & " US Equity","PX_LAST",$B4,$B4)} -> 29 | P4: {=_xll.BDH(P$2 & " US Equity","PX_LAST",$B4,$B4)} -> 14.16 | ... Z4: {=_xll.BDH(Z$2 & " US Equity","PX_LAST",$B4,$B4)} -> 286.48 | AA4: {=_xll.BDH(AA$2 & " PE Equity","PX_LAST",$B4,$B4)} -> 0.384 | AB4: {=_xll.BDH(AB$2 & " PE Equity","PX_LAST",$B4,$B4)} -> 27.94 | AC4: {=_xll.BDH(AC$2 & " US Equity","PX_LAST",$B4,$B4)} -> 67.81 | AD4: {=_xll.BDH(AD$2 & " US Equity","PX_LAST",$B4,$B4)} -> 640.27 | AE4: {=_xll.BDH(AE$2 & " PE Equity","PX_LAST",$B4,$B4)} -> #N/A Connection | AF4: {=_xll.BDH(AF$2 & " US Equity","PX_LAST",$B4,$B4)} -> 51.593 | AG4: {=_xll.BDH(AG$2 & " US Equity","PX_LAST",$B4,$B4)} -> 13.1551 | AH4: {=_xll.BDH(AH$2 & " US Equity","PX_LAST",$B4,$B4)} -> 565.62 | AI4: {=_xll.BDH(AI$2 & " US Equity","PX_LAST",$B4,$B4)} -> 107.41 | AJ4: {=_xll.BDH(AJ$2 & " US Equity","PX_LAST",$B4,$B4)} -> 118.27 | AK4: {=_xll.BDH(AK$2 & " US Equity","PX_LAST",$B4,$B4)} -> 115.005 | AL4: {=_xll.BDH(AL$2 & " US Equity","PX_LAST",$B4,$B4)} -> 225.34 | AM4: {=_xll.BDH(AM$2 & " US Equity","PX_LAST",$B4,$B4)} -> 43.54 | ... AW4: {=_xll.BDH(AW$2 & " US Equity","PX_LAST",$B4,$B4)} -> 138.74
B5: 45903 | C5: {=_xll.BDH(C$2 & " US Equity","PX_LAST",$B5,$B5)} -> 225.34 | D5: {=_xll.BDH(D$2 & " PE Equity","PX_LAST",$B5,$B5)} -> 4 | E5: {=_xll.BDH(E$2 & " PE Equity","PX_LAST",$B5,$B5)} -> 1.66 | F5: {=_xll.BDH(F$2 & " PE Equity","PX_LAST",$B5,$B5)} -> 2.56 | G5: {=_xll.BDH(G$2 & " US Equity","PX_LAST",$B5,$B5)} -> 20.25 | H5: {=_xll.BDH(H$2 & " PE Equity","PX_LAST",$B5,$B5)} -> 3.48 | I5: {=_xll.BDH(I$2 & " US Equity","PX_LAST",$B5,$B5)} -> 41.57 | J5: {=_xll.BDH(J$2 & " US Equity","PX_LAST",$B5,$B5)} -> 6.7379 | K5: {=_xll.BDH(K$2 & " US Equity","PX_LAST",$B5,$B5)} -> 47.05 | L5: {=_xll.BDH(L$2 & " US Equity","PX_LAST",$B5,$B5)} -> 50.01 | M5: {=_xll.BDH(M$2 & " US Equity","PX_LAST",$B5,$B5)} -> 261.56 | N5: {=_xll.BDH(N$2 & " US Equity","PX_LAST",$B5,$B5)} -> 32.99 | O5: {=_xll.BDH(O$2 & " US Equity","PX_LAST",$B5,$B5)} -> 28.99 | P5: {=_xll.BDH(P$2 & " US Equity","PX_LAST",$B5,$B5)} -> 14.2 | ... Z5: {=_xll.BDH(Z$2 & " US Equity","PX_LAST",$B5,$B5)} -> 286.43 | AA5: {=_xll.BDH(AA$2 & " PE Equity","PX_LAST",$B5,$B5)} -> 0.4 | AB5: {=_xll.BDH(AB$2 & " PE Equity","PX_LAST",$B5,$B5)} -> 27.9 | AC5: {=_xll.BDH(AC$2 & " US Equity","PX_LAST",$B5,$B5)} -> 67.64 | AD5: {=_xll.BDH(AD$2 & " US Equity","PX_LAST",$B5,$B5)} -> 643.74 | AE5: {=_xll.BDH(AE$2 & " PE Equity","PX_LAST",$B5,$B5)} -> #N/A Connection | AF5: {=_xll.BDH(AF$2 & " US Equity","PX_LAST",$B5,$B5)} -> 51.6447 | AG5: {=_xll.BDH(AG$2 & " US Equity","PX_LAST",$B5,$B5)} -> 13.1886 | AH5: {=_xll.BDH(AH$2 & " US Equity","PX_LAST",$B5,$B5)} -> 570.07 | AI5: {=_xll.BDH(AI$2 & " US Equity","PX_LAST",$B5,$B5)} -> 107.43 | AJ5: {=_xll.BDH(AJ$2 & " US Equity","PX_LAST",$B5,$B5)} -> 117.38 | AK5: {=_xll.BDH(AK$2 & " US Equity","PX_LAST",$B5,$B5)} -> 115.47 | AL5: {=_xll.BDH(AL$2 & " US Equity","PX_LAST",$B5,$B5)} -> 225.99 | AM5: {=_xll.BDH(AM$2 & " US Equity","PX_LAST",$B5,$B5)} -> 44.555 | ... AW5: {=_xll.BDH(AW$2 & " US Equity","PX_LAST",$B5,$B5)} -> 134.83
B6: 45904 | C6: {=_xll.BDH(C$2 & " US Equity","PX_LAST",$B6,$B6)} -> 225.28 | D6: {=_xll.BDH(D$2 & " PE Equity","PX_LAST",$B6,$B6)} -> 4 | E6: {=_xll.BDH(E$2 & " PE Equity","PX_LAST",$B6,$B6)} -> #N/A N/A | F6: {=_xll.BDH(F$2 & " PE Equity","PX_LAST",$B6,$B6)} -> 2.54 | G6: {=_xll.BDH(G$2 & " US Equity","PX_LAST",$B6,$B6)} -> 19.84 | H6: {=_xll.BDH(H$2 & " PE Equity","PX_LAST",$B6,$B6)} -> 3.48 | I6: {=_xll.BDH(I$2 & " US Equity","PX_LAST",$B6,$B6)} -> 42.02 | J6: {=_xll.BDH(J$2 & " US Equity","PX_LAST",$B6,$B6)} -> 6.7864 | K6: {=_xll.BDH(K$2 & " US Equity","PX_LAST",$B6,$B6)} -> 47.48 | L6: {=_xll.BDH(L$2 & " US Equity","PX_LAST",$B6,$B6)} -> 49.85 | M6: {=_xll.BDH(M$2 & " US Equity","PX_LAST",$B6,$B6)} -> 259.98 | N6: {=_xll.BDH(N$2 & " US Equity","PX_LAST",$B6,$B6)} -> 33.37 | O6: {=_xll.BDH(O$2 & " US Equity","PX_LAST",$B6,$B6)} -> 29.17 | P6: {=_xll.BDH(P$2 & " US Equity","PX_LAST",$B6,$B6)} -> 14.33 | ... Z6: {=_xll.BDH(Z$2 & " US Equity","PX_LAST",$B6,$B6)} -> 289.86 | AA6: {=_xll.BDH(AA$2 & " PE Equity","PX_LAST",$B6,$B6)} -> 0.4 | AB6: {=_xll.BDH(AB$2 & " PE Equity","PX_LAST",$B6,$B6)} -> 27.5 | AC6: {=_xll.BDH(AC$2 & " US Equity","PX_LAST",$B6,$B6)} -> 68.25 | AD6: {=_xll.BDH(AD$2 & " US Equity","PX_LAST",$B6,$B6)} -> 649.12 | AE6: {=_xll.BDH(AE$2 & " PE Equity","PX_LAST",$B6,$B6)} -> #N/A Connection | AF6: {=_xll.BDH(AF$2 & " US Equity","PX_LAST",$B6,$B6)} -> 51.7739 | AG6: {=_xll.BDH(AG$2 & " US Equity","PX_LAST",$B6,$B6)} -> 13.3765 | AH6: {=_xll.BDH(AH$2 & " US Equity","PX_LAST",$B6,$B6)} -> 575.23 | AI6: {=_xll.BDH(AI$2 & " US Equity","PX_LAST",$B6,$B6)} -> 108.84 | AJ6: {=_xll.BDH(AJ$2 & " US Equity","PX_LAST",$B6,$B6)} -> 118.81 | AK6: {=_xll.BDH(AK$2 & " US Equity","PX_LAST",$B6,$B6)} -> 117.58 | AL6: {=_xll.BDH(AL$2 & " US Equity","PX_LAST",$B6,$B6)} -> 235.68 | AM6: {=_xll.BDH(AM$2 & " US Equity","PX_LAST",$B6,$B6)} -> 45.76 | ... AW6: {=_xll.BDH(AW$2 & " US Equity","PX_LAST",$B6,$B6)} -> 137.35
B7: 45905 | C7: {=_xll.BDH(C$2 & " US Equity","PX_LAST",$B7,$B7)} -> 227.72 | D7: {=_xll.BDH(D$2 & " PE Equity","PX_LAST",$B7,$B7)} -> 4 | E7: {=_xll.BDH(E$2 & " PE Equity","PX_LAST",$B7,$B7)} -> #N/A N/A | F7: {=_xll.BDH(F$2 & " PE Equity","PX_LAST",$B7,$B7)} -> 2.59 | G7: {=_xll.BDH(G$2 & " US Equity","PX_LAST",$B7,$B7)} -> 19.83 | H7: {=_xll.BDH(H$2 & " PE Equity","PX_LAST",$B7,$B7)} -> 3.47 | I7: {=_xll.BDH(I$2 & " US Equity","PX_LAST",$B7,$B7)} -> 44.04 | J7: {=_xll.BDH(J$2 & " US Equity","PX_LAST",$B7,$B7)} -> 6.8932 | K7: {=_xll.BDH(K$2 & " US Equity","PX_LAST",$B7,$B7)} -> 47.6 | L7: {=_xll.BDH(L$2 & " US Equity","PX_LAST",$B7,$B7)} -> 50.45 | M7: {=_xll.BDH(M$2 & " US Equity","PX_LAST",$B7,$B7)} -> 261.2 | N7: {=_xll.BDH(N$2 & " US Equity","PX_LAST",$B7,$B7)} -> 33.31 | O7: {=_xll.BDH(O$2 & " US Equity","PX_LAST",$B7,$B7)} -> 29.63 | P7: {=_xll.BDH(P$2 & " US Equity","PX_LAST",$B7,$B7)} -> 14.68 | ... Z7: {=_xll.BDH(Z$2 & " US Equity","PX_LAST",$B7,$B7)} -> 293.28 | AA7: {=_xll.BDH(AA$2 & " PE Equity","PX_LAST",$B7,$B7)} -> 0.4 | AB7: {=_xll.BDH(AB$2 & " PE Equity","PX_LAST",$B7,$B7)} -> 27.1 | AC7: {=_xll.BDH(AC$2 & " US Equity","PX_LAST",$B7,$B7)} -> 68.06 | AD7: {=_xll.BDH(AD$2 & " US Equity","PX_LAST",$B7,$B7)} -> 647.24 | AE7: {=_xll.BDH(AE$2 & " PE Equity","PX_LAST",$B7,$B7)} -> #N/A Connection | AF7: {=_xll.BDH(AF$2 & " US Equity","PX_LAST",$B7,$B7)} -> 51.9817 | AG7: {=_xll.BDH(AG$2 & " US Equity","PX_LAST",$B7,$B7)} -> 13.7 | AH7: {=_xll.BDH(AH$2 & " US Equity","PX_LAST",$B7,$B7)} -> 576.06 | AI7: {=_xll.BDH(AI$2 & " US Equity","PX_LAST",$B7,$B7)} -> 105.71 | AJ7: {=_xll.BDH(AJ$2 & " US Equity","PX_LAST",$B7,$B7)} -> 117.91 | AK7: {=_xll.BDH(AK$2 & " US Equity","PX_LAST",$B7,$B7)} -> 117.555 | AL7: {=_xll.BDH(AL$2 & " US Equity","PX_LAST",$B7,$B7)} -> 232.33 | AM7: {=_xll.BDH(AM$2 & " US Equity","PX_LAST",$B7,$B7)} -> 45.91 | ... AW7: {=_xll.BDH(AW$2 & " US Equity","PX_LAST",$B7,$B7)} -> 135.53
B8: 45906 | C8: {=_xll.BDH(C$2 & " US Equity","PX_LAST",$B8,$B8)} -> #N/A N/A | D8: {=_xll.BDH(D$2 & " PE Equity","PX_LAST",$B8,$B8)} -> #N/A N/A | E8: {=_xll.BDH(E$2 & " PE Equity","PX_LAST",$B8,$B8)} -> #N/A N/A | F8: {=_xll.BDH(F$2 & " PE Equity","PX_LAST",$B8,$B8)} -> #N/A N/A | G8: {=_xll.BDH(G$2 & " US Equity","PX_LAST",$B8,$B8)} -> #N/A N/A | H8: {=_xll.BDH(H$2 & " PE Equity","PX_LAST",$B8,$B8)} -> #N/A N/A | I8: {=_xll.BDH(I$2 & " US Equity","PX_LAST",$B8,$B8)} -> #N/A N/A | J8: {=_xll.BDH(J$2 & " US Equity","PX_LAST",$B8,$B8)} -> #N/A N/A | K8: {=_xll.BDH(K$2 & " US Equity","PX_LAST",$B8,$B8)} -> #N/A N/A | L8: {=_xll.BDH(L$2 & " US Equity","PX_LAST",$B8,$B8)} -> #N/A N/A | M8: {=_xll.BDH(M$2 & " US Equity","PX_LAST",$B8,$B8)} -> #N/A N/A | N8: {=_xll.BDH(N$2 & " US Equity","PX_LAST",$B8,$B8)} -> #N/A N/A | O8: {=_xll.BDH(O$2 & " US Equity","PX_LAST",$B8,$B8)} -> #N/A N/A | P8: {=_xll.BDH(P$2 & " US Equity","PX_LAST",$B8,$B8)} -> #N/A N/A | ... Z8: {=_xll.BDH(Z$2 & " US Equity","PX_LAST",$B8,$B8)} -> #N/A N/A | AA8: {=_xll.BDH(AA$2 & " PE Equity","PX_LAST",$B8,$B8)} -> #N/A N/A | AB8: {=_xll.BDH(AB$2 & " PE Equity","PX_LAST",$B8,$B8)} -> #N/A N/A | AC8: {=_xll.BDH(AC$2 & " US Equity","PX_LAST",$B8,$B8)} -> #N/A N/A | AD8: {=_xll.BDH(AD$2 & " US Equity","PX_LAST",$B8,$B8)} -> #N/A N/A | AE8: {=_xll.BDH(AE$2 & " PE Equity","PX_LAST",$B8,$B8)} -> #N/A Connection | AF8: {=_xll.BDH(AF$2 & " US Equity","PX_LAST",$B8,$B8)} -> #N/A N/A | AG8: {=_xll.BDH(AG$2 & " US Equity","PX_LAST",$B8,$B8)} -> #N/A N/A | AH8: {=_xll.BDH(AH$2 & " US Equity","PX_LAST",$B8,$B8)} -> #N/A N/A | AI8: {=_xll.BDH(AI$2 & " US Equity","PX_LAST",$B8,$B8)} -> #N/A N/A | AJ8: {=_xll.BDH(AJ$2 & " US Equity","PX_LAST",$B8,$B8)} -> #N/A N/A | AK8: {=_xll.BDH(AK$2 & " US Equity","PX_LAST",$B8,$B8)} -> #N/A N/A | AL8: {=_xll.BDH(AL$2 & " US Equity","PX_LAST",$B8,$B8)} -> #N/A N/A | AM8: {=_xll.BDH(AM$2 & " US Equity","PX_LAST",$B8,$B8)} -> #N/A N/A | ... AW8: {=_xll.BDH(AW$2 & " US Equity","PX_LAST",$B8,$B8)} -> #N/A N/A
B9: 45907 | C9: {=_xll.BDH(C$2 & " US Equity","PX_LAST",$B9,$B9)} -> #N/A N/A | D9: {=_xll.BDH(D$2 & " PE Equity","PX_LAST",$B9,$B9)} -> #N/A N/A | E9: {=_xll.BDH(E$2 & " PE Equity","PX_LAST",$B9,$B9)} -> #N/A N/A | F9: {=_xll.BDH(F$2 & " PE Equity","PX_LAST",$B9,$B9)} -> #N/A N/A | G9: {=_xll.BDH(G$2 & " US Equity","PX_LAST",$B9,$B9)} -> #N/A N/A | H9: {=_xll.BDH(H$2 & " PE Equity","PX_LAST",$B9,$B9)} -> #N/A N/A | I9: {=_xll.BDH(I$2 & " US Equity","PX_LAST",$B9,$B9)} -> #N/A N/A | J9: {=_xll.BDH(J$2 & " US Equity","PX_LAST",$B9,$B9)} -> #N/A N/A | K9: {=_xll.BDH(K$2 & " US Equity","PX_LAST",$B9,$B9)} -> #N/A N/A | L9: {=_xll.BDH(L$2 & " US Equity","PX_LAST",$B9,$B9)} -> #N/A N/A | M9: {=_xll.BDH(M$2 & " US Equity","PX_LAST",$B9,$B9)} -> #N/A N/A | N9: {=_xll.BDH(N$2 & " US Equity","PX_LAST",$B9,$B9)} -> #N/A N/A | O9: {=_xll.BDH(O$2 & " US Equity","PX_LAST",$B9,$B9)} -> #N/A N/A | P9: {=_xll.BDH(P$2 & " US Equity","PX_LAST",$B9,$B9)} -> #N/A N/A | ... Z9: {=_xll.BDH(Z$2 & " US Equity","PX_LAST",$B9,$B9)} -> #N/A N/A | AA9: {=_xll.BDH(AA$2 & " PE Equity","PX_LAST",$B9,$B9)} -> #N/A N/A | AB9: {=_xll.BDH(AB$2 & " PE Equity","PX_LAST",$B9,$B9)} -> #N/A N/A | AC9: {=_xll.BDH(AC$2 & " US Equity","PX_LAST",$B9,$B9)} -> #N/A N/A | AD9: {=_xll.BDH(AD$2 & " US Equity","PX_LAST",$B9,$B9)} -> #N/A N/A | AE9: {=_xll.BDH(AE$2 & " PE Equity","PX_LAST",$B9,$B9)} -> #N/A Connection | AF9: {=_xll.BDH(AF$2 & " US Equity","PX_LAST",$B9,$B9)} -> #N/A N/A | AG9: {=_xll.BDH(AG$2 & " US Equity","PX_LAST",$B9,$B9)} -> #N/A N/A | AH9: {=_xll.BDH(AH$2 & " US Equity","PX_LAST",$B9,$B9)} -> #N/A N/A | AI9: {=_xll.BDH(AI$2 & " US Equity","PX_LAST",$B9,$B9)} -> #N/A N/A | AJ9: {=_xll.BDH(AJ$2 & " US Equity","PX_LAST",$B9,$B9)} -> #N/A N/A | AK9: {=_xll.BDH(AK$2 & " US Equity","PX_LAST",$B9,$B9)} -> #N/A N/A | AL9: {=_xll.BDH(AL$2 & " US Equity","PX_LAST",$B9,$B9)} -> #N/A N/A | AM9: {=_xll.BDH(AM$2 & " US Equity","PX_LAST",$B9,$B9)} -> #N/A N/A | ... AW9: {=_xll.BDH(AW$2 & " US Equity","PX_LAST",$B9,$B9)} -> #N/A N/A
B10: 45908 | C10: {=_xll.BDH(C$2 & " US Equity","PX_LAST",$B10,$B10)} -> 225 | D10: {=_xll.BDH(D$2 & " PE Equity","PX_LAST",$B10,$B10)} -> 4 | E10: {=_xll.BDH(E$2 & " PE Equity","PX_LAST",$B10,$B10)} -> #N/A N/A | F10: {=_xll.BDH(F$2 & " PE Equity","PX_LAST",$B10,$B10)} -> 2.54 | G10: {=_xll.BDH(G$2 & " US Equity","PX_LAST",$B10,$B10)} -> 20.58 | H10: {=_xll.BDH(H$2 & " PE Equity","PX_LAST",$B10,$B10)} -> 3.48 | I10: {=_xll.BDH(I$2 & " US Equity","PX_LAST",$B10,$B10)} -> 43.33 | J10: {=_xll.BDH(J$2 & " US Equity","PX_LAST",$B10,$B10)} -> 6.8447 | K10: {=_xll.BDH(K$2 & " US Equity","PX_LAST",$B10,$B10)} -> 48.07 | L10: {=_xll.BDH(L$2 & " US Equity","PX_LAST",$B10,$B10)} -> 50.91 | M10: {=_xll.BDH(M$2 & " US Equity","PX_LAST",$B10,$B10)} -> 263.5 | N10: {=_xll.BDH(N$2 & " US Equity","PX_LAST",$B10,$B10)} -> 33.55 | O10: {=_xll.BDH(O$2 & " US Equity","PX_LAST",$B10,$B10)} -> 29.58 | P10: {=_xll.BDH(P$2 & " US Equity","PX_LAST",$B10,$B10)} -> 14.57 | ... Z10: {=_xll.BDH(Z$2 & " US Equity","PX_LAST",$B10,$B10)} -> 296.52 | AA10: {=_xll.BDH(AA$2 & " PE Equity","PX_LAST",$B10,$B10)} -> 0.383 | AB10: {=_xll.BDH(AB$2 & " PE Equity","PX_LAST",$B10,$B10)} -> 27.5 | AC10: {=_xll.BDH(AC$2 & " US Equity","PX_LAST",$B10,$B10)} -> 68.05 | AD10: {=_xll.BDH(AD$2 & " US Equity","PX_LAST",$B10,$B10)} -> 648.83 | AE10: {=_xll.BDH(AE$2 & " PE Equity","PX_LAST",$B10,$B10)} -> #N/A Connection | AF10: {=_xll.BDH(AF$2 & " US Equity","PX_LAST",$B10,$B10)} -> 52.0234 | AG10: {=_xll.BDH(AG$2 & " US Equity","PX_LAST",$B10,$B10)} -> 13.57 | AH10: {=_xll.BDH(AH$2 & " US Equity","PX_LAST",$B10,$B10)} -> 578.87 | AI10: {=_xll.BDH(AI$2 & " US Equity","PX_LAST",$B10,$B10)} -> 105.84 | AJ10: {=_xll.BDH(AJ$2 & " US Equity","PX_LAST",$B10,$B10)} -> 118.84 | AK10: {=_xll.BDH(AK$2 & " US Equity","PX_LAST",$B10,$B10)} -> 118.01 | AL10: {=_xll.BDH(AL$2 & " US Equity","PX_LAST",$B10,$B10)} -> 235.84 | AM10: {=_xll.BDH(AM$2 & " US Equity","PX_LAST",$B10,$B10)} -> 46.565 | ... AW10: {=_xll.BDH(AW$2 & " US Equity","PX_LAST",$B10,$B10)} -> 138.69
B11: 45909 | C11: {=_xll.BDH(C$2 & " US Equity","PX_LAST",$B11,$B11)} -> 225.75 | D11: {=_xll.BDH(D$2 & " PE Equity","PX_LAST",$B11,$B11)} -> 3.99 | E11: {=_xll.BDH(E$2 & " PE Equity","PX_LAST",$B11,$B11)} -> 1.75 | F11: {=_xll.BDH(F$2 & " PE Equity","PX_LAST",$B11,$B11)} -> 2.54 | G11: {=_xll.BDH(G$2 & " US Equity","PX_LAST",$B11,$B11)} -> 20.75 | H11: {=_xll.BDH(H$2 & " PE Equity","PX_LAST",$B11,$B11)} -> 3.46 | I11: {=_xll.BDH(I$2 & " US Equity","PX_LAST",$B11,$B11)} -> 41.97 | J11: {=_xll.BDH(J$2 & " US Equity","PX_LAST",$B11,$B11)} -> 6.7864 | K11: {=_xll.BDH(K$2 & " US Equity","PX_LAST",$B11,$B11)} -> 48.08 | L11: {=_xll.BDH(L$2 & " US Equity","PX_LAST",$B11,$B11)} -> 51.19 | M11: {=_xll.BDH(M$2 & " US Equity","PX_LAST",$B11,$B11)} -> 263.92 | N11: {=_xll.BDH(N$2 & " US Equity","PX_LAST",$B11,$B11)} -> 33.57 | O11: {=_xll.BDH(O$2 & " US Equity","PX_LAST",$B11,$B11)} -> 29.54 | P11: {=_xll.BDH(P$2 & " US Equity","PX_LAST",$B11,$B11)} -> 14.39 | ... Z11: {=_xll.BDH(Z$2 & " US Equity","PX_LAST",$B11,$B11)} -> 297.81 | AA11: {=_xll.BDH(AA$2 & " PE Equity","PX_LAST",$B11,$B11)} -> 0.375 | AB11: {=_xll.BDH(AB$2 & " PE Equity","PX_LAST",$B11,$B11)} -> 27.5 | AC11: {=_xll.BDH(AC$2 & " US Equity","PX_LAST",$B11,$B11)} -> 68.08 | AD11: {=_xll.BDH(AD$2 & " US Equity","PX_LAST",$B11,$B11)} -> 650.33 | AE11: {=_xll.BDH(AE$2 & " PE Equity","PX_LAST",$B11,$B11)} -> #N/A Connection | AF11: {=_xll.BDH(AF$2 & " US Equity","PX_LAST",$B11,$B11)} -> 52.1809 | AG11: {=_xll.BDH(AG$2 & " US Equity","PX_LAST",$B11,$B11)} -> 13.49 | AH11: {=_xll.BDH(AH$2 & " US Equity","PX_LAST",$B11,$B11)} -> 580.51 | AI11: {=_xll.BDH(AI$2 & " US Equity","PX_LAST",$B11,$B11)} -> 105.54 | AJ11: {=_xll.BDH(AJ$2 & " US Equity","PX_LAST",$B11,$B11)} -> 117.37 | AK11: {=_xll.BDH(AK$2 & " US Equity","PX_LAST",$B11,$B11)} -> 117.845 | AL11: {=_xll.BDH(AL$2 & " US Equity","PX_LAST",$B11,$B11)} -> 238.24 | AM11: {=_xll.BDH(AM$2 & " US Equity","PX_LAST",$B11,$B11)} -> 46.945 | ... AW11: {=_xll.BDH(AW$2 & " US Equity","PX_LAST",$B11,$B11)} -> 137.39
B12: 45910 | C12: {=_xll.BDH(C$2 & " US Equity","PX_LAST",$B12,$B12)} -> 225.69 | D12: {=_xll.BDH(D$2 & " PE Equity","PX_LAST",$B12,$B12)} -> 3.99 | E12: {=_xll.BDH(E$2 & " PE Equity","PX_LAST",$B12,$B12)} -> 1.77 | F12: {=_xll.BDH(F$2 & " PE Equity","PX_LAST",$B12,$B12)} -> 2.59 | G12: {=_xll.BDH(G$2 & " US Equity","PX_LAST",$B12,$B12)} -> 20.1 | H12: {=_xll.BDH(H$2 & " PE Equity","PX_LAST",$B12,$B12)} -> 3.45 | I12: {=_xll.BDH(I$2 & " US Equity","PX_LAST",$B12,$B12)} -> 41.91 | J12: {=_xll.BDH(J$2 & " US Equity","PX_LAST",$B12,$B12)} -> 6.835 | K12: {=_xll.BDH(K$2 & " US Equity","PX_LAST",$B12,$B12)} -> 48.47 | L12: {=_xll.BDH(L$2 & " US Equity","PX_LAST",$B12,$B12)} -> 51.54 | M12: {=_xll.BDH(M$2 & " US Equity","PX_LAST",$B12,$B12)} -> 264.18 | N12: {=_xll.BDH(N$2 & " US Equity","PX_LAST",$B12,$B12)} -> 33.71 | O12: {=_xll.BDH(O$2 & " US Equity","PX_LAST",$B12,$B12)} -> 29.79 | P12: {=_xll.BDH(P$2 & " US Equity","PX_LAST",$B12,$B12)} -> 14.555 | ... Z12: {=_xll.BDH(Z$2 & " US Equity","PX_LAST",$B12,$B12)} -> 300.83 | AA12: {=_xll.BDH(AA$2 & " PE Equity","PX_LAST",$B12,$B12)} -> 0.392 | AB12: {=_xll.BDH(AB$2 & " PE Equity","PX_LAST",$B12,$B12)} -> 27.45 | AC12: {=_xll.BDH(AC$2 & " US Equity","PX_LAST",$B12,$B12)} -> 68.11 | AD12: {=_xll.BDH(AD$2 & " US Equity","PX_LAST",$B12,$B12)} -> 652.21 | AE12: {=_xll.BDH(AE$2 & " PE Equity","PX_LAST",$B12,$B12)} -> #N/A Connection | AF12: {=_xll.BDH(AF$2 & " US Equity","PX_LAST",$B12,$B12)} -> 51.6893 | AG12: {=_xll.BDH(AG$2 & " US Equity","PX_LAST",$B12,$B12)} -> 13.5454 | AH12: {=_xll.BDH(AH$2 & " US Equity","PX_LAST",$B12,$B12)} -> 580.7 | AI12: {=_xll.BDH(AI$2 & " US Equity","PX_LAST",$B12,$B12)} -> 105.67 | AJ12: {=_xll.BDH(AJ$2 & " US Equity","PX_LAST",$B12,$B12)} -> 115.79 | AK12: {=_xll.BDH(AK$2 & " US Equity","PX_LAST",$B12,$B12)} -> 116.435 | AL12: {=_xll.BDH(AL$2 & " US Equity","PX_LAST",$B12,$B12)} -> 230.33 | AM12: {=_xll.BDH(AM$2 & " US Equity","PX_LAST",$B12,$B12)} -> 46.995 | ... AW12: {=_xll.BDH(AW$2 & " US Equity","PX_LAST",$B12,$B12)} -> 139.29
B13: 45911 | C13: {=_xll.BDH(C$2 & " US Equity","PX_LAST",$B13,$B13)} -> 228.81 | D13: {=_xll.BDH(D$2 & " PE Equity","PX_LAST",$B13,$B13)} -> 4.01 | E13: {=_xll.BDH(E$2 & " PE Equity","PX_LAST",$B13,$B13)} -> #N/A N/A | F13: {=_xll.BDH(F$2 & " PE Equity","PX_LAST",$B13,$B13)} -> 2.57 | G13: {=_xll.BDH(G$2 & " US Equity","PX_LAST",$B13,$B13)} -> 20.58 | H13: {=_xll.BDH(H$2 & " PE Equity","PX_LAST",$B13,$B13)} -> 3.45 | I13: {=_xll.BDH(I$2 & " US Equity","PX_LAST",$B13,$B13)} -> 41.86 | J13: {=_xll.BDH(J$2 & " US Equity","PX_LAST",$B13,$B13)} -> 6.8738 | K13: {=_xll.BDH(K$2 & " US Equity","PX_LAST",$B13,$B13)} -> 48.98 | L13: {=_xll.BDH(L$2 & " US Equity","PX_LAST",$B13,$B13)} -> 52.29 | M13: {=_xll.BDH(M$2 & " US Equity","PX_LAST",$B13,$B13)} -> 266.59 | N13: {=_xll.BDH(N$2 & " US Equity","PX_LAST",$B13,$B13)} -> 34.1 | O13: {=_xll.BDH(O$2 & " US Equity","PX_LAST",$B13,$B13)} -> 30.05 | P13: {=_xll.BDH(P$2 & " US Equity","PX_LAST",$B13,$B13)} -> 14.69 | ... Z13: {=_xll.BDH(Z$2 & " US Equity","PX_LAST",$B13,$B13)} -> 303.93 | AA13: {=_xll.BDH(AA$2 & " PE Equity","PX_LAST",$B13,$B13)} -> 0.397 | AB13: {=_xll.BDH(AB$2 & " PE Equity","PX_LAST",$B13,$B13)} -> 27.5 | AC13: {=_xll.BDH(AC$2 & " US Equity","PX_LAST",$B13,$B13)} -> 69.05 | AD13: {=_xll.BDH(AD$2 & " US Equity","PX_LAST",$B13,$B13)} -> 657.63 | AE13: {=_xll.BDH(AE$2 & " PE Equity","PX_LAST",$B13,$B13)} -> #N/A Connection | AF13: {=_xll.BDH(AF$2 & " US Equity","PX_LAST",$B13,$B13)} -> 52.3269 | AG13: {=_xll.BDH(AG$2 & " US Equity","PX_LAST",$B13,$B13)} -> 13.73 | AH13: {=_xll.BDH(AH$2 & " US Equity","PX_LAST",$B13,$B13)} -> 584.08 | AI13: {=_xll.BDH(AI$2 & " US Equity","PX_LAST",$B13,$B13)} -> 106.99 | AJ13: {=_xll.BDH(AJ$2 & " US Equity","PX_LAST",$B13,$B13)} -> 117.08 | AK13: {=_xll.BDH(AK$2 & " US Equity","PX_LAST",$B13,$B13)} -> 118.7 | AL13: {=_xll.BDH(AL$2 & " US Equity","PX_LAST",$B13,$B13)} -> 229.95 | AM13: {=_xll.BDH(AM$2 & " US Equity","PX_LAST",$B13,$B13)} -> 47.785 | ... AW13: {=_xll.BDH(AW$2 & " US Equity","PX_LAST",$B13,$B13)} -> 145.01
B14: 45912 | C14: {=_xll.BDH(C$2 & " US Equity","PX_LAST",$B14,$B14)} -> 229.55 | D14: {=_xll.BDH(D$2 & " PE Equity","PX_LAST",$B14,$B14)} -> 4.01 | E14: {=_xll.BDH(E$2 & " PE Equity","PX_LAST",$B14,$B14)} -> 1.76 | F14: {=_xll.BDH(F$2 & " PE Equity","PX_LAST",$B14,$B14)} -> 2.57 | G14: {=_xll.BDH(G$2 & " US Equity","PX_LAST",$B14,$B14)} -> 20.87 | H14: {=_xll.BDH(H$2 & " PE Equity","PX_LAST",$B14,$B14)} -> 3.37 | I14: {=_xll.BDH(I$2 & " US Equity","PX_LAST",$B14,$B14)} -> 41.78 | J14: {=_xll.BDH(J$2 & " US Equity","PX_LAST",$B14,$B14)} -> 6.767 | K14: {=_xll.BDH(K$2 & " US Equity","PX_LAST",$B14,$B14)} -> 49 | L14: {=_xll.BDH(L$2 & " US Equity","PX_LAST",$B14,$B14)} -> 52.26 | M14: {=_xll.BDH(M$2 & " US Equity","PX_LAST",$B14,$B14)} -> 266.06 | N14: {=_xll.BDH(N$2 & " US Equity","PX_LAST",$B14,$B14)} -> 34.1 | O14: {=_xll.BDH(O$2 & " US Equity","PX_LAST",$B14,$B14)} -> 30.03 | P14: {=_xll.BDH(P$2 & " US Equity","PX_LAST",$B14,$B14)} -> 14.63 | ... Z14: {=_xll.BDH(Z$2 & " US Equity","PX_LAST",$B14,$B14)} -> 304.32 | AA14: {=_xll.BDH(AA$2 & " PE Equity","PX_LAST",$B14,$B14)} -> 0.42 | AB14: {=_xll.BDH(AB$2 & " PE Equity","PX_LAST",$B14,$B14)} -> 27.5 | AC14: {=_xll.BDH(AC$2 & " US Equity","PX_LAST",$B14,$B14)} -> 68.68 | AD14: {=_xll.BDH(AD$2 & " US Equity","PX_LAST",$B14,$B14)} -> 657.41 | AE14: {=_xll.BDH(AE$2 & " PE Equity","PX_LAST",$B14,$B14)} -> #N/A Connection | AF14: {=_xll.BDH(AF$2 & " US Equity","PX_LAST",$B14,$B14)} -> 51.7648 | AG14: {=_xll.BDH(AG$2 & " US Equity","PX_LAST",$B14,$B14)} -> 13.78 | AH14: {=_xll.BDH(AH$2 & " US Equity","PX_LAST",$B14,$B14)} -> 586.66 | AI14: {=_xll.BDH(AI$2 & " US Equity","PX_LAST",$B14,$B14)} -> 106.9 | AJ14: {=_xll.BDH(AJ$2 & " US Equity","PX_LAST",$B14,$B14)} -> 115.96 | AK14: {=_xll.BDH(AK$2 & " US Equity","PX_LAST",$B14,$B14)} -> 119.315 | AL14: {=_xll.BDH(AL$2 & " US Equity","PX_LAST",$B14,$B14)} -> 228.15 | AM14: {=_xll.BDH(AM$2 & " US Equity","PX_LAST",$B14,$B14)} -> 48.38 | ... AW14: {=_xll.BDH(AW$2 & " US Equity","PX_LAST",$B14,$B14)} -> 143.34
... B193: 46091 | C193: {=_xll.BDH(C$2 & " US Equity","PX_LAST",$B193,$B193)} -> #N/A Connection | D193: {=_xll.BDH(D$2 & " PE Equity","PX_LAST",$B193,$B193)} -> #N/A Connection | E193: {=_xll.BDH(E$2 & " PE Equity","PX_LAST",$B193,$B193)} -> #N/A Connection | F193: {=_xll.BDH(F$2 & " PE Equity","PX_LAST",$B193,$B193)} -> #N/A Connection | G193: {=_xll.BDH(G$2 & " US Equity","PX_LAST",$B193,$B193)} -> #N/A Connection | H193: {=_xll.BDH(H$2 & " PE Equity","PX_LAST",$B193,$B193)} -> #N/A Connection | I193: {=_xll.BDH(I$2 & " US Equity","PX_LAST",$B193,$B193)} -> #N/A Connection | J193: {=_xll.BDH(J$2 & " US Equity","PX_LAST",$B193,$B193)} -> #N/A Connection | K193: {=_xll.BDH(K$2 & " US Equity","PX_LAST",$B193,$B193)} -> #N/A Connection | L193: {=_xll.BDH(L$2 & " US Equity","PX_LAST",$B193,$B193)} -> #N/A Connection | M193: {=_xll.BDH(M$2 & " US Equity","PX_LAST",$B193,$B193)} -> #N/A Connection | N193: {=_xll.BDH(N$2 & " US Equity","PX_LAST",$B193,$B193)} -> #N/A Connection | O193: {=_xll.BDH(O$2 & " US Equity","PX_LAST",$B193,$B193)} -> #N/A Connection | P193: {=_xll.BDH(P$2 & " US Equity","PX_LAST",$B193,$B193)} -> #N/A Connection | ... Z193: {=_xll.BDH(Z$2 & " US Equity","PX_LAST",$B193,$B193)} -> #N/A Connection | AA193: {=_xll.BDH(AA$2 & " PE Equity","PX_LAST",$B193,$B193)} -> #N/A Connection | AB193: {=_xll.BDH(AB$2 & " PE Equity","PX_LAST",$B193,$B193)} -> #N/A Connection | AC193: {=_xll.BDH(AC$2 & " US Equity","PX_LAST",$B193,$B193)} -> #N/A Connection | AD193: {=_xll.BDH(AD$2 & " US Equity","PX_LAST",$B193,$B193)} -> #N/A Connection | AE193: {=_xll.BDH(AE$2 & " PE Equity","PX_LAST",$B193,$B193)} -> #N/A Connection | AF193: {=_xll.BDH(AF$2 & " US Equity","PX_LAST",$B193,$B193)} -> #N/A Connection | AG193: {=_xll.BDH(AG$2 & " US Equity","PX_LAST",$B193,$B193)} -> #N/A Connection | AH193: {=_xll.BDH(AH$2 & " US Equity","PX_LAST",$B193,$B193)} -> #N/A Connection | AI193: {=_xll.BDH(AI$2 & " US Equity","PX_LAST",$B193,$B193)} -> #N/A Connection | AJ193: {=_xll.BDH(AJ$2 & " US Equity","PX_LAST",$B193,$B193)} -> #N/A Connection | AK193: {=_xll.BDH(AK$2 & " US Equity","PX_LAST",$B193,$B193)} -> #N/A Connection | AL193: {=_xll.BDH(AL$2 & " US Equity","PX_LAST",$B193,$B193)} -> #N/A Connection | AM193: {=_xll.BDH(AM$2 & " US Equity","PX_LAST",$B193,$B193)} -> #N/A Connection | ... AW193: {=_xll.BDH(AW$2 & " US Equity","PX_LAST",$B193,$B193)} -> #N/A Connection

Sheet Hoja1
H3: Flujo
F4: 46022 | G4: 80 | H4: 80
F5: 46053 | G5: 100
F6: 46068 | G6: 120 | H6: 20
F7: 46081 | G7: 125
G9: =+(G7-G4)/(G4+H6) -> 0.45 | I9: =+(G7-G4)/(G4+H6*13/60) -> 0.53359684

Sheet Compras
A1: Stock | B1: Fecha de compra | C1: Cliente | D1: Ticker | E1: ISIN | F1: Moneda | G1: Identificador | H1: Nombre | I1: Cod_Ope | J1: Q | K1: P | L1: Monto compra | M1: P&L % | N1: Fecha Liquidación | O1: Status
A2: =+IF(COUNTIF(Tabla2[Cod_ope],Tabla1[[#This Row],[Cod_Ope]])>0,"out","stock") -> out | B2: 45912 | C2: 39592 | D2: ITUB | E2: US4655621062 | F2: {=_xll.BDP(G2,"DS004")} -> USD | G2: =D2& " US Equity" -> ITUB US Equity | H2: =+_xll.BDP($G2,"Name") -> ITAU UNIBANCO H-SPON PRF ADR | I2: =+_xlfn.CONCAT(Tabla1[[#This Row],[Fecha de compra]],Tabla1[[#This Row],[Ticker]],Tabla1[[#This Row],[Q]]) -> 45912ITUB5705 | J2: 5705 | K2: 6.9883 | L2: =+Tabla1[[#This Row],[Q]]*Tabla1[[#This Row],[P]] -> 39868.251 | M2: =+VLOOKUP(Tabla1[[#This Row],[Identificador]],'P&L Total'!A:L,12,FALSE) -> 0.15526952 | N2: =WORKDAY(Tabla1[[#This Row],[Fecha de compra]],0) -> 45912 | O2: Liquidado
A3: =+IF(COUNTIF(Tabla2[Cod_ope],Tabla1[[#This Row],[Cod_Ope]])>0,"out","stock") -> stock | B3: 45912 | C3: 39592 | D3: EEM | E3: US4642872349 | F3: {=_xll.BDP(G3,"DS004")} -> USD | G3: =D3& " US Equity" -> EEM US Equity | H3: =+_xll.BDP($G3,"Name") -> ISHARES MSCI EMERGING MARKET | I3: =+_xlfn.CONCAT(Tabla1[[#This Row],[Fecha de compra]],Tabla1[[#This Row],[Ticker]],Tabla1[[#This Row],[Q]]) -> 45912EEM1527 | J3: 1527 | K3: 52.29 | L3: =+Tabla1[[#This Row],[Q]]*Tabla1[[#This Row],[P]] -> 79846.83 | M3: =+VLOOKUP(Tabla1[[#This Row],[Identificador]],'P&L Total'!A:L,12,FALSE) -> 0.098275989 | N3: =WORKDAY(Tabla1[[#This Row],[Fecha de compra]],0) -> 45912 | O3: Liquidado
A4: =+IF(COUNTIF(Tabla2[Cod_ope],Tabla1[[#This Row],[Cod_Ope]])>0,"out","stock") -> stock | B4: 45912 | C4: 39592 | D4: XLU | E4: US81369Y8865 | F4: {=_xll.BDP(G4,"DS004")} -> USD | G4: =D4& " US Equity" -> XLU US Equity | H4: =+_xll.BDP($G4,"Name") -> ST SR UTL SL SE SPDR ETF-USD | I4: =+_xlfn.CONCAT(Tabla1[[#This Row],[Fecha de compra]],Tabla1[[#This Row],[Ticker]],Tabla1[[#This Row],[Q]]) -> 45912XLU1872 | J4: =936*2 -> 1872 | K4: =85.3599/2 -> 42.67995 | L4: =+Tabla1[[#This Row],[Q]]*Tabla1[[#This Row],[P]] -> 79896.866 | M4: =+VLOOKUP(Tabla1[[#This Row],[Identificador]],'P&L Total'!A:L,12,FALSE) -> 0.07128845 | N4: =WORKDAY(Tabla1[[#This Row],[Fecha de compra]],0) -> 45912 | O4: Liquidado
A5: =+IF(COUNTIF(Tabla2[Cod_ope],Tabla1[[#This Row],[Cod_Ope]])>0,"out","stock") -> stock | B5: 45912 | C5: 39592 | D5: XLI | E5: US81369Y7040 | F5: {=_xll.BDP(G5,"DS004")} -> USD | G5: =D5& " US Equity" -> XLI US Equity | H5: =+_xll.BDP($G5,"Name") -> SS INDUSTRIAL SELECT SECTOR | I5: =+_xlfn.CONCAT(Tabla1[[#This Row],[Fecha de compra]],Tabla1[[#This Row],[Ticker]],Tabla1[[#This Row],[Q]]) -> 45912XLI526 | J5: 526 | K5: 151.8778 | L5: =+Tabla1[[#This Row],[Q]]*Tabla1[[#This Row],[P]] -> 79887.723 | M5: =+VLOOKUP(Tabla1[[#This Row],[Identificador]],'P&L Total'!A:L,12,FALSE) -> 0.063487408 | N5: =WORKDAY(Tabla1[[#This Row],[Fecha de compra]],0) -> 45912 | O5: Liquidado
A6: =+IF(COUNTIF(Tabla2[Cod_ope],Tabla1[[#This Row],[Cod_Ope]])>0,"out","stock") -> stock | B6: 45912 | C6: 39592 | D6: XLY | E6: US81369Y4070 | F6: {=_xll.BDP(G6,"DS004")} -> USD | G6: =D6& " US Equity" -> XLY US Equity | H6: =+_xll.BDP($G6,"Name") -> SS CONSUMER DISC SELECT SECT | I6: =+_xlfn.CONCAT(Tabla1[[#This Row],[Fecha de compra]],Tabla1[[#This Row],[Ticker]],Tabla1[[#This Row],[Q]]) -> 45912XLY670 | J6: =335*2 -> 670 | K6: =238.33/2 -> 119.165 | L6: =+Tabla1[[#This Row],[Q]]*Tabla1[[#This Row],[P]] -> 79840.55 | M6: =+VLOOKUP(Tabla1[[#This Row],[Identificador]],'P&L Total'!A:L,12,FALSE) -> -0.024749212 | N6: =WORKDAY(Tabla1[[#This Row],[Fecha de compra]],0) -> 45912 | O6: Liquidado
A7: =+IF(COUNTIF(Tabla2[Cod_ope],Tabla1[[#This Row],[Cod_Ope]])>0,"out","stock") -> out | B7: 45917 | C7: 39592 | D7: PLTR | E7: US69608A1088 | F7: {=_xll.BDP(G7,"DS004")} -> USD | G7: =D7& " US Equity" -> PLTR US Equity | H7: =+_xll.BDP($G7,"Name") -> PALANTIR TECHNOLOGIES INC-A | I7: =+_xlfn.CONCAT(Tabla1[[#This Row],[Fecha de compra]],Tabla1[[#This Row],[Ticker]],Tabla1[[#This Row],[Q]]) -> 45917PLTR491 | J7: 491 | K7: 162.926 | L7: =+Tabla1[[#This Row],[Q]]*Tabla1[[#This Row],[P]] -> 79996.666 | M7: =+VLOOKUP(Tabla1[[#This Row],[Identificador]],'P&L Total'!A:L,12,FALSE) -> 0.048158251 | N7: =WORKDAY(Tabla1[[#This Row],[Fecha de compra]],0) -> 45917 | O7: Liquidado
A8: =+IF(COUNTIF(Tabla2[Cod_ope],Tabla1[[#This Row],[Cod_Ope]])>0,"out","stock") -> out | B8: 45917 | C8: 39592 | D8: SPY | E8: US78462F1030 | F8: {=_xll.BDP(G8,"DS004")} -> USD | G8: =D8& " US Equity" -> SPY US Equity | H8: =+_xll.BDP($G8,"Name") -> SS SPDR S&P 500 ETF TRUST-US | I8: =+_xlfn.CONCAT(Tabla1[[#This Row],[Fecha de compra]],Tabla1[[#This Row],[Ticker]],Tabla1[[#This Row],[Q]]) -> 45917SPY151 | J8: 151 | K8: 658.38 | L8: =+Tabla1[[#This Row],[Q]]*Tabla1[[#This Row],[P]] -> 99415.38 | M8: =+VLOOKUP(Tabla1[[#This Row],[Identificador]],'P&L Total'!A:L,12,FALSE) -> 0.036936014 | N8: =WORKDAY(Tabla1[[#This Row],[Fecha de compra]],0) -> 45917 | O8: Liquidado
A9: =+IF(COUNTIF(Tabla2[Cod_ope],Tabla1[[#This Row],[Cod_Ope]])>0,"out","stock") -> stock | B9: 45922 | C9: 39592 | D9: FDX | E9: US31428X1063 | F9: {=_xll.BDP(G9,"DS004")} -> USD | G9: =D9& " US Equity" -> FDX US Equity | H9: =+_xll.BDP($G9,"Name") -> FEDEX CORP | I9: =+_xlfn.CONCAT(Tabla1[[#This Row],[Fecha de compra]],Tabla1[[#This Row],[Ticker]],Tabla1[[#This Row],[Q]]) -> 45922FDX218 | J9: 218 | K9: 228.4 | L9: =+Tabla1[[#This Row],[Q]]*Tabla1[[#This Row],[P]] -> 49791.2 | M9: =+VLOOKUP(Tabla1[[#This Row],[Identificador]],'P&L Total'!A:L,12,FALSE) -> 0.58021016 | N9: =WORKDAY(Tabla1[[#This Row],[Fecha de compra]],0) -> 45922 | O9: Liquidado
A10: =+IF(COUNTIF(Tabla2[Cod_ope],Tabla1[[#This Row],[Cod_Ope]])>0,"out","stock") -> out | B10: 45922 | C10: 39592 | D10: XPEV | E10: US98422D1054 | F10: {=_xll.BDP(G10,"DS004")} -> USD | G10: =D10& " US Equity" -> XPEV US Equity | H10: =+_xll.BDP($G10,"Name") -> XPENG INC - ADR | I10: =+_xlfn.CONCAT(Tabla1[[#This Row],[Fecha de compra]],Tabla1[[#This Row],[Ticker]],Tabla1[[#This Row],[Q]]) -> 45922XPEV1403 | J10: 1403 | K10: 21.348 | L10: =+Tabla1[[#This Row],[Q]]*Tabla1[[#This Row],[P]] -> 29951.244 | M10: =+VLOOKUP(Tabla1[[#This Row],[Identificador]],'P&L Total'!A:L,12,FALSE) -> 0.26335696 | N10: =WORKDAY(Tabla1[[#This Row],[Fecha de compra]],0) -> 45922 | O10: Liquidado
A11: =+IF(COUNTIF(Tabla2[Cod_ope],Tabla1[[#This Row],[Cod_Ope]])>0,"out","stock") -> out | B11: 45922 | C11: 39592 | D11: EWP | E11: US4642867646 | F11: {=_xll.BDP(G11,"DS004")} -> USD | G11: =D11& " US Equity" -> EWP US Equity | H11: =+_xll.BDP($G11,"Name") -> ISHARES MSCI SPAIN ETF | I11: =+_xlfn.CONCAT(Tabla1[[#This Row],[Fecha de compra]],Tabla1[[#This Row],[Ticker]],Tabla1[[#This Row],[Q]]) -> 45922EWP1031 | J11: 1031 | K11: 48.40709 | L11: =+Tabla1[[#This Row],[Q]]*Tabla1[[#This Row],[P]] -> 49907.71 | M11: =+VLOOKUP(Tabla1[[#This Row],[Identificador]],'P&L Total'!A:L,12,FALSE) -> 0.15211367 | N11: =WORKDAY(Tabla1[[#This Row],[Fecha de compra]],0) -> 45922 | O11: Liquidado
A12: =+IF(COUNTIF(Tabla2[Cod_ope],Tabla1[[#This Row],[Cod_Ope]])>0,"out","stock") -> stock | B12: 45922 | C12: 39592 | D12: NIO | E12: US62914V1061 | F12: {=_xll.BDP(G12,"DS004")} -> USD | G12: =D12& " US Equity" -> NIO US Equity | H12: =+_xll.BDP($G12,"Name") -> NIO INC - ADR | I12: =+_xlfn.CONCAT(Tabla1[[#This Row],[Fecha de compra]],Tabla1[[#This Row],[Ticker]],Tabla1[[#This Row],[Q]]) -> 45922NIO4360 | J12: 4360 | K12: 6.86 | L12: =+Tabla1[[#This Row],[Q]]*Tabla1[[#This Row],[P]] -> 29909.6 | M12: =+VLOOKUP(Tabla1[[#This Row],[Identificador]],'P&L Total'!A:L,12,FALSE) -> 0.0016996563 | N12: =WORKDAY(Tabla1[[#This Row],[Fecha de compra]],1) -> 45923 | O12: Liquidado
A13: =+IF(COUNTIF(Tabla2[Cod_ope],Tabla1[[#This Row],[Cod_Ope]])>0,"out","stock") -> stock | B13: 45922 | C13: 39592 | D13: PRU | E13: US7443201022 | F13: {=_xll.BDP(G13,"DS004")} -> USD | G13: =D13& " US Equity" -> PRU US Equity | H13: =+_xll.BDP($G13,"Name") -> PRUDENTIAL FINANCIAL INC | I13: =+_xlfn.CONCAT(Tabla1[[#This Row],[Fecha de compra]],Tabla1[[#This Row],[Ticker]],Tabla1[[#This Row],[Q]]) -> 45922PRU483 | J13: 483 | K13: 103.3625 | L13: =+Tabla1[[#This Row],[Q]]*Tabla1[[#This Row],[P]] -> 49924.088 | M13: =+VLOOKUP(Tabla1[[#This Row],[Identificador]],'P&L Total'!A:L,12,FALSE) -> -0.06329665 | N13: =WORKDAY(Tabla1[[#This Row],[Fecha de compra]],0) -> 45922 | O13: Liquidado
A14: =+IF(COUNTIF(Tabla2[Cod_ope],Tabla1[[#This Row],[Cod_Ope]])>0,"out","stock") -> stock | B14: 45922 | C14: 39592 | D14: KMB | E14: US4943681035 | F14: {=_xll.BDP(G14,"DS004")} -> USD | G14: =D14& " US Equity" -> KMB US Equity | H14: =+_xll.BDP($G14,"Name") -> KIMBERLY-CLARK CORP | I14: =+_xlfn.CONCAT(Tabla1[[#This Row],[Fecha de compra]],Tabla1[[#This Row],[Ticker]],Tabla1[[#This Row],[Q]]) -> 45922KMB402 | J14: 402 | K14: 124.1899 | L14: =+Tabla1[[#This Row],[Q]]*Tabla1[[#This Row],[P]] -> 49924.34 | M14: =+VLOOKUP(Tabla1[[#This Row],[Identificador]],'P&L Total'!A:L,12,FALSE) -> -0.10395594 | N14: =WORKDAY(Tabla1[[#This Row],[Fecha de compra]],1) -> 45923 | O14: Liquidado
A15: =+IF(COUNTIF(Tabla2[Cod_ope],Tabla1[[#This Row],[Cod_Ope]])>0,"out","stock") -> stock | B15: 45922 | C15: 39592 | D15: UNH | E15: US91324P1021 | F15: {=_xll.BDP(G15,"DS004")} -> USD | G15: =D15& " US Equity" -> UNH US Equity | H15: =+_xll.BDP($G15,"Name") -> UNITEDHEALTH GROUP INC | I15: =+_xlfn.CONCAT(Tabla1[[#This Row],[Fecha de compra]],Tabla1[[#This Row],[Ticker]],Tabla1[[#This Row],[Q]]) -> 45922UNH147 | J15: 147 | K15: 340.3 | L15: =+Tabla1[[#This Row],[Q]]*Tabla1[[#This Row],[P]] -> 50024.1 | M15: =+VLOOKUP(Tabla1[[#This Row],[Identificador]],'P&L Total'!A:L,12,FALSE) -> -0.16883552 | N15: =WORKDAY(Tabla1[[#This Row],[Fecha de compra]],1) -> 45923 | O15: Liquidado
A16: =+IF(COUNTIF(Tabla2[Cod_ope],Tabla1[[#This Row],[Cod_Ope]])>0,"out","stock") -> stock | B16: 45922 | C16: 39592 | D16: KKR | E16: US48251W1045 | F16: {=_xll.BDP(G16,"DS004")} -> USD | G16: =D16& " US Equity" -> KKR US Equity | H16: =+_xll.BDP($G16,"Name") -> KKR & CO INC | I16: =+_xlfn.CONCAT(Tabla1[[#This Row],[Fecha de compra]],Tabla1[[#This Row],[Ticker]],Tabla1[[#This Row],[Q]]) -> 45922KKR341 | J16: 341 | K16: 146.35 | L16: =+Tabla1[[#This Row],[Q]]*Tabla1[[#This Row],[P]] -> 49905.35 | M16: =+VLOOKUP(Tabla1[[#This Row],[Identificador]],'P&L Total'!A:L,12,FALSE) -> -0.3840451 | N16: =WORKDAY(Tabla1[[#This Row],[Fecha de compra]],1) -> 45923 | O16: Liquidado
A17: =+IF(COUNTIF(Tabla2[Cod_ope],Tabla1[[#This Row],[Cod_Ope]])>0,"out","stock") -> stock | B17: 45927 | C17: 39592 | D17: EEM | E17: US4642872349 | F17: {=_xll.BDP(G17,"DS004")} -> USD | G17: =D17& " US Equity" -> EEM US Equity | H17: =+_xll.BDP($G17,"Name") -> ISHARES MSCI EMERGING MARKET | I17: =+_xlfn.CONCAT(Tabla1[[#This Row],[Fecha de compra]],Tabla1[[#This Row],[Ticker]],Tabla1[[#This Row],[Q]]) -> 45927EEM1436 | J17: 1436 | K17: 55.5799 | L17: =+Tabla1[[#This Row],[Q]]*Tabla1[[#This Row],[P]] -> 79812.736 | M17: =+VLOOKUP(Tabla1[[#This Row],[Identificador]],'P&L Total'!A:L,12,FALSE) -> 0.098275989 | N17: =WORKDAY(Tabla1[[#This Row],[Fecha de compra]],0) -> 45927 | O17: Liquidado
A18: =+IF(COUNTIF(Tabla2[Cod_ope],Tabla1[[#This Row],[Cod_Ope]])>0,"out","stock") -> stock | B18: 45927 | C18: 39592 | D18: EUFN | E18: US4642891802 | F18: {=_xll.BDP(G18,"DS004")} -> USD | G18: =D18& " US Equity" -> EUFN US Equity | H18: =+_xll.BDP($G18,"Name") -> ISHARES MSCI EUROPE FINANCIA | I18: =+_xlfn.CONCAT(Tabla1[[#This Row],[Fecha de compra]],Tabla1[[#This Row],[Ticker]],Tabla1[[#This Row],[Q]]) -> 45927EUFN2062 | J18: 2062 | K18: 33.879983 | L18: =+Tabla1[[#This Row],[Q]]*Tabla1[[#This Row],[P]] -> 69860.525 | M18: =+VLOOKUP(Tabla1[[#This Row],[Identificador]],'P&L Total'!A:L,12,FALSE) -> 0.058038723 | N18: =WORKDAY(Tabla1[[#This Row],[Fecha de compra]],0) -> 45927 | O18: Liquidado
A19: =+IF(COUNTIF(Tabla2[Cod_ope],Tabla1[[#This Row],[Cod_Ope]])>0,"out","stock") -> stock | B19: 45927 | C19: 39592 | D19: EZU | E19: US4642866085 | F19: {=_xll.BDP(G19,"DS004")} -> USD | G19: =D19& " US Equity" -> EZU US Equity | H19: =+_xll.BDP($G19,"Name") -> ISHARES MSCI EUROZONE ETF | I19: =+_xlfn.CONCAT(Tabla1[[#This Row],[Fecha de compra]],Tabla1[[#This Row],[Ticker]],Tabla1[[#This Row],[Q]]) -> 45927EZU1584 | J19: 1584 | K19: 63.025879 | L19: =+Tabla1[[#This Row],[Q]]*Tabla1[[#This Row],[P]] -> 99832.992 | M19: =+VLOOKUP(Tabla1[[#This Row],[Identificador]],'P&L Total'!A:L,12,FALSE) -> 0.032270331 | N19: =WORKDAY(Tabla1[[#This Row],[Fecha de compra]],0) -> 45927 | O19: Liquidado
A20: =+IF(COUNTIF(Tabla2[Cod_ope],Tabla1[[#This Row],[Cod_Ope]])>0,"out","stock") -> stock | B20: 45927 | C20: 39592 | D20: UNH | E20: US91324P1021 | F20: {=_xll.BDP(G20,"DS004")} -> USD | G20: =D20& " US Equity" -> UNH US Equity | H20: =+_xll.BDP($G20,"Name") -> UNITEDHEALTH GROUP INC | I20: =+_xlfn.CONCAT(Tabla1[[#This Row],[Fecha de compra]],Tabla1[[#This Row],[Ticker]],Tabla1[[#This Row],[Q]]) -> 45927UNH137 | J20: 137 | K20: 364.0234 | L20: =+Tabla1[[#This Row],[Q]]*Tabla1[[#This Row],[P]] -> 49871.206 | M20: =+VLOOKUP(Tabla1[[#This Row],[Identificador]],'P&L Total'!A:L,12,FALSE) -> -0.16883552 | N20: =WORKDAY(Tabla1[[#This Row],[Fecha de compra]],1) -> 45929 | O20: Liquidado
A21: =+IF(COUNTIF(Tabla2[Cod_ope],Tabla1[[#This Row],[Cod_Ope]])>0,"out","stock") -> out | B21: 45932 | C21: 39592 | D21: EWZ | E21: US4642864007 | F21: {=_xll.BDP(G21,"DS004")} -> USD | G21: =D21& " US Equity" -> EWZ US Equity | H21: =+_xll.BDP($G21,"Name") -> ISHARES MSCI BRAZIL ETF | I21: =+_xlfn.CONCAT(Tabla1[[#This Row],[Fecha de compra]],Tabla1[[#This Row],[Ticker]],Tabla1[[#This Row],[Q]]) -> 45932EWZ1994 | J21: 1994 | K21: 30.03 | L21: =+Tabla1[[#This Row],[Q]]*Tabla1[[#This Row],[P]] -> 59879.82 | M21: =+VLOOKUP(Tabla1[[#This Row],[Identificador]],'P&L Total'!A:L,12,FALSE) -> 0.031229701 | N21: =WORKDAY(Tabla1[[#This Row],[Fecha de compra]],0) -> 45932 | O21: Liquidado
A22: =+IF(COUNTIF(Tabla2[Cod_ope],Tabla1[[#This Row],[Cod_Ope]])>0,"out","stock") -> out | B22: 45932 | C22: 39592 | D22: EWZS | E22: US4642891315 | F22: {=_xll.BDP(G22,"DS004")} -> USD | G22: =D22& " US Equity" -> EWZS US Equity | H22: =+_xll.BDP($G22,"Name") -> ISHARES MSCI BRAZIL SMALL-CA | I22: =+_xlfn.CONCAT(Tabla1[[#This Row],[Fecha de compra]],Tabla1[[#This Row],[Ticker]],Tabla1[[#This Row],[Q]]) -> 45932EWZS4422 | J22: 4422 | K22: 13.52 | L22: =+Tabla1[[#This Row],[Q]]*Tabla1[[#This Row],[P]] -> 59785.44 | M22: =+VLOOKUP(Tabla1[[#This Row],[Identificador]],'P&L Total'!A:L,12,FALSE) -> 0.022474688 | N22: =WORKDAY(Tabla1[[#This Row],[Fecha de compra]],0) -> 45932 | O22: Liquidado
A23: =+IF(COUNTIF(Tabla2[Cod_ope],Tabla1[[#This Row],[Cod_Ope]])>0,"out","stock") -> out | B23: 45937 | C23: 39592 | D23: EWZ | E23: US4642864007 | F23: {=_xll.BDP(G23,"DS004")} -> USD | G23: =D23& " US Equity" -> EWZ US Equity | H23: =+_xll.BDP($G23,"Name") -> ISHARES MSCI BRAZIL ETF | I23: =+_xlfn.CONCAT(Tabla1[[#This Row],[Fecha de compra]],Tabla1[[#This Row],[Ticker]],Tabla1[[#This Row],[Q]]) -> 45937EWZ1008 | J23: 1008 | K23: 29.69 | L23: =+Tabla1[[#This Row],[Q]]*Tabla1[[#This Row],[P]] -> 29927.52 | M23: =+VLOOKUP(Tabla1[[#This Row],[Identificador]],'P&L Total'!A:L,12,FALSE) -> 0.031229701 | N23: =WORKDAY(Tabla1[[#This Row],[Fecha de compra]],0) -> 45937 | O23: Liquidado
A24: =+IF(COUNTIF(Tabla2[Cod_ope],Tabla1[[#This Row],[Cod_Ope]])>0,"out","stock") -> out | B24: 45937 | C24: 39592 | D24: EWZS | E24: US4642891315 | F24: {=_xll.BDP(G24,"DS004")} -> USD | G24: =D24& " US Equity" -> EWZS US Equity | H24: =+_xll.BDP($G24,"Name") -> ISHARES MSCI BRAZIL SMALL-CA | I24: =+_xlfn.CONCAT(Tabla1[[#This Row],[Fecha de compra]],Tabla1[[#This Row],[Ticker]],Tabla1[[#This Row],[Q]]) -> 45937EWZS2266 | J24: 2266 | K24: 13.2 | L24: =+Tabla1[[#This Row],[Q]]*Tabla1[[#This Row],[P]] -> 29911.2 | M24: =+VLOOKUP(Tabla1[[#This Row],[Identificador]],'P&L Total'!A:L,12,FALSE) -> 0.022474688 | N24: =WORKDAY(Tabla1[[#This Row],[Fecha de compra]],0) -> 45937 | O24: Liquidado
A25: =+IF(COUNTIF(Tabla2[Cod_ope],Tabla1[[#This Row],[Cod_Ope]])>0,"out","stock") -> stock | B25: 45939 | C25: 39592 | D25: FERREYC1 | E25: PEP736001004 | F25: {=_xll.BDP(G25,"DS004")} -> PEN | G25: =D25& " pe Equity" -> FERREYC1 pe Equity | H25: =+_xll.BDP($G25,"Name") -> FERREYCORP SAA | I25: =+_xlfn.CONCAT(Tabla1[[#This Row],[Fecha de compra]],Tabla1[[#This Row],[Ticker]],Tabla1[[#This Row],[Q]]) -> 45939FERREYC123520 | J25: 23520 | K25: 3.31 | L25: =+Tabla1[[#This Row],[Q]]*Tabla1[[#This Row],[P]] -> 77851.2 | M25: =+VLOOKUP(Tabla1[[#This Row],[Identificador]],'P&L Total'!A:L,12,FALSE) -> 0.26768554 | N25: =WORKDAY(Tabla1[[#This Row],[Fecha de compra]],0) -> 45939 | O25: Liquidado
A26: =+IF(COUNTIF(Tabla2[Cod_ope],Tabla1[[#This Row],[Cod_Ope]])>0,"out","stock") -> stock | B26: 45939 | C26: 39592 | D26: FERREYC1 | E26: PEP736001004 | F26: {=_xll.BDP(G26,"DS004")} -> PEN | G26: =D26& " pe Equity" -> FERREYC1 pe Equity | H26: =+_xll.BDP($G26,"Name") -> FERREYCORP SAA | I26: =+_xlfn.CONCAT(Tabla1[[#This Row],[Fecha de compra]],Tabla1[[#This Row],[Ticker]],Tabla1[[#This Row],[Q]]) -> 45939FERREYC120000 | J26: 20000 | K26: 3.31 | L26: =+Tabla1[[#This Row],[Q]]*Tabla1[[#This Row],[P]] -> 66200 | M26: =+VLOOKUP(Tabla1[[#This Row],[Identificador]],'P&L Total'!A:L,12,FALSE) -> 0.26768554 | N26: =WORKDAY(Tabla1[[#This Row],[Fecha de compra]],0) -> 45939 | O26: Liquidado
A27: =+IF(COUNTIF(Tabla2[Cod_ope],Tabla1[[#This Row],[Cod_Ope]])>0,"out","stock") -> out | B27: 45939 | C27: 39592 | D27: XPEV | E27: US98422D1054 | F27: {=_xll.BDP(G27,"DS004")} -> USD | G27: =D27& " US Equity" -> XPEV US Equity | H27: =+_xll.BDP($G27,"Name") -> XPENG INC - ADR | I27: =+_xlfn.CONCAT(Tabla1[[#This Row],[Fecha de compra]],Tabla1[[#This Row],[Ticker]],Tabla1[[#This Row],[Q]]) -> 45939XPEV1097 | J27: 1097 | K27: 22.736726 | L27: =+Tabla1[[#This Row],[Q]]*Tabla1[[#This Row],[P]] -> 24942.188 | M27: =+VLOOKUP(Tabla1[[#This Row],[Identificador]],'P&L Total'!A:L,12,FALSE) -> 0.26335696 | N27: =WORKDAY(Tabla1[[#This Row],[Fecha de compra]],0) -> 45939 | O27: Liquidado
A28: =+IF(COUNTIF(Tabla2[Cod_ope],Tabla1[[#This Row],[Cod_Ope]])>0,"out","stock") -> stock | B28: 45939 | C28: 39592 | D28: EUFN | E28: US4642891802 | F28: {=_xll.BDP(G28,"DS004")} -> USD | G28: =D28& " US Equity" -> EUFN US Equity | H28: =+_xll.BDP($G28,"Name") -> ISHARES MSCI EUROPE FINANCIA | I28: =+_xlfn.CONCAT(Tabla1[[#This Row],[Fecha de compra]],Tabla1[[#This Row],[Ticker]],Tabla1[[#This Row],[Q]]) -> 45939EUFN2073 | J28: 2073 | K28: 33.709 | L28: =+Tabla1[[#This Row],[Q]]*Tabla1[[#This Row],[P]] -> 69878.757 | M28: =+VLOOKUP(Tabla1[[#This Row],[Identificador]],'P&L Total'!A:L,12,FALSE) -> 0.058038723 | N28: =WORKDAY(Tabla1[[#This Row],[Fecha de compra]],0) -> 45939 | O28: Liquidado
A29: =+IF(COUNTIF(Tabla2[Cod_ope],Tabla1[[#This Row],[Cod_Ope]])>0,"out","stock") -> stock | B29: 45939 | C29: 39592 | D29: EZU | E29: US4642866085 | F29: {=_xll.BDP(G29,"DS004")} -> USD | G29: =D29& " US Equity" -> EZU US Equity | H29: =+_xll.BDP($G29,"Name") -> ISHARES MSCI EUROZONE ETF | I29: =+_xlfn.CONCAT(Tabla1[[#This Row],[Fecha de compra]],Tabla1[[#This Row],[Ticker]],Tabla1[[#This Row],[Q]]) -> 45939EZU807 | J29: 807 | K29: 61.85 | L29: =+Tabla1[[#This Row],[Q]]*Tabla1[[#This Row],[P]] -> 49912.95 | M29: =+VLOOKUP(Tabla1[[#This Row],[Identificador]],'P&L Total'!A:L,12,FALSE) -> 0.032270331 | N29: =WORKDAY(Tabla1[[#This Row],[Fecha de compra]],0) -> 45939 | O29: Liquidado
A30: =+IF(COUNTIF(Tabla2[Cod_ope],Tabla1[[#This Row],[Cod_Ope]])>0,"out","stock") -> stock | B30: 45939 | C30: 39592 | D30: BIDU | E30: US0567521085 | F30: {=_xll.BDP(G30,"DS004")} -> USD | G30: =D30& " US Equity" -> BIDU US Equity | H30: =+_xll.BDP($G30,"Name") -> BAIDU INC - SPON ADR | I30: =+_xlfn.CONCAT(Tabla1[[#This Row],[Fecha de compra]],Tabla1[[#This Row],[Ticker]],Tabla1[[#This Row],[Q]]) -> 45939BIDU378 | J30: 378 | K30: 132.1 | L30: =+Tabla1[[#This Row],[Q]]*Tabla1[[#This Row],[P]] -> 49933.8 | M30: =+VLOOKUP(Tabla1[[#This Row],[Identificador]],'P&L Total'!A:L,12,FALSE) -> -0.0029078851 | N30: =WORKDAY(Tabla1[[#This Row],[Fecha de compra]],0) -> 45939 | O30: Liquidado
A31: =+IF(COUNTIF(Tabla2[Cod_ope],Tabla1[[#This Row],[Cod_Ope]])>0,"out","stock") -> stock | B31: 45939 | C31: 39592 | D31: NIO | E31: US62914V1061 | F31: {=_xll.BDP(G31,"DS004")} -> USD | G31: =D31& " US Equity" -> NIO US Equity | H31: =+_xll.BDP($G31,"Name") -> NIO INC - ADR | I31: =+_xlfn.CONCAT(Tabla1[[#This Row],[Fecha de compra]],Tabla1[[#This Row],[Ticker]],Tabla1[[#This Row],[Q]]) -> 45939NIO3328 | J31: 3328 | K31: 7.4965 | L31: =+Tabla1[[#This Row],[Q]]*Tabla1[[#This Row],[P]] -> 24948.352 | M31: =+VLOOKUP(Tabla1[[#This Row],[Identificador]],'P&L Total'!A:L,12,FALSE) -> 0.0016996563 | N31: =WORKDAY(Tabla1[[#This Row],[Fecha de compra]],1) -> 45940 | O31: Liquidado
A32: =+IF(COUNTIF(Tabla2[Cod_ope],Tabla1[[#This Row],[Cod_Ope]])>0,"out","stock") -> stock | B32: 45939 | C32: 39592 | D32: TCHI | E32: US46436E4290 | F32: {=_xll.BDP(G32,"DS004")} -> USD | G32: =D32& " US Equity" -> TCHI US Equity | H32: =+_xll.BDP($G32,"Name") -> ISHARES MSCI CHINA TECH | I32: =+_xlfn.CONCAT(Tabla1[[#This Row],[Fecha de compra]],Tabla1[[#This Row],[Ticker]],Tabla1[[#This Row],[Q]]) -> 45939TCHI2252 | J32: 2252 | K32: 26.6 | L32: =+Tabla1[[#This Row],[Q]]*Tabla1[[#This Row],[P]] -> 59903.2 | M32: =+VLOOKUP(Tabla1[[#This Row],[Identificador]],'P&L Total'!A:L,12,FALSE) -> -0.059251608 | N32: =WORKDAY(Tabla1[[#This Row],[Fecha de compra]],0) -> 45939 | O32: Liquidado
A33: =+IF(COUNTIF(Tabla2[Cod_ope],Tabla1[[#This Row],[Cod_Ope]])>0,"out","stock") -> stock | B33: 45939 | C33: 39592 | D33: CQQQ | E33: US46138E8003 | F33: {=_xll.BDP(G33,"DS004")} -> USD | G33: =D33& " US Equity" -> CQQQ US Equity | H33: =+_xll.BDP($G33,"Name") -> INVESCO CHINA TECHNOLOGY ETF | I33: =+_xlfn.CONCAT(Tabla1[[#This Row],[Fecha de compra]],Tabla1[[#This Row],[Ticker]],Tabla1[[#This Row],[Q]]) -> 45939CQQQ679 | J33: 679 | K33: 58.74 | L33: =+Tabla1[[#This Row],[Q]]*Tabla1[[#This Row],[P]] -> 39884.46 | M33: =+VLOOKUP(Tabla1[[#This Row],[Identificador]],'P&L Total'!A:L,12,FALSE) -> -0.06876884 | N33: =WORKDAY(Tabla1[[#This Row],[Fecha de compra]],0) -> 45939 | O33: Liquidado
A34: =+IF(COUNTIF(Tabla2[Cod_ope],Tabla1[[#This Row],[Cod_Ope]])>0,"out","stock") -> stock | B34: 45940 | C34: 39592 | D34: MINSURI1 | E34: PEP622005002 | F34: {=_xll.BDP(G34,"DS004")} -> PEN | G34: =D34& " pe Equity" -> MINSURI1 pe Equity | H34: =+_xll.BDP($G34,"Name") -> MINSUR SA-INVERSIONES | I34: =+_xlfn.CONCAT(Tabla1[[#This Row],[Fecha de compra]],Tabla1[[#This Row],[Ticker]],Tabla1[[#This Row],[Q]]) -> 45940MINSURI115450 | J34: 15450 | K34: 4.3 | L34: =+Tabla1[[#This Row],[Q]]*Tabla1[[#This Row],[P]] -> 66435 | M34: =+VLOOKUP(Tabla1[[#This Row],[Identificador]],'P&L Total'!A:L,12,FALSE) -> 0.30273197 | N34: =WORKDAY(Tabla1[[#This Row],[Fecha de compra]],0) -> 45940 | O34: Liquidado
A35: =+IF(COUNTIF(Tabla2[Cod_ope],Tabla1[[#This Row],[Cod_Ope]])>0,"out","stock") -> stock | B35: 45943 | C35: 39592 | D35: FERREYC1 | E35: PEP736001004 | F35: {=_xll.BDP(G35,"DS004")} -> PEN | G35: =D35& " pe Equity" -> FERREYC1 pe Equity | H35: =+_xll.BDP($G35,"Name") -> FERREYCORP SAA | I35: =+_xlfn.CONCAT(Tabla1[[#This Row],[Fecha de compra]],Tabla1[[#This Row],[Ticker]],Tabla1[[#This Row],[Q]]) -> 45943FERREYC1202 | J35: 202 | K35: 3.3 | L35: =+Tabla1[[#This Row],[Q]]*Tabla1[[#This Row],[P]] -> 666.6 | M35: =+VLOOKUP(Tabla1[[#This Row],[Identificador]],'P&L Total'!A:L,12,FALSE) -> 0.26768554 | N35: =WORKDAY(Tabla1[[#This Row],[Fecha de compra]],0) -> 45943 | O35: Liquidado
A36: =+IF(COUNTIF(Tabla2[Cod_ope],Tabla1[[#This Row],[Cod_Ope]])>0,"out","stock") -> stock | B36: 45944 | C36: 39592 | D36: SIDERC1 | E36: PEP531001001 | F36: {=_xll.BDP(G36,"DS004")} -> PEN | G36: =D36& " PE Equity" -> SIDERC1 PE Equity | H36: =+_xll.BDP($G36,"Name") -> EMPRESA SIDERURGICA PERU SAA | I36: =+_xlfn.CONCAT(Tabla1[[#This Row],[Fecha de compra]],Tabla1[[#This Row],[Ticker]],Tabla1[[#This Row],[Q]]) -> 45944SIDERC130000 | J36: 30000 | K36: 1.78 | L36: =+Tabla1[[#This Row],[Q]]*Tabla1[[#This Row],[P]] -> 53400 | M36: =+VLOOKUP(Tabla1[[#This Row],[Identificador]],'P&L Total'!A:L,12,FALSE) -> 0.34374633 | N36: =WORKDAY(Tabla1[[#This Row],[Fecha de compra]],0) -> 45944 | O36: Liquidado
A37: =+IF(COUNTIF(Tabla2[Cod_ope],Tabla1[[#This Row],[Cod_Ope]])>0,"out","stock") -> stock | B37: 45944 | C37: 39592 | D37: BIDU | E37: US0567521085 | F37: {=_xll.BDP(G37,"DS004")} -> USD | G37: =D37& " US Equity" -> BIDU US Equity | H37: =+_xll.BDP($G37,"Name") -> BAIDU INC - SPON ADR | I37: =+_xlfn.CONCAT(Tabla1[[#This Row],[Fecha de compra]],Tabla1[[#This Row],[Ticker]],Tabla1[[#This Row],[Q]]) -> 45944BIDU250 | J37: 250 | K37: 119.69 | L37: =+Tabla1[[#This Row],[Q]]*Tabla1[[#This Row],[P]] -> 29922.5 | M37: =+VLOOKUP(Tabla1[[#This Row],[Identificador]],'P&L Total'!A:L,12,FALSE) -> -0.0029078851 | N37: =WORKDAY(Tabla1[[#This Row],[Fecha de compra]],0) -> 45944 | O37: Liquidado
A38: =+IF(COUNTIF(Tabla2[Cod_ope],Tabla1[[#This Row],[Cod_Ope]])>0,"out","stock") -> stock | B38: 45945 | C38: 39592 | D38: SIDERC1 | E38: PEP531001001 | F38: {=_xll.BDP(G38,"DS004")} -> PEN | G38: =D38& " PE Equity" -> SIDERC1 PE Equity | H38: =+_xll.BDP($G38,"Name") -> EMPRESA SIDERURGICA PERU SAA | I38: =+_xlfn.CONCAT(Tabla1[[#This Row],[Fecha de compra]],Tabla1[[#This Row],[Ticker]],Tabla1[[#This Row],[Q]]) -> 45945SIDERC115000 | J38: 15000 | K38: 1.76 | L38: =+Tabla1[[#This Row],[Q]]*Tabla1[[#This Row],[P]] -> 26400 | M38: =+VLOOKUP(Tabla1[[#This Row],[Identificador]],'P&L Total'!A:L,12,FALSE) -> 0.34374633 | N38: =WORKDAY(Tabla1[[#This Row],[Fecha de compra]],0) -> 45945 | O38: Liquidado
A39: =+IF(COUNTIF(Tabla2[Cod_ope],Tabla1[[#This Row],[Cod_Ope]])>0,"out","stock") -> stock | B39: 45945 | C39: 39592 | D39: SIDERC1 | E39: PEP531001001 | F39: {=_xll.BDP(G39,"DS004")} -> PEN | G39: =D39& " PE Equity" -> SIDERC1 PE Equity | H39: =+_xll.BDP($G39,"Name") -> EMPRESA SIDERURGICA PERU SAA | I39: =+_xlfn.CONCAT(Tabla1[[#This Row],[Fecha de compra]],Tabla1[[#This Row],[Ticker]],Tabla1[[#This Row],[Q]]) -> 45945SIDERC114649 | J39: 14649 | K39: 1.76 | L39: =+Tabla1[[#This Row],[Q]]*Tabla1[[#This Row],[P]] -> 25782.24 | M39: =+VLOOKUP(Tabla1[[#This Row],[Identificador]],'P&L Total'!A:L,12,FALSE) -> 0.34374633 | N39: =WORKDAY(Tabla1[[#This Row],[Fecha de compra]],0) -> 45945 | O39: Liquidado
A40: =+IF(COUNTIF(Tabla2[Cod_ope],Tabla1[[#This Row],[Cod_Ope]])>0,"out","stock") -> stock | B40: 45945 | C40: 39592 | D40: FERREYC1 | E40: PEP736001004 | F40: {=_xll.BDP(G40,"DS004")} -> PEN | G40: =D40& " pe Equity" -> FERREYC1 pe Equity | H40: =+_xll.BDP($G40,"Name") -> FERREYCORP SAA | I40: =+_xlfn.CONCAT(Tabla1[[#This Row],[Fecha de compra]],Tabla1[[#This Row],[Ticker]],Tabla1[[#This Row],[Q]]) -> 45945FERREYC119770 | J40: =150+19083+537 -> 19770 | K40: 3.35 | L40: =+Tabla1[[#This Row],[Q]]*Tabla1[[#This Row],[P]] -> 66229.5 | M40: =+VLOOKUP(Tabla1[[#This Row],[Identificador]],'P&L Total'!A:L,12,FALSE) -> 0.26768554 | N40: =WORKDAY(Tabla1[[#This Row],[Fecha de compra]],0) -> 45945 | O40: Liquidado
A41: =+IF(COUNTIF(Tabla2[Cod_ope],Tabla1[[#This Row],[Cod_Ope]])>0,"out","stock") -> stock | B41: 45951 | C41: 39592 | D41: MINSURI1 | E41: PEP622005002 | F41: {=_xll.BDP(G41,"DS004")} -> PEN | G41: =D41& " pe Equity" -> MINSURI1 pe Equity | H41: =+_xll.BDP($G41,"Name") -> MINSUR SA-INVERSIONES | I41: =+_xlfn.CONCAT(Tabla1[[#This Row],[Fecha de compra]],Tabla1[[#This Row],[Ticker]],Tabla1[[#This Row],[Q]]) -> 45951MINSURI115000 | J41: 15000 | K41: 4.48 | L41: =+Tabla1[[#This Row],[Q]]*Tabla1[[#This Row],[P]] -> 67200 | M41: =+VLOOKUP(Tabla1[[#This Row],[Identificador]],'P&L Total'!A:L,12,FALSE) -> 0.30273197 | N41: =WORKDAY(Tabla1[[#This Row],[Fecha de compra]],0) -> 45951 | O41: Liquidado
A42: =+IF(COUNTIF(Tabla2[Cod_ope],Tabla1[[#This Row],[Cod_Ope]])>0,"out","stock") -> stock | B42: 45951 | C42: 39592 | D42: MINSURI1 | E42: PEP622005002 | F42: {=_xll.BDP(G42,"DS004")} -> PEN | G42: =D42& " pe Equity" -> MINSURI1 pe Equity | H42: =+_xll.BDP($G42,"Name") -> MINSUR SA-INVERSIONES | I42: =+_xlfn.CONCAT(Tabla1[[#This Row],[Fecha de compra]],Tabla1[[#This Row],[Ticker]],Tabla1[[#This Row],[Q]]) -> 45951MINSURI115000 | J42: 15000 | K42: 4.45 | L42: =+Tabla1[[#This Row],[Q]]*Tabla1[[#This Row],[P]] -> 66750 | M42: =+VLOOKUP(Tabla1[[#This Row],[Identificador]],'P&L Total'!A:L,12,FALSE) -> 0.30273197 | N42: =WORKDAY(Tabla1[[#This Row],[Fecha de compra]],0) -> 45951 | O42: Liquidado
A43: =+IF(COUNTIF(Tabla2[Cod_ope],Tabla1[[#This Row],[Cod_Ope]])>0,"out","stock") -> stock | B43: 45951 | C43: 39592 | D43: MINSURI1 | E43: PEP622005002 | F43: {=_xll.BDP(G43,"DS004")} -> PEN | G43: =D43& " pe Equity" -> MINSURI1 pe Equity | H43: =+_xll.BDP($G43,"Name") -> MINSUR SA-INVERSIONES | I43: =+_xlfn.CONCAT(Tabla1[[#This Row],[Fecha de compra]],Tabla1[[#This Row],[Ticker]],Tabla1[[#This Row],[Q]]) -> 45951MINSURI115000 | J43: 15000 | K43: 4.4 | L43: =+Tabla1[[#This Row],[Q]]*Tabla1[[#This Row],[P]] -> 66000 | M43: =+VLOOKUP(Tabla1[[#This Row],[Identificador]],'P&L Total'!A:L,12,FALSE) -> 0.30273197 | N43: =WORKDAY(Tabla1[[#This Row],[Fecha de compra]],0) -> 45951 | O43: Liquidado
A44: =+IF(COUNTIF(Tabla2[Cod_ope],Tabla1[[#This Row],[Cod_Ope]])>0,"out","stock") -> out | B44: 45951 | C44: 39592 | D44: BVN | E44: US2044481040 | F44: {=_xll.BDP(G44,"DS004")} -> USD | G44: =D44& " us Equity" -> BVN us Equity | H44: =+_xll.BDP($G44,"Name") -> CIA DE MINAS BUENAVENTUR-ADR | I44: =+_xlfn.CONCAT(Tabla1[[#This Row],[Fecha de compra]],Tabla1[[#This Row],[Ticker]],Tabla1[[#This Row],[Q]]) -> 45951BVN2612 | J44: =2464+148 -> 2612 | K44: 22.92 | L44: =+Tabla1[[#This Row],[Q]]*Tabla1[[#This Row],[P]] -> 59867.04 | M44: =+VLOOKUP(Tabla1[[#This Row],[Identificador]],'P&L Total'!A:L,12,FALSE) -> 0.065707417 | N44: =WORKDAY(Tabla1[[#This Row],[Fecha de compra]],0) -> 45951 | O44: Liquidado
A45: =+IF(COUNTIF(Tabla2[Cod_ope],Tabla1[[#This Row],[Cod_Ope]])>0,"out","stock") -> stock | B45: 45951 | C45: 39592 | D45: AUNA | E45: LU2791994721 | F45: {=_xll.BDP(G45,"DS004")} -> USD | G45: =D45& " us Equity" -> AUNA us Equity | H45: =+_xll.BDP($G45,"Name") -> AUNA SA-CLASS A | I45: =+_xlfn.CONCAT(Tabla1[[#This Row],[Fecha de compra]],Tabla1[[#This Row],[Ticker]],Tabla1[[#This Row],[Q]]) -> 45951AUNA10000 | J45: 10000 | K45: 6.318 | L45: =+Tabla1[[#This Row],[Q]]*Tabla1[[#This Row],[P]] -> 63180 | M45: =+VLOOKUP(Tabla1[[#This Row],[Identificador]],'P&L Total'!A:L,12,FALSE) -> -0.086320452 | N45: =WORKDAY(Tabla1[[#This Row],[Fecha de compra]],0) -> 45951 | O45: Liquidado
A46: =+IF(COUNTIF(Tabla2[Cod_ope],Tabla1[[#This Row],[Cod_Ope]])>0,"out","stock") -> stock | B46: 45952 | C46: 39592 | D46: MINSURI1 | E46: PEP622005002 | F46: {=_xll.BDP(G46,"DS004")} -> PEN | G46: =D46& " pe Equity" -> MINSURI1 pe Equity | H46: =+_xll.BDP($G46,"Name") -> MINSUR SA-INVERSIONES | I46: =+_xlfn.CONCAT(Tabla1[[#This Row],[Fecha de compra]],Tabla1[[#This Row],[Ticker]],Tabla1[[#This Row],[Q]]) -> 45952MINSURI110000 | J46: 10000 | K46: 4.41 | L46: =+Tabla1[[#This Row],[Q]]*Tabla1[[#This Row],[P]] -> 44100 | M46: =+VLOOKUP(Tabla1[[#This Row],[Identificador]],'P&L Total'!A:L,12,FALSE) -> 0.30273197 | N46: =WORKDAY(Tabla1[[#This Row],[Fecha de compra]],0) -> 45952 | O46: Liquidado
A47: =+IF(COUNTIF(Tabla2[Cod_ope],Tabla1[[#This Row],[Cod_Ope]])>0,"out","stock") -> stock | B47: 45952 | C47: 39592 | D47: MINSURI1 | E47: PEP622005002 | F47: {=_xll.BDP(G47,"DS004")} -> PEN | G47: =D47& " pe Equity" -> MINSURI1 pe Equity | H47: =+_xll.BDP($G47,"Name") -> MINSUR SA-INVERSIONES | I47: =+_xlfn.CONCAT(Tabla1[[#This Row],[Fecha de compra]],Tabla1[[#This Row],[Ticker]],Tabla1[[#This Row],[Q]]) -> 45952MINSURI110000 | J47: 10000 | K47: 4.38 | L47: =+Tabla1[[#This Row],[Q]]*Tabla1[[#This Row],[P]] -> 43800 | M47: =+VLOOKUP(Tabla1[[#This Row],[Identificador]],'P&L Total'!A:L,12,FALSE) -> 0.30273197 | N47: =WORKDAY(Tabla1[[#This Row],[Fecha de compra]],0) -> 45952 | O47: Liquidado
A48: =+IF(COUNTIF(Tabla2[Cod_ope],Tabla1[[#This Row],[Cod_Ope]])>0,"out","stock") -> stock | B48: 45952 | C48: 39592 | D48: MINSURI1 | E48: PEP622005002 | F48: {=_xll.BDP(G48,"DS004")} -> PEN | G48: =D48& " pe Equity" -> MINSURI1 pe Equity | H48: =+_xll.BDP($G48,"Name") -> MINSUR SA-INVERSIONES | I48: =+_xlfn.CONCAT(Tabla1[[#This Row],[Fecha de compra]],Tabla1[[#This Row],[Ticker]],Tabla1[[#This Row],[Q]]) -> 45952MINSURI110000 | J48: 10000 | K48: 4.35 | L48: =+Tabla1[[#This Row],[Q]]*Tabla1[[#This Row],[P]] -> 43500 | M48: =+VLOOKUP(Tabla1[[#This Row],[Identificador]],'P&L Total'!A:L,12,FALSE) -> 0.30273197 | N48: =WORKDAY(Tabla1[[#This Row],[Fecha de compra]],0) -> 45952 | O48: Liquidado
A49: =+IF(COUNTIF(Tabla2[Cod_ope],Tabla1[[#This Row],[Cod_Ope]])>0,"out","stock") -> stock | B49: 45952 | C49: 39592 | D49: FERREYC1 | E49: PEP736001004 | F49: {=_xll.BDP(G49,"DS004")} -> PEN | G49: =D49& " pe Equity" -> FERREYC1 pe Equity | H49: =+_xll.BDP($G49,"Name") -> FERREYCORP SAA | I49: =+_xlfn.CONCAT(Tabla1[[#This Row],[Fecha de compra]],Tabla1[[#This Row],[Ticker]],Tabla1[[#This Row],[Q]]) -> 45952FERREYC120000 | J49: 20000 | K49: 3.32 | L49: =+Tabla1[[#This Row],[Q]]*Tabla1[[#This Row],[P]] -> 66400 | M49: =+VLOOKUP(Tabla1[[#This Row],[Identificador]],'P&L Total'!A:L,12,FALSE) -> 0.26768554 | N49: =WORKDAY(Tabla1[[#This Row],[Fecha de compra]],0) -> 45952 | O49: Liquidado
A50: =+IF(COUNTIF(Tabla2[Cod_ope],Tabla1[[#This Row],[Cod_Ope]])>0,"out","stock") -> stock | B50: 45952 | C50: 39592 | D50: FERREYC1 | E50: PEP736001004 | F50: {=_xll.BDP(G50,"DS004")} -> PEN | G50: =D50& " pe Equity" -> FERREYC1 pe Equity | H50: =+_xll.BDP($G50,"Name") -> FERREYCORP SAA | I50: =+_xlfn.CONCAT(Tabla1[[#This Row],[Fecha de compra]],Tabla1[[#This Row],[Ticker]],Tabla1[[#This Row],[Q]]) -> 45952FERREYC120000 | J50: 20000 | K50: 3.3 | L50: =+Tabla1[[#This Row],[Q]]*Tabla1[[#This Row],[P]] -> 66000 | M50: =+VLOOKUP(Tabla1[[#This Row],[Identificador]],'P&L Total'!A:L,12,FALSE) -> 0.26768554 | N50: =WORKDAY(Tabla1[[#This Row],[Fecha de compra]],0) -> 45952 | O50: Liquidado
A51: =+IF(COUNTIF(Tabla2[Cod_ope],Tabla1[[#This Row],[Cod_Ope]])>0,"out","stock") -> out | B51: 45952 | C51: 39592 | D51: BVN | E51: US2044481040 | F51: {=_xll.BDP(G51,"DS004")} -> USD | G51: =D51& " us Equity" -> BVN us Equity | H51: =+_xll.BDP($G51,"Name") -> CIA DE MINAS BUENAVENTUR-ADR | I51: =+_xlfn.CONCAT(Tabla1[[#This Row],[Fecha de compra]],Tabla1[[#This Row],[Ticker]],Tabla1[[#This Row],[Q]]) -> 45952BVN2000 | J51: 2000 | K51: 22.6665 | L51: =+Tabla1[[#This Row],[Q]]*Tabla1[[#This Row],[P]] -> 45333 | M51: =+VLOOKUP(Tabla1[[#This Row],[Identificador]],'P&L Total'!A:L,12,FALSE) -> 0.065707417 | N51: =WORKDAY(Tabla1[[#This Row],[Fecha de compra]],0) -> 45952 | O51: Liquidado
A52: =+IF(COUNTIF(Tabla2[Cod_ope],Tabla1[[#This Row],[Cod_Ope]])>0,"out","stock") -> stock | B52: 45952 | C52: 39592 | D52: AUNA | E52: LU2791994721 | F52: {=_xll.BDP(G52,"DS004")} -> USD | G52: =D52& " us Equity" -> AUNA us Equity | H52: =+_xll.BDP($G52,"Name") -> AUNA SA-CLASS A | I52: =+_xlfn.CONCAT(Tabla1[[#This Row],[Fecha de compra]],Tabla1[[#This Row],[Ticker]],Tabla1[[#This Row],[Q]]) -> 45952AUNA5000 | J52: 5000 | K52: 6.383 | L52: =+Tabla1[[#This Row],[Q]]*Tabla1[[#This Row],[P]] -> 31915 | M52: =+VLOOKUP(Tabla1[[#This Row],[Identificador]],'P&L Total'!A:L,12,FALSE) -> -0.086320452 | N52: =WORKDAY(Tabla1[[#This Row],[Fecha de compra]],0) -> 45952 | O52: Liquidado
A53: =+IF(COUNTIF(Tabla2[Cod_ope],Tabla1[[#This Row],[Cod_Ope]])>0,"out","stock") -> stock | B53: 45957 | C53: 39592 | D53: MINSURI1 | E53: PEP622005002 | F53: {=_xll.BDP(G53,"DS004")} -> PEN | G53: =D53& " pe Equity" -> MINSURI1 pe Equity | H53: =+_xll.BDP($G53,"Name") -> MINSUR SA-INVERSIONES | I53: =+_xlfn.CONCAT(Tabla1[[#This Row],[Fecha de compra]],Tabla1[[#This Row],[Ticker]],Tabla1[[#This Row],[Q]]) -> 45957MINSURI15580 | J53: 5580 | K53: 4.23 | L53: =+Tabla1[[#This Row],[Q]]*Tabla1[[#This Row],[P]] -> 23603.4 | M53: =+VLOOKUP(Tabla1[[#This Row],[Identificador]],'P&L Total'!A:L,12,FALSE) -> 0.30273197 | N53: =WORKDAY(Tabla1[[#This Row],[Fecha de compra]],0) -> 45957 | O53: Liquidado
A54: =+IF(COUNTIF(Tabla2[Cod_ope],Tabla1[[#This Row],[Cod_Ope]])>0,"out","stock") -> stock | B54: 45967 | C54: 39592 | D54: EEM | E54: US4642872349 | F54: {=_xll.BDP(G54,"DS004")} -> USD | G54: =D54& " US Equity" -> EEM US Equity | H54: =+_xll.BDP($G54,"Name") -> ISHARES MSCI EMERGING MARKET | I54: =+_xlfn.CONCAT(Tabla1[[#This Row],[Fecha de compra]],Tabla1[[#This Row],[Ticker]],Tabla1[[#This Row],[Q]]) -> 45967EEM1462 | J54: 1462 | K54: 54.61 | L54: =+Tabla1[[#This Row],[Q]]*Tabla1[[#This Row],[P]] -> 79839.82 | M54: =+VLOOKUP(Tabla1[[#This Row],[Identificador]],'P&L Total'!A:L,12,FALSE) -> 0.098275989 | N54: =WORKDAY(Tabla1[[#This Row],[Fecha de compra]],0) -> 45967 | O54: Liquidado
A55: =+IF(COUNTIF(Tabla2[Cod_ope],Tabla1[[#This Row],[Cod_Ope]])>0,"out","stock") -> stock | B55: 45967 | C55: 39592 | D55: PFE | E55: US7170811035 | F55: {=_xll.BDP(G55,"DS004")} -> USD | G55: =D55& " US Equity" -> PFE US Equity | H55: =+_xll.BDP($G55,"Name") -> PFIZER INC | I55: =+_xlfn.CONCAT(Tabla1[[#This Row],[Fecha de compra]],Tabla1[[#This Row],[Ticker]],Tabla1[[#This Row],[Q]]) -> 45967PFE3195 | J55: 3195 | K55: 25.029601 | L55: =+Tabla1[[#This Row],[Q]]*Tabla1[[#This Row],[P]] -> 79969.575 | M55: =+VLOOKUP(Tabla1[[#This Row],[Identificador]],'P&L Total'!A:L,12,FALSE) -> 0.10229484 | N55: =WORKDAY(Tabla1[[#This Row],[Fecha de compra]],0) -> 45967 | O55: Liquidado
A56: =+IF(COUNTIF(Tabla2[Cod_ope],Tabla1[[#This Row],[Cod_Ope]])>0,"out","stock") -> out | B56: 45967 | C56: 39592 | D56: PLTR | E56: US69608A1088 | F56: {=_xll.BDP(G56,"DS004")} -> USD | G56: =D56& " US Equity" -> PLTR US Equity | H56: =+_xll.BDP($G56,"Name") -> PALANTIR TECHNOLOGIES INC-A | I56: =+_xlfn.CONCAT(Tabla1[[#This Row],[Fecha de compra]],Tabla1[[#This Row],[Ticker]],Tabla1[[#This Row],[Q]]) -> 45967PLTR434 | J56: 434 | K56: 184.31 | L56: =+Tabla1[[#This Row],[Q]]*Tabla1[[#This Row],[P]] -> 79990.54 | M56: =+VLOOKUP(Tabla1[[#This Row],[Identificador]],'P&L Total'!A:L,12,FALSE) -> 0.048158251 | N56: =WORKDAY(Tabla1[[#This Row],[Fecha de compra]],0) -> 45967 | O56: Liquidado
A57: =+IF(COUNTIF(Tabla2[Cod_ope],Tabla1[[#This Row],[Cod_Ope]])>0,"out","stock") -> out | B57: 45967 | C57: 39592 | D57: VOLCABC1 | E57: PEP648014202 | F57: {=_xll.BDP(G57,"DS004")} -> PEN | G57: =D57& " pe Equity" -> VOLCABC1 pe Equity | H57: =+_xll.BDP($G57,"Name") -> VOLCAN CIA MINERA SAA-CMN B | I57: =+_xlfn.CONCAT(Tabla1[[#This Row],[Fecha de compra]],Tabla1[[#This Row],[Ticker]],Tabla1[[#This Row],[Q]]) -> 45967VOLCABC1167440 | J57: =95000+72150+290 -> 167440 | K57: 0.465 | L57: =+Tabla1[[#This Row],[Q]]*Tabla1[[#This Row],[P]] -> 77859.6 | M57: =+VLOOKUP(Tabla1[[#This Row],[Identificador]],'P&L Total'!A:L,12,FALSE) -> 0.031459705 | N57: =WORKDAY(Tabla1[[#This Row],[Fecha de compra]],0) -> 45967 | O57: Liquidado
A58: =+IF(COUNTIF(Tabla2[Cod_ope],Tabla1[[#This Row],[Cod_Ope]])>0,"out","stock") -> out | B58: 45967 | C58: 39592 | D58: VOLCABC1 | E58: PEP648014202 | F58: {=_xll.BDP(G58,"DS004")} -> PEN | G58: =D58& " pe Equity" -> VOLCABC1 pe Equity | H58: =+_xll.BDP($G58,"Name") -> VOLCAN CIA MINERA SAA-CMN B | I58: =+_xlfn.CONCAT(Tabla1[[#This Row],[Fecha de compra]],Tabla1[[#This Row],[Ticker]],Tabla1[[#This Row],[Q]]) -> 45967VOLCABC150 | J58: 50 | K58: 0.463 | L58: =+Tabla1[[#This Row],[Q]]*Tabla1[[#This Row],[P]] -> 23.15 | M58: =+VLOOKUP(Tabla1[[#This Row],[Identificador]],'P&L Total'!A:L,12,FALSE) -> 0.031459705 | N58: =WORKDAY(Tabla1[[#This Row],[Fecha de compra]],0) -> 45967 | O58: Liquidado
A59: =+IF(COUNTIF(Tabla2[Cod_ope],Tabla1[[#This Row],[Cod_Ope]])>0,"out","stock") -> stock | B59: 45967 | C59: 39592 | D59: UNH | E59: US91324P1021 | F59: {=_xll.BDP(G59,"DS004")} -> USD | G59: =D59& " US Equity" -> UNH US Equity | H59: =+_xll.BDP($G59,"Name") -> UNITEDHEALTH GROUP INC | I59: =+_xlfn.CONCAT(Tabla1[[#This Row],[Fecha de compra]],Tabla1[[#This Row],[Ticker]],Tabla1[[#This Row],[Q]]) -> 45967UNH153 | J59: 153 | K59: 324.9156 | L59: =+Tabla1[[#This Row],[Q]]*Tabla1[[#This Row],[P]] -> 49712.087 | M59: =+VLOOKUP(Tabla1[[#This Row],[Identificador]],'P&L Total'!A:L,12,FALSE) -> -0.16883552 | N59: =WORKDAY(Tabla1[[#This Row],[Fecha de compra]],1) -> 45968 | O59: Liquidado
A60: =+IF(COUNTIF(Tabla2[Cod_ope],Tabla1[[#This Row],[Cod_Ope]])>0,"out","stock") -> out | B60: 45968 | C60: 39592 | D60: EWQ | E60: US4642867075 | F60: {=_xll.BDP(G60,"DS004")} -> USD | G60: =D60& " US Equity" -> EWQ US Equity | H60: =+_xll.BDP($G60,"Name") -> ISHARES MSCI FRANCE ETF | I60: =+_xlfn.CONCAT(Tabla1[[#This Row],[Fecha de compra]],Tabla1[[#This Row],[Ticker]],Tabla1[[#This Row],[Q]]) -> 45968EWQ1839 | J60: 1839 | K60: 43.48 | L60: =+Tabla1[[#This Row],[Q]]*Tabla1[[#This Row],[P]] -> 79959.72 | M60: =+VLOOKUP(Tabla1[[#This Row],[Identificador]],'P&L Total'!A:L,12,FALSE) -> 0.062284154 | N60: =WORKDAY(Tabla1[[#This Row],[Fecha de compra]],0) -> 45968 | O60: Liquidado
A61: =+IF(COUNTIF(Tabla2[Cod_ope],Tabla1[[#This Row],[Cod_Ope]])>0,"out","stock") -> out | B61: 45968 | C61: 39592 | D61: PLTR | E61: US69608A1088 | F61: {=_xll.BDP(G61,"DS004")} -> USD | G61: =D61& " US Equity" -> PLTR US Equity | H61: =+_xll.BDP($G61,"Name") -> PALANTIR TECHNOLOGIES INC-A | I61: =+_xlfn.CONCAT(Tabla1[[#This Row],[Fecha de compra]],Tabla1[[#This Row],[Ticker]],Tabla1[[#This Row],[Q]]) -> 45968PLTR117 | J61: 117 | K61: 170.01 | L61: =+Tabla1[[#This Row],[Q]]*Tabla1[[#This Row],[P]] -> 19891.17 | M61: =+VLOOKUP(Tabla1[[#This Row],[Identificador]],'P&L Total'!A:L,12,FALSE) -> 0.048158251 | N61: =WORKDAY(Tabla1[[#This Row],[Fecha de compra]],0) -> 45968 | O61: Liquidado
A62: =+IF(COUNTIF(Tabla2[Cod_ope],Tabla1[[#This Row],[Cod_Ope]])>0,"out","stock") -> out | B62: 45968 | C62: 39592 | D62: VOLCABC1 | E62: PEP648014202 | F62: {=_xll.BDP(G62,"DS004")} -> PEN | G62: =D62& " pe Equity" -> VOLCABC1 pe Equity | H62: =+_xll.BDP($G62,"Name") -> VOLCAN CIA MINERA SAA-CMN B | I62: =+_xlfn.CONCAT(Tabla1[[#This Row],[Fecha de compra]],Tabla1[[#This Row],[Ticker]],Tabla1[[#This Row],[Q]]) -> 45968VOLCABC1100000 | J62: 100000 | K62: 0.466 | L62: =+Tabla1[[#This Row],[Q]]*Tabla1[[#This Row],[P]] -> 46600 | M62: =+VLOOKUP(Tabla1[[#This Row],[Identificador]],'P&L Total'!A:L,12,FALSE) -> 0.031459705 | N62: =WORKDAY(Tabla1[[#This Row],[Fecha de compra]],0) -> 45968 | O62: Liquidado
A63: =+IF(COUNTIF(Tabla2[Cod_ope],Tabla1[[#This Row],[Cod_Ope]])>0,"out","stock") -> out | B63: 45968 | C63: 39592 | D63: VOLCABC1 | E63: PEP648014202 | F63: {=_xll.BDP(G63,"DS004")} -> PEN | G63: =D63& " pe Equity" -> VOLCABC1 pe Equity | H63: =+_xll.BDP($G63,"Name") -> VOLCAN CIA MINERA SAA-CMN B | I63: =+_xlfn.CONCAT(Tabla1[[#This Row],[Fecha de compra]],Tabla1[[#This Row],[Ticker]],Tabla1[[#This Row],[Q]]) -> 45968VOLCABC199560 | J63: 99560 | K63: 0.463 | L63: =+Tabla1[[#This Row],[Q]]*Tabla1[[#This Row],[P]] -> 46096.28 | M63: =+VLOOKUP(Tabla1[[#This Row],[Identificador]],'P&L Total'!A:L,12,FALSE) -> 0.031459705 | N63: =WORKDAY(Tabla1[[#This Row],[Fecha de compra]],0) -> 45968 | O63: Liquidado
A64: =+IF(COUNTIF(Tabla2[Cod_ope],Tabla1[[#This Row],[Cod_Ope]])>0,"out","stock") -> out | B64: 45968 | C64: 39592 | D64: VOLCABC1 | E64: PEP648014202 | F64: {=_xll.BDP(G64,"DS004")} -> PEN | G64: =D64& " pe Equity" -> VOLCABC1 pe Equity | H64: =+_xll.BDP($G64,"Name") -> VOLCAN CIA MINERA SAA-CMN B | I64: =+_xlfn.CONCAT(Tabla1[[#This Row],[Fecha de compra]],Tabla1[[#This Row],[Ticker]],Tabla1[[#This Row],[Q]]) -> 45968VOLCABC1440 | J64: 440 | K64: 0.463 | L64: =+Tabla1[[#This Row],[Q]]*Tabla1[[#This Row],[P]] -> 203.72 | M64: =+VLOOKUP(Tabla1[[#This Row],[Identificador]],'P&L Total'!A:L,12,FALSE) -> 0.031459705 | N64: =WORKDAY(Tabla1[[#This Row],[Fecha de compra]],0) -> 45968 | O64: Liquidado
A65: =+IF(COUNTIF(Tabla2[Cod_ope],Tabla1[[#This Row],[Cod_Ope]])>0,"out","stock") -> out | B65: 45968 | C65: 39592 | D65: SPY | E65: US78462F1030 | F65: {=_xll.BDP(G65,"DS004")} -> USD | G65: =D65& " US Equity" -> SPY US Equity | H65: =+_xll.BDP($G65,"Name") -> SS SPDR S&P 500 ETF TRUST-US | I65: =+_xlfn.CONCAT(Tabla1[[#This Row],[Fecha de compra]],Tabla1[[#This Row],[Ticker]],Tabla1[[#This Row],[Q]]) -> 45968SPY90 | J65: 90 | K65: 663.09 | L65: =+Tabla1[[#This Row],[Q]]*Tabla1[[#This Row],[P]] -> 59678.1 | M65: =+VLOOKUP(Tabla1[[#This Row],[Identificador]],'P&L Total'!A:L,12,FALSE) -> 0.036936014 | N65: =WORKDAY(Tabla1[[#This Row],[Fecha de compra]],0) -> 45968 | O65: Liquidado
A66: =+IF(COUNTIF(Tabla2[Cod_ope],Tabla1[[#This Row],[Cod_Ope]])>0,"out","stock") -> out | B66: 45968 | C66: 39592 | D66: QQQ | E66: US46090E1038 | F66: {=_xll.BDP(G66,"DS004")} -> USD | G66: =D66& " US Equity" -> QQQ US Equity | H66: =+_xll.BDP($G66,"Name") -> INVESCO QQQ TRUST SERIES 1 | I66: =+_xlfn.CONCAT(Tabla1[[#This Row],[Fecha de compra]],Tabla1[[#This Row],[Ticker]],Tabla1[[#This Row],[Q]]) -> 45968QQQ83 | J66: 83 | K66: 601.32 | L66: =+Tabla1[[#This Row],[Q]]*Tabla1[[#This Row],[P]] -> 49909.56 | M66: =+VLOOKUP(Tabla1[[#This Row],[Identificador]],'P&L Total'!A:L,12,FALSE) -> 0.020044586 | N66: =WORKDAY(Tabla1[[#This Row],[Fecha de compra]],0) -> 45968 | O66: Liquidado
A67: =+IF(COUNTIF(Tabla2[Cod_ope],Tabla1[[#This Row],[Cod_Ope]])>0,"out","stock") -> stock | B67: 45973 | C67: 39592 | D67: BAP | E67: BMG2519Y1084 | F67: {=_xll.BDP(G67,"DS004")} -> USD | G67: =D67& " US Equity" -> BAP US Equity | H67: =+_xll.BDP($G67,"Name") -> CREDICORP LTD | I67: =+_xlfn.CONCAT(Tabla1[[#This Row],[Fecha de compra]],Tabla1[[#This Row],[Ticker]],Tabla1[[#This Row],[Q]]) -> 45973BAP383 | J67: 383 | K67: 260.735 | L67: =+Tabla1[[#This Row],[Q]]*Tabla1[[#This Row],[P]] -> 99861.505 | M67: =+VLOOKUP(Tabla1[[#This Row],[Identificador]],'P&L Total'!A:L,12,FALSE) -> 0.15438165 | N67: =WORKDAY(Tabla1[[#This Row],[Fecha de compra]],0) -> 45973 | O67: Liquidado
A68: =+IF(COUNTIF(Tabla2[Cod_ope],Tabla1[[#This Row],[Cod_Ope]])>0,"out","stock") -> out | B68: 45973 | C68: 39592 | D68: PLTR | E68: US69608A1088 | F68: {=_xll.BDP(G68,"DS004")} -> USD | G68: =D68& " US Equity" -> PLTR US Equity | H68: =+_xll.BDP($G68,"Name") -> PALANTIR TECHNOLOGIES INC-A | I68: =+_xlfn.CONCAT(Tabla1[[#This Row],[Fecha de compra]],Tabla1[[#This Row],[Ticker]],Tabla1[[#This Row],[Q]]) -> 45973PLTR439 | J68: 439 | K68: 181.99 | L68: =+Tabla1[[#This Row],[Q]]*Tabla1[[#This Row],[P]] -> 79893.61 | M68: =+VLOOKUP(Tabla1[[#This Row],[Identificador]],'P&L Total'!A:L,12,FALSE) -> 0.048158251 | N68: =WORKDAY(Tabla1[[#This Row],[Fecha de compra]],0) -> 45973 | O68: Liquidado
A69: =+IF(COUNTIF(Tabla2[Cod_ope],Tabla1[[#This Row],[Cod_Ope]])>0,"out","stock") -> stock | B69: 45973 | C69: 39592 | D69: TTWO | E69: US8740541094 | F69: {=_xll.BDP(G69,"DS004")} -> USD | G69: =D69& " US Equity" -> TTWO US Equity | H69: =+_xll.BDP($G69,"Name") -> TAKE-TWO INTERACTIVE SOFTWRE | I69: =+_xlfn.CONCAT(Tabla1[[#This Row],[Fecha de compra]],Tabla1[[#This Row],[Ticker]],Tabla1[[#This Row],[Q]]) -> 45973TTWO330 | J69: 330 | K69: 241.52 | L69: =+Tabla1[[#This Row],[Q]]*Tabla1[[#This Row],[P]] -> 79701.6 | M69: =+VLOOKUP(Tabla1[[#This Row],[Identificador]],'P&L Total'!A:L,12,FALSE) -> -0.134316 | N69: =WORKDAY(Tabla1[[#This Row],[Fecha de compra]],1) -> 45974 | O69: Liquidado
A70: =+IF(COUNTIF(Tabla2[Cod_ope],Tabla1[[#This Row],[Cod_Ope]])>0,"out","stock") -> stock | B70: 45974 | C70: 39592 | D70: TAN | E70: US46138G7060 | F70: {=_xll.BDP(G70,"DS004")} -> USD | G70: =D70& " US Equity" -> TAN US Equity | H70: =+_xll.BDP($G70,"Name") -> INVESCO SOLAR ETF | I70: =+_xlfn.CONCAT(Tabla1[[#This Row],[Fecha de compra]],Tabla1[[#This Row],[Ticker]],Tabla1[[#This Row],[Q]]) -> 45974TAN1019 | J70: 1019 | K70: 49 | L70: =+Tabla1[[#This Row],[Q]]*Tabla1[[#This Row],[P]] -> 49931 | M70: =+VLOOKUP(Tabla1[[#This Row],[Identificador]],'P&L Total'!A:L,12,FALSE) -> 0.12040816 | N70: =WORKDAY(Tabla1[[#This Row],[Fecha de compra]],0) -> 45974 | O70: Liquidado
A71: =+IF(COUNTIF(Tabla2[Cod_ope],Tabla1[[#This Row],[Cod_Ope]])>0,"out","stock") -> stock | B71: 45974 | C71: 39592 | D71: ICLN | E71: US4642882249 | F71: {=_xll.BDP(G71,"DS004")} -> USD | G71: =D71& " US Equity" -> ICLN US Equity | H71: =+_xll.BDP($G71,"Name") -> ISHARES GLOBAL CLEAN ENERGY | I71: =+_xlfn.CONCAT(Tabla1[[#This Row],[Fecha de compra]],Tabla1[[#This Row],[Ticker]],Tabla1[[#This Row],[Q]]) -> 45974ICLN4702 | J71: 4702 | K71: 16.9899 | L71: =+Tabla1[[#This Row],[Q]]*Tabla1[[#This Row],[P]] -> 79886.51 | M71: =+VLOOKUP(Tabla1[[#This Row],[Identificador]],'P&L Total'!A:L,12,FALSE) -> 0.081713253 | N71: =WORKDAY(Tabla1[[#This Row],[Fecha de compra]],0) -> 45974 | O71: Liquidado
A72: =+IF(COUNTIF(Tabla2[Cod_ope],Tabla1[[#This Row],[Cod_Ope]])>0,"out","stock") -> out | B72: 45974 | C72: 39592 | D72: PLTR | E72: US69608A1088 | F72: {=_xll.BDP(G72,"DS004")} -> USD | G72: =D72& " US Equity" -> PLTR US Equity | H72: =+_xll.BDP($G72,"Name") -> PALANTIR TECHNOLOGIES INC-A | I72: =+_xlfn.CONCAT(Tabla1[[#This Row],[Fecha de compra]],Tabla1[[#This Row],[Ticker]],Tabla1[[#This Row],[Q]]) -> 45974PLTR172 | J72: 172 | K72: 173.92 | L72: =+Tabla1[[#This Row],[Q]]*Tabla1[[#This Row],[P]] -> 29914.24 | M72: =+VLOOKUP(Tabla1[[#This Row],[Identificador]],'P&L Total'!A:L,12,FALSE) -> 0.048158251 | N72: =WORKDAY(Tabla1[[#This Row],[Fecha de compra]],0) -> 45974 | O72: Liquidado
A73: =+IF(COUNTIF(Tabla2[Cod_ope],Tabla1[[#This Row],[Cod_Ope]])>0,"out","stock") -> stock | B73: 45974 | C73: 39592 | D73: DIS | E73: US2546871060 | F73: {=_xll.BDP(G73,"DS004")} -> USD | G73: =D73& " US Equity" -> DIS US Equity | H73: =+_xll.BDP($G73,"Name") -> WALT DISNEY CO/THE | I73: =+_xlfn.CONCAT(Tabla1[[#This Row],[Fecha de compra]],Tabla1[[#This Row],[Ticker]],Tabla1[[#This Row],[Q]]) -> 45974DIS752 | J73: 752 | K73: 106.14 | L73: =+Tabla1[[#This Row],[Q]]*Tabla1[[#This Row],[P]] -> 79817.28 | M73: =+VLOOKUP(Tabla1[[#This Row],[Identificador]],'P&L Total'!A:L,12,FALSE) -> -0.038345581 | N73: =WORKDAY(Tabla1[[#This Row],[Fecha de compra]],0) -> 45974 | O73: Liquidado
A74: =+IF(COUNTIF(Tabla2[Cod_ope],Tabla1[[#This Row],[Cod_Ope]])>0,"out","stock") -> stock | B74: 45975 | C74: 39592 | D74: XLU | E74: US81369Y8865 | F74: {=_xll.BDP(G74,"DS004")} -> USD | G74: =D74& " US Equity" -> XLU US Equity | H74: =+_xll.BDP($G74,"Name") -> ST SR UTL SL SE SPDR ETF-USD | I74: =+_xlfn.CONCAT(Tabla1[[#This Row],[Fecha de compra]],Tabla1[[#This Row],[Ticker]],Tabla1[[#This Row],[Q]]) -> 45975XLU1128 | J74: =564*2 -> 1128 | K74: =88.4499/2 -> 44.22495 | L74: =+Tabla1[[#This Row],[Q]]*Tabla1[[#This Row],[P]] -> 49885.744 | M74: =+VLOOKUP(Tabla1[[#This Row],[Identificador]],'P&L Total'!A:L,12,FALSE) -> 0.07128845 | N74: =WORKDAY(Tabla1[[#This Row],[Fecha de compra]],0) -> 45975 | O74: Liquidado
A75: =+IF(COUNTIF(Tabla2[Cod_ope],Tabla1[[#This Row],[Cod_Ope]])>0,"out","stock") -> out | B75: 45975 | C75: 39592 | D75: PLTR | E75: US69608A1088 | F75: {=_xll.BDP(G75,"DS004")} -> USD | G75: =D75& " US Equity" -> PLTR US Equity | H75: =+_xll.BDP($G75,"Name") -> PALANTIR TECHNOLOGIES INC-A | I75: =+_xlfn.CONCAT(Tabla1[[#This Row],[Fecha de compra]],Tabla1[[#This Row],[Ticker]],Tabla1[[#This Row],[Q]]) -> 45975PLTR300 | J75: 300 | K75: 166.75 | L75: =+Tabla1[[#This Row],[Q]]*Tabla1[[#This Row],[P]] -> 50025 | M75: =+VLOOKUP(Tabla1[[#This Row],[Identificador]],'P&L Total'!A:L,12,FALSE) -> 0.048158251 | N75: =WORKDAY(Tabla1[[#This Row],[Fecha de compra]],0) -> 45975 | O75: Liquidado
A76: =+IF(COUNTIF(Tabla2[Cod_ope],Tabla1[[#This Row],[Cod_Ope]])>0,"out","stock") -> out | B76: 45975 | C76: 39592 | D76: SPY | E76: US78462F1030 | F76: {=_xll.BDP(G76,"DS004")} -> USD | G76: =D76& " US Equity" -> SPY US Equity | H76: =+_xll.BDP($G76,"Name") -> SS SPDR S&P 500 ETF TRUST-US | I76: =+_xlfn.CONCAT(Tabla1[[#This Row],[Fecha de compra]],Tabla1[[#This Row],[Ticker]],Tabla1[[#This Row],[Q]]) -> 45975SPY75 | J76: 75 | K76: 665.299 | L76: =+Tabla1[[#This Row],[Q]]*Tabla1[[#This Row],[P]] -> 49897.425 | M76: =+VLOOKUP(Tabla1[[#This Row],[Identificador]],'P&L Total'!A:L,12,FALSE) -> 0.036936014 | N76: =WORKDAY(Tabla1[[#This Row],[Fecha de compra]],0) -> 45975 | O76: Liquidado
A77: =+IF(COUNTIF(Tabla2[Cod_ope],Tabla1[[#This Row],[Cod_Ope]])>0,"out","stock") -> out | B77: 45975 | C77: 39592 | D77: QQQ | E77: US46090E1038 | F77: {=_xll.BDP(G77,"DS004")} -> USD | G77: =D77& " US Equity" -> QQQ US Equity | H77: =+_xll.BDP($G77,"Name") -> INVESCO QQQ TRUST SERIES 1 | I77: =+_xlfn.CONCAT(Tabla1[[#This Row],[Fecha de compra]],Tabla1[[#This Row],[Ticker]],Tabla1[[#This Row],[Q]]) -> 45975QQQ83 | J77: 83 | K77: 599.34 | L77: =+Tabla1[[#This Row],[Q]]*Tabla1[[#This Row],[P]] -> 49745.22 | M77: =+VLOOKUP(Tabla1[[#This Row],[Identificador]],'P&L Total'!A:L,12,FALSE) -> 0.020044586 | N77: =WORKDAY(Tabla1[[#This Row],[Fecha de compra]],0) -> 45975 | O77: Liquidado
A78: =+IF(COUNTIF(Tabla2[Cod_ope],Tabla1[[#This Row],[Cod_Ope]])>0,"out","stock") -> stock | B78: 45975 | C78: 39592 | D78: XLY | E78: US81369Y4070 | F78: {=_xll.BDP(G78,"DS004")} -> USD | G78: =D78& " US Equity" -> XLY US Equity | H78: =+_xll.BDP($G78,"Name") -> SS CONSUMER DISC SELECT SECT | I78: =+_xlfn.CONCAT(Tabla1[[#This Row],[Fecha de compra]],Tabla1[[#This Row],[Ticker]],Tabla1[[#This Row],[Q]]) -> 45975XLY434 | J78: =217*2 -> 434 | K78: =229.74/2 -> 114.87 | L78: =+Tabla1[[#This Row],[Q]]*Tabla1[[#This Row],[P]] -> 49853.58 | M78: =+VLOOKUP(Tabla1[[#This Row],[Identificador]],'P&L Total'!A:L,12,FALSE) -> -0.024749212 | N78: =WORKDAY(Tabla1[[#This Row],[Fecha de compra]],0) -> 45975 | O78: Liquidado
A79: =+IF(COUNTIF(Tabla2[Cod_ope],Tabla1[[#This Row],[Cod_Ope]])>0,"out","stock") -> stock | B79: 45988 | C79: 39592 | D79: ORYGENC1 | E79: PEP700511004 | F79: {=_xll.BDP(G79,"DS004")} -> PEN | G79: =D79& " pe Equity" -> ORYGENC1 pe Equity | H79: =+_xll.BDP($G79,"Name") -> ORYGEN PERU SAA | I79: =+_xlfn.CONCAT(Tabla1[[#This Row],[Fecha de compra]],Tabla1[[#This Row],[Ticker]],Tabla1[[#This Row],[Q]]) -> 45988ORYGENC13829 | J79: 3829 | K79: 2.4 | L79: =+Tabla1[[#This Row],[Q]]*Tabla1[[#This Row],[P]] -> 9189.6 | M79: =+VLOOKUP(Tabla1[[#This Row],[Identificador]],'P&L Total'!A:L,12,FALSE) -> 0.30369889 | N79: =WORKDAY(Tabla1[[#This Row],[Fecha de compra]],0) -> 45988 | O79: Liquidado
A80: =+IF(COUNTIF(Tabla2[Cod_ope],Tabla1[[#This Row],[Cod_Ope]])>0,"out","stock") -> stock | B80: 45989 | C80: 39592 | D80: ORYGENC1 | E80: PEP700511004 | F80: {=_xll.BDP(G80,"DS004")} -> PEN | G80: =D80& " pe Equity" -> ORYGENC1 pe Equity | H80: =+_xll.BDP($G80,"Name") -> ORYGEN PERU SAA | I80: =+_xlfn.CONCAT(Tabla1[[#This Row],[Fecha de compra]],Tabla1[[#This Row],[Ticker]],Tabla1[[#This Row],[Q]]) -> 45989ORYGENC115000 | J80: 15000 | K80: 2.42 | L80: =+Tabla1[[#This Row],[Q]]*Tabla1[[#This Row],[P]] -> 36300 | M80: =+VLOOKUP(Tabla1[[#This Row],[Identificador]],'P&L Total'!A:L,12,FALSE) -> 0.30369889 | N80: =WORKDAY(Tabla1[[#This Row],[Fecha de compra]],0) -> 45989 | O80: Liquidado
A81: =+IF(COUNTIF(Tabla2[Cod_ope],Tabla1[[#This Row],[Cod_Ope]])>0,"out","stock") -> stock | B81: 45989 | C81: 39592 | D81: ORYGENC1 | E81: PEP700511004 | F81: {=_xll.BDP(G81,"DS004")} -> PEN | G81: =D81& " pe Equity" -> ORYGENC1 pe Equity | H81: =+_xll.BDP($G81,"Name") -> ORYGEN PERU SAA | I81: =+_xlfn.CONCAT(Tabla1[[#This Row],[Fecha de compra]],Tabla1[[#This Row],[Ticker]],Tabla1[[#This Row],[Q]]) -> 45989ORYGENC115000 | J81: 15000 | K81: 2.41 | L81: =+Tabla1[[#This Row],[Q]]*Tabla1[[#This Row],[P]] -> 36150 | M81: =+VLOOKUP(Tabla1[[#This Row],[Identificador]],'P&L Total'!A:L,12,FALSE) -> 0.30369889 | N81: =WORKDAY(Tabla1[[#This Row],[Fecha de compra]],0) -> 45989 | O81: Liquidado
A82: =+IF(COUNTIF(Tabla2[Cod_ope],Tabla1[[#This Row],[Cod_Ope]])>0,"out","stock") -> stock | B82: 45989 | C82: 39592 | D82: ORYGENC1 | E82: PEP700511004 | F82: {=_xll.BDP(G82,"DS004")} -> PEN | G82: =D82& " pe Equity" -> ORYGENC1 pe Equity | H82: =+_xll.BDP($G82,"Name") -> ORYGEN PERU SAA | I82: =+_xlfn.CONCAT(Tabla1[[#This Row],[Fecha de compra]],Tabla1[[#This Row],[Ticker]],Tabla1[[#This Row],[Q]]) -> 45989ORYGENC115000 | J82: 15000 | K82: 2.4 | L82: =+Tabla1[[#This Row],[Q]]*Tabla1[[#This Row],[P]] -> 36000 | M82: =+VLOOKUP(Tabla1[[#This Row],[Identificador]],'P&L Total'!A:L,12,FALSE) -> 0.30369889 | N82: =WORKDAY(Tabla1[[#This Row],[Fecha de compra]],0) -> 45989 | O82: Liquidado
A83: =+IF(COUNTIF(Tabla2[Cod_ope],Tabla1[[#This Row],[Cod_Ope]])>0,"out","stock") -> stock | B83: 46002 | C83: 39592 | D83: JAVA | E83: US46641Q1673 | F83: {=_xll.BDP(G83,"DS004")} -> USD | G83: =D83& " US Equity" -> JAVA US Equity | H83: =+_xll.BDP($G83,"Name") -> JPMORGAN ACTIVE VALUE ETF | I83: =+_xlfn.CONCAT(Tabla1[[#This Row],[Fecha de compra]],Tabla1[[#This Row],[Ticker]],Tabla1[[#This Row],[Q]]) -> 46002JAVA1000 | J83: 1000 | K83: 72.66 | L83: =+Tabla1[[#This Row],[Q]]*Tabla1[[#This Row],[P]] -> 72660 | M83: =+VLOOKUP(Tabla1[[#This Row],[Identificador]],'P&L Total'!A:L,12,FALSE) -> 0.0080635838 | N83: =WORKDAY(Tabla1[[#This Row],[Fecha de compra]],0) -> 46002 | O83: Liquidado
A84: =+IF(COUNTIF(Tabla2[Cod_ope],Tabla1[[#This Row],[Cod_Ope]])>0,"out","stock") -> stock | B84: 46002 | C84: 39592 | D84: JDOC | E84: US46654Q7658 | F84: {=_xll.BDP(G84,"DS004")} -> USD | G84: =D84& " US Equity" -> JDOC US Equity | H84: =+_xll.BDP($G84,"Name") -> JPMORGAN HEALTHCARE LEAD ETF | I84: =+_xlfn.CONCAT(Tabla1[[#This Row],[Fecha de compra]],Tabla1[[#This Row],[Ticker]],Tabla1[[#This Row],[Q]]) -> 46002JDOC1500 | J84: 1500 | K84: 58.081 | L84: =+Tabla1[[#This Row],[Q]]*Tabla1[[#This Row],[P]] -> 87121.5 | M84: =+VLOOKUP(Tabla1[[#This Row],[Identificador]],'P&L Total'!A:L,12,FALSE) -> -0.013802436 | N84: =WORKDAY(Tabla1[[#This Row],[Fecha de compra]],0) -> 46002 | O84: Liquidado
A85: =+IF(COUNTIF(Tabla2[Cod_ope],Tabla1[[#This Row],[Cod_Ope]])>0,"out","stock") -> stock | B85: 46002 | C85: 39592 | D85: TCHI | E85: US46436E4290 | F85: {=_xll.BDP(G85,"DS004")} -> USD | G85: =D85& " US Equity" -> TCHI US Equity | H85: =+_xll.BDP($G85,"Name") -> ISHARES MSCI CHINA TECH | I85: =+_xlfn.CONCAT(Tabla1[[#This Row],[Fecha de compra]],Tabla1[[#This Row],[Ticker]],Tabla1[[#This Row],[Q]]) -> 46002TCHI3000 | J85: 3000 | K85: 24.056 | L85: =+Tabla1[[#This Row],[Q]]*Tabla1[[#This Row],[P]] -> 72168 | M85: =+VLOOKUP(Tabla1[[#This Row],[Identificador]],'P&L Total'!A:L,12,FALSE) -> -0.059251608 | N85: =WORKDAY(Tabla1[[#This Row],[Fecha de compra]],0) -> 46002 | O85: Liquidado
A86: =+IF(COUNTIF(Tabla2[Cod_ope],Tabla1[[#This Row],[Cod_Ope]])>0,"out","stock") -> stock | B86: 46002 | C86: 39592 | D86: KMB | E86: US4943681035 | F86: {=_xll.BDP(G86,"DS004")} -> USD | G86: =D86& " US Equity" -> KMB US Equity | H86: =+_xll.BDP($G86,"Name") -> KIMBERLY-CLARK CORP | I86: =+_xlfn.CONCAT(Tabla1[[#This Row],[Fecha de compra]],Tabla1[[#This Row],[Ticker]],Tabla1[[#This Row],[Q]]) -> 46002KMB400 | J86: 400 | K86: 104.19 | L86: =+Tabla1[[#This Row],[Q]]*Tabla1[[#This Row],[P]] -> 41676 | M86: =+VLOOKUP(Tabla1[[#This Row],[Identificador]],'P&L Total'!A:L,12,FALSE) -> -0.10395594 | N86: =WORKDAY(Tabla1[[#This Row],[Fecha de compra]],1) -> 46003 | O86: Liquidado
A87: =+IF(COUNTIF(Tabla2[Cod_ope],Tabla1[[#This Row],[Cod_Ope]])>0,"out","stock") -> out | B87: 46003 | C87: 39592 | D87: QQQ | E87: US46090E1038 | F87: {=_xll.BDP(G87,"DS004")} -> USD | G87: =D87& " US Equity" -> QQQ US Equity | H87: =+_xll.BDP($G87,"Name") -> INVESCO QQQ TRUST SERIES 1 | I87: =+_xlfn.CONCAT(Tabla1[[#This Row],[Fecha de compra]],Tabla1[[#This Row],[Ticker]],Tabla1[[#This Row],[Q]]) -> 46003QQQ325 | J87: 325 | K87: 613.51 | L87: =+Tabla1[[#This Row],[Q]]*Tabla1[[#This Row],[P]] -> 199390.75 | M87: =+VLOOKUP(Tabla1[[#This Row],[Identificador]],'P&L Total'!A:L,12,FALSE) -> 0.020044586 | N87: =WORKDAY(Tabla1[[#This Row],[Fecha de compra]],0) -> 46003 | O87: Liquidado
A88: =+IF(COUNTIF(Tabla2[Cod_ope],Tabla1[[#This Row],[Cod_Ope]])>0,"out","stock") -> stock | B88: 46007 | C88: 39592 | D88: AUNA | E88: LU2791994721 | F88: {=_xll.BDP(G88,"DS004")} -> USD | G88: =D88& " US Equity" -> AUNA US Equity | H88: =+_xll.BDP($G88,"Name") -> AUNA SA-CLASS A | I88: =+_xlfn.CONCAT(Tabla1[[#This Row],[Fecha de compra]],Tabla1[[#This Row],[Ticker]],Tabla1[[#This Row],[Q]]) -> 46007AUNA6440 | J88: 6440 | K88: 4.63 | L88: =+Tabla1[[#This Row],[Q]]*Tabla1[[#This Row],[P]] -> 29817.2 | M88: =+VLOOKUP(Tabla1[[#This Row],[Identificador]],'P&L Total'!A:L,12,FALSE) -> -0.086320452 | N88: =WORKDAY(Tabla1[[#This Row],[Fecha de compra]],0) -> 46007 | O88: Liquidado
A89: =+IF(COUNTIF(Tabla2[Cod_ope],Tabla1[[#This Row],[Cod_Ope]])>0,"out","stock") -> stock | B89: 46009 | C89: 39592 | D89: CPACASC1 | E89: PEP239501005 | F89: {=_xll.BDP(G89,"DS004")} -> PEN | G89: =D89& " PE Equity" -> CPACASC1 PE Equity | H89: =+_xll.BDP($G89,"Name") -> CEMENTOS PACASMAYO SAA-CMN | I89: =+_xlfn.CONCAT(Tabla1[[#This Row],[Fecha de compra]],Tabla1[[#This Row],[Ticker]],Tabla1[[#This Row],[Q]]) -> 46009CPACASC115000 | J89: 15000 | K89: 6.92 | L89: =+Tabla1[[#This Row],[Q]]*Tabla1[[#This Row],[P]] -> 103800 | M89: =+VLOOKUP(Tabla1[[#This Row],[Identificador]],'P&L Total'!A:L,12,FALSE) -> 0.0086705202 | N89: =WORKDAY(Tabla1[[#This Row],[Fecha de compra]],0) -> 46009 | O89: Liquidado
A90: =+IF(COUNTIF(Tabla2[Cod_ope],Tabla1[[#This Row],[Cod_Ope]])>0,"out","stock") -> stock | B90: 46021 | C90: 39592 | D90: SIDERC1 | E90: PEP531001001 | F90: {=_xll.BDP(G90,"DS004")} -> PEN | G90: =D90& " PE Equity" -> SIDERC1 PE Equity | H90: =+_xll.BDP($G90,"Name") -> EMPRESA SIDERURGICA PERU SAA | I90: =+_xlfn.CONCAT(Tabla1[[#This Row],[Fecha de compra]],Tabla1[[#This Row],[Ticker]],Tabla1[[#This Row],[Q]]) -> 46021SIDERC115000 | J90: 15000 | K90: 2.22 | L90: =+Tabla1[[#This Row],[Q]]*Tabla1[[#This Row],[P]] -> 33300 | M90: =+VLOOKUP(Tabla1[[#This Row],[Identificador]],'P&L Total'!A:L,12,FALSE) -> 0.34374633 | N90: =WORKDAY(Tabla1[[#This Row],[Fecha de compra]],0) -> 46021 | O90: Liquidado
A91: =+IF(COUNTIF(Tabla2[Cod_ope],Tabla1[[#This Row],[Cod_Ope]])>0,"out","stock") -> stock | B91: 46021 | C91: 39592 | D91: INRETC1 | E91: PAL1801171A1 | F91: {=_xll.BDP(G91,"DS004")} -> USD | G91: =D91& " PE Equity" -> INRETC1 PE Equity | H91: =+_xll.BDP($G91,"Name") -> INRETAIL PERU CORP | I91: =+_xlfn.CONCAT(Tabla1[[#This Row],[Fecha de compra]],Tabla1[[#This Row],[Ticker]],Tabla1[[#This Row],[Q]]) -> 46021INRETC11500 | J91: 1500 | K91: 24.8 | L91: =+Tabla1[[#This Row],[Q]]*Tabla1[[#This Row],[P]] -> 37200 | M91: =+VLOOKUP(Tabla1[[#This Row],[Identificador]],'P&L Total'!A:L,12,FALSE) -> 0.070657617 | N91: =WORKDAY(Tabla1[[#This Row],[Fecha de compra]],0) -> 46021 | O91: Liquidado
A92: =+IF(COUNTIF(Tabla2[Cod_ope],Tabla1[[#This Row],[Cod_Ope]])>0,"out","stock") -> stock | B92: 46021 | C92: 39592 | D92: INRETC1 | E92: PAL1801171A1 | F92: {=_xll.BDP(G92,"DS004")} -> USD | G92: =D92& " PE Equity" -> INRETC1 PE Equity | H92: =+_xll.BDP($G92,"Name") -> INRETAIL PERU CORP | I92: =+_xlfn.CONCAT(Tabla1[[#This Row],[Fecha de compra]],Tabla1[[#This Row],[Ticker]],Tabla1[[#This Row],[Q]]) -> 46021INRETC11500 | J92: 1500 | K92: 24.75 | L92: =+Tabla1[[#This Row],[Q]]*Tabla1[[#This Row],[P]] -> 37125 | M92: =+VLOOKUP(Tabla1[[#This Row],[Identificador]],'P&L Total'!A:L,12,FALSE) -> 0.070657617 | N92: =WORKDAY(Tabla1[[#This Row],[Fecha de compra]],0) -> 46021 | O92: Liquidado
A93: =+IF(COUNTIF(Tabla2[Cod_ope],Tabla1[[#This Row],[Cod_Ope]])>0,"out","stock") -> out | B93: 46024 | C93: 39592 | D93: EWZ | E93: US4642864007 | F93: {=_xll.BDP(G93,"DS004")} -> USD | G93: =D93& " US Equity" -> EWZ US Equity | H93: =+_xll.BDP($G93,"Name") -> ISHARES MSCI BRAZIL ETF | I93: =+_xlfn.CONCAT(Tabla1[[#This Row],[Fecha de compra]],Tabla1[[#This Row],[Ticker]],Tabla1[[#This Row],[Q]]) -> 46024EWZ2490 | J93: 2490 | K93: 32.06 | L93: =+Tabla1[[#This Row],[Q]]*Tabla1[[#This Row],[P]] -> 79829.4 | M93: =+VLOOKUP(Tabla1[[#This Row],[Identificador]],'P&L Total'!A:L,12,FALSE) -> 0.031229701 | N93: =WORKDAY(Tabla1[[#This Row],[Fecha de compra]],0) -> 46024 | O93: Liquidado
A94: =+IF(COUNTIF(Tabla2[Cod_ope],Tabla1[[#This Row],[Cod_Ope]])>0,"out","stock") -> stock | B94: 46024 | C94: 39592 | D94: TCHI | E94: US46436E4290 | F94: {=_xll.BDP(G94,"DS004")} -> USD | G94: =D94& " US Equity" -> TCHI US Equity | H94: =+_xll.BDP($G94,"Name") -> ISHARES MSCI CHINA TECH | I94: =+_xlfn.CONCAT(Tabla1[[#This Row],[Fecha de compra]],Tabla1[[#This Row],[Ticker]],Tabla1[[#This Row],[Q]]) -> 46024TCHI2060 | J94: 2060 | K94: 24.24 | L94: =+Tabla1[[#This Row],[Q]]*Tabla1[[#This Row],[P]] -> 49934.4 | M94: =+VLOOKUP(Tabla1[[#This Row],[Identificador]],'P&L Total'!A:L,12,FALSE) -> -0.059251608 | N94: =WORKDAY(Tabla1[[#This Row],[Fecha de compra]],0) -> 46024 | O94: Liquidado
A95: =+IF(COUNTIF(Tabla2[Cod_ope],Tabla1[[#This Row],[Cod_Ope]])>0,"out","stock") -> stock | B95: 46024 | C95: 39592 | D95: CQQQ | E95: US46138E8003 | F95: {=_xll.BDP(G95,"DS004")} -> USD | G95: =D95& " US Equity" -> CQQQ US Equity | H95: =+_xll.BDP($G95,"Name") -> INVESCO CHINA TECHNOLOGY ETF | I95: =+_xlfn.CONCAT(Tabla1[[#This Row],[Fecha de compra]],Tabla1[[#This Row],[Ticker]],Tabla1[[#This Row],[Q]]) -> 46024CQQQ553 | J95: 553 | K95: 54.17 | L95: =+Tabla1[[#This Row],[Q]]*Tabla1[[#This Row],[P]] -> 29956.01 | M95: =+VLOOKUP(Tabla1[[#This Row],[Identificador]],'P&L Total'!A:L,12,FALSE) -> -0.06876884 | N95: =WORKDAY(Tabla1[[#This Row],[Fecha de compra]],0) -> 46024 | O95: Liquidado
A96: =+IF(COUNTIF(Tabla2[Cod_ope],Tabla1[[#This Row],[Cod_Ope]])>0,"out","stock") -> stock | B96: 46043 | C96: 39592 | D96: NFLX | E96: US64110L1061 | F96: {=_xll.BDP(G96,"DS004")} -> USD | G96: NFLX US Equity | H96: =+_xll.BDP($G96,"Name") -> NETFLIX INC | I96: =+_xlfn.CONCAT(Tabla1[[#This Row],[Fecha de compra]],Tabla1[[#This Row],[Ticker]],Tabla1[[#This Row],[Q]]) -> 46043NFLX1187 | J96: 1187 | K96: 84.28 | L96: =+Tabla1[[#This Row],[Q]]*Tabla1[[#This Row],[P]] -> 100040.36 | M96: =+VLOOKUP(Tabla1[[#This Row],[Identificador]],'P&L Total'!A:L,12,FALSE) -> 0.15021357 | N96: =WORKDAY(Tabla1[[#This Row],[Fecha de compra]],0) -> 46043 | O96: Liquidado
A97: =+IF(COUNTIF(Tabla2[Cod_ope],Tabla1[[#This Row],[Cod_Ope]])>0,"out","stock") -> out | B97: 46043 | C97: 39592 | D97: PLTR | E97: US69608A1088 | F97: {=_xll.BDP(G97,"DS004")} -> USD | G97: PLTR US Equity | H97: =+_xll.BDP($G97,"Name") -> PALANTIR TECHNOLOGIES INC-A | I97: =+_xlfn.CONCAT(Tabla1[[#This Row],[Fecha de compra]],Tabla1[[#This Row],[Ticker]],Tabla1[[#This Row],[Q]]) -> 46043PLTR598 | J97: 598 | K97: 166.93719 | L97: =+Tabla1[[#This Row],[Q]]*Tabla1[[#This Row],[P]] -> 99828.438 | M97: =+VLOOKUP(Tabla1[[#This Row],[Identificador]],'P&L Total'!A:L,12,FALSE) -> 0.048158251 | N97: =WORKDAY(Tabla1[[#This Row],[Fecha de compra]],0) -> 46043 | O97: Liquidado
A98: =+IF(COUNTIF(Tabla2[Cod_ope],Tabla1[[#This Row],[Cod_Ope]])>0,"out","stock") -> out | B98: 46043 | C98: 39592 | D98: TQQQ | E98: US74347X8314 | F98: {=_xll.BDP(G98,"DS004")} -> USD | G98: TQQQ US Equity | H98: =+_xll.BDP($G98,"Name") -> PROSHARES ULTRAPRO QQQ | I98: =+_xlfn.CONCAT(Tabla1[[#This Row],[Fecha de compra]],Tabla1[[#This Row],[Ticker]],Tabla1[[#This Row],[Q]]) -> 46043TQQQ2929 | J98: 2929 | K98: 51.1199 | L98: =+Tabla1[[#This Row],[Q]]*Tabla1[[#This Row],[P]] -> 149730.19 | M98: =+VLOOKUP(Tabla1[[#This Row],[Identificador]],'P&L Total'!A:L,12,FALSE) -> 0.018529142 | N98: =WORKDAY(Tabla1[[#This Row],[Fecha de compra]],0) -> 46043 | O98: Liquidado
A99: =+IF(COUNTIF(Tabla2[Cod_ope],Tabla1[[#This Row],[Cod_Ope]])>0,"out","stock") -> stock | B99: 46043 | C99: 39592 | D99: NIO | E99: US62914V1061 | F99: {=_xll.BDP(G99,"DS004")} -> USD | G99: NIO US Equity | H99: =+_xll.BDP($G99,"Name") -> NIO INC - ADR | I99: =+_xlfn.CONCAT(Tabla1[[#This Row],[Fecha de compra]],Tabla1[[#This Row],[Ticker]],Tabla1[[#This Row],[Q]]) -> 46043NIO10680 | J99: 10680 | K99: 4.65 | L99: =+Tabla1[[#This Row],[Q]]*Tabla1[[#This Row],[P]] -> 49662 | M99: =+VLOOKUP(Tabla1[[#This Row],[Identificador]],'P&L Total'!A:L,12,FALSE) -> 0.0016996563 | N99: =WORKDAY(Tabla1[[#This Row],[Fecha de compra]],1) -> 46044 | O99: Liquidado
A100: =+IF(COUNTIF(Tabla2[Cod_ope],Tabla1[[#This Row],[Cod_Ope]])>0,"out","stock") -> stock | B100: 46044 | C100: 39592 | D100: EWL | E100: US4642867497 | F100: {=_xll.BDP(G100,"DS004")} -> USD | G100: EWL US Equity | H100: =+_xll.BDP($G100,"Name") -> ISHARES MSCI SWITZERLAND ETF | I100: =+_xlfn.CONCAT(Tabla1[[#This Row],[Fecha de compra]],Tabla1[[#This Row],[Ticker]],Tabla1[[#This Row],[Q]]) -> 46044EWL1645 | J100: 1645 | K100: 60.702 | L100: =+Tabla1[[#This Row],[Q]]*Tabla1[[#This Row],[P]] -> 99854.79 | M100: =+VLOOKUP(Tabla1[[#This Row],[Identificador]],'P&L Total'!A:L,12,FALSE) -> -0.0076109519 | N100: =WORKDAY(Tabla1[[#This Row],[Fecha de compra]],0) -> 46044 | O100: Liquidado
...

Sheet Ventas
A1: Fecha de Venta | B1: Cliente | C1: Ticker | D1: ISIN | E1: Moneda | F1: Identificador | G1: Nombre | H1: Q | I1: P | J1: Monto_venta | K1: Cod_ope | L1: P&L
A2: 45941 | B2: 39592 | C2: XPEV | D2: =+VLOOKUP(C2,Tabla1[[#All],[Ticker]:[Nombre]],2,FALSE) -> US98422D1054 | E2: =+VLOOKUP(C2,Tabla1[[#All],[Ticker]:[Nombre]],3,FALSE) -> USD | F2: =+VLOOKUP(C2,Tabla1[[#All],[Ticker]:[Nombre]],4,FALSE) -> XPEV US Equity | G2: =+_xll.BDP($F2,"Name") -> XPENG INC - ADR | H2: 1403 | I2: 27.74 | J2: =+Tabla2[[#This Row],[Q]]*Tabla2[[#This Row],[P]] -> 38919.22 | K2: 45922XPEV1403 | L2: =+Tabla2[[#This Row],[Q]]*Tabla2[[#This Row],[P]]-VLOOKUP(Tabla2[[#This Row],[Cod_ope]],Tabla1[[Cod_Ope]:[Monto compra]],4,) -> 8967.976
A3: 45941 | B3: 39592 | C3: XPEV | D3: =+VLOOKUP(C3,Tabla1[[#All],[Ticker]:[Nombre]],2,FALSE) -> US98422D1054 | E3: =+VLOOKUP(C3,Tabla1[[#All],[Ticker]:[Nombre]],3,FALSE) -> USD | F3: =+VLOOKUP(C3,Tabla1[[#All],[Ticker]:[Nombre]],4,FALSE) -> XPEV US Equity | G3: =+_xll.BDP($F3,"Name") -> XPENG INC - ADR | H3: 1097 | I3: 27.74 | J3: =+Tabla2[[#This Row],[Q]]*Tabla2[[#This Row],[P]] -> 30430.78 | K3: 45939XPEV1097 | L3: =+Tabla2[[#This Row],[Q]]*Tabla2[[#This Row],[P]]-VLOOKUP(Tabla2[[#This Row],[Cod_ope]],Tabla1[[Cod_Ope]:[Monto compra]],4,) -> 5488.5916
A4: 45957 | B4: 39592 | C4: PLTR | D4: =+VLOOKUP(C4,Tabla1[[#All],[Ticker]:[Nombre]],2,FALSE) -> US69608A1088 | E4: =+VLOOKUP(C4,Tabla1[[#All],[Ticker]:[Nombre]],3,FALSE) -> USD | F4: =+VLOOKUP(C4,Tabla1[[#All],[Ticker]:[Nombre]],4,FALSE) -> PLTR US Equity | G4: =+_xll.BDP($F4,"Name") -> PALANTIR TECHNOLOGIES INC-A | H4: 491 | I4: 191.3001 | J4: =+Tabla2[[#This Row],[Q]]*Tabla2[[#This Row],[P]] -> 93928.349 | K4: 45917PLTR491 | L4: =+Tabla2[[#This Row],[Q]]*Tabla2[[#This Row],[P]]-VLOOKUP(Tabla2[[#This Row],[Cod_ope]],Tabla1[[Cod_Ope]:[Monto compra]],4,) -> 13931.683
A5: 45959 | B5: 39592 | C5: SPY | D5: =+VLOOKUP(C5,Tabla1[[#All],[Ticker]:[Nombre]],2,FALSE) -> US78462F1030 | E5: =+VLOOKUP(C5,Tabla1[[#All],[Ticker]:[Nombre]],3,FALSE) -> USD | F5: =+VLOOKUP(C5,Tabla1[[#All],[Ticker]:[Nombre]],4,FALSE) -> SPY US Equity | G5: =+_xll.BDP($F5,"Name") -> SS SPDR S&P 500 ETF TRUST-US | H5: 151 | I5: 688.296 | J5: =+Tabla2[[#This Row],[Q]]*Tabla2[[#This Row],[P]] -> 103932.7 | K5: 45917SPY151 | L5: =+Tabla2[[#This Row],[Q]]*Tabla2[[#This Row],[P]]-VLOOKUP(Tabla2[[#This Row],[Cod_ope]],Tabla1[[Cod_Ope]:[Monto compra]],4,) -> 4517.316
A6: 45959 | B6: 39592 | C6: EWZ | D6: =+VLOOKUP(C6,Tabla1[[#All],[Ticker]:[Nombre]],2,FALSE) -> US4642864007 | E6: =+VLOOKUP(C6,Tabla1[[#All],[Ticker]:[Nombre]],3,FALSE) -> USD | F6: =+VLOOKUP(C6,Tabla1[[#All],[Ticker]:[Nombre]],4,FALSE) -> EWZ US Equity | G6: =+_xll.BDP($F6,"Name") -> ISHARES MSCI BRAZIL ETF | H6: 1994 | I6: 31.21 | J6: =+Tabla2[[#This Row],[Q]]*Tabla2[[#This Row],[P]] -> 62232.74 | K6: 45932EWZ1994 | L6: =+Tabla2[[#This Row],[Q]]*Tabla2[[#This Row],[P]]-VLOOKUP(Tabla2[[#This Row],[Cod_ope]],Tabla1[[Cod_Ope]:[Monto compra]],4,) -> 2352.92
A7: 45959 | B7: 39592 | C7: EWZ | D7: =+VLOOKUP(C7,Tabla1[[#All],[Ticker]:[Nombre]],2,FALSE) -> US4642864007 | E7: =+VLOOKUP(C7,Tabla1[[#All],[Ticker]:[Nombre]],3,FALSE) -> USD | F7: =+VLOOKUP(C7,Tabla1[[#All],[Ticker]:[Nombre]],4,FALSE) -> EWZ US Equity | G7: =+_xll.BDP($F7,"Name") -> ISHARES MSCI BRAZIL ETF | H7: 1008 | I7: 31.21 | J7: =+Tabla2[[#This Row],[Q]]*Tabla2[[#This Row],[P]] -> 31459.68 | K7: 45937EWZ1008 | L7: =+Tabla2[[#This Row],[Q]]*Tabla2[[#This Row],[P]]-VLOOKUP(Tabla2[[#This Row],[Cod_ope]],Tabla1[[Cod_Ope]:[Monto compra]],4,) -> 1532.16
A8: 45959 | B8: 39592 | C8: EWZS | D8: =+VLOOKUP(C8,Tabla1[[#All],[Ticker]:[Nombre]],2,FALSE) -> US4642891315 | E8: =+VLOOKUP(C8,Tabla1[[#All],[Ticker]:[Nombre]],3,FALSE) -> USD | F8: =+VLOOKUP(C8,Tabla1[[#All],[Ticker]:[Nombre]],4,FALSE) -> EWZS US Equity | G8: =+_xll.BDP($F8,"Name") -> ISHARES MSCI BRAZIL SMALL-CA | H8: 2266 | I8: 13.713 | J8: =+Tabla2[[#This Row],[Q]]*Tabla2[[#This Row],[P]] -> 31073.658 | K8: 45937EWZS2266 | L8: =+Tabla2[[#This Row],[Q]]*Tabla2[[#This Row],[P]]-VLOOKUP(Tabla2[[#This Row],[Cod_ope]],Tabla1[[Cod_Ope]:[Monto compra]],4,) -> 1162.458
A9: 45959 | B9: 39592 | C9: EWZS | D9: =+VLOOKUP(C9,Tabla1[[#All],[Ticker]:[Nombre]],2,FALSE) -> US4642891315 | E9: =+VLOOKUP(C9,Tabla1[[#All],[Ticker]:[Nombre]],3,FALSE) -> USD | F9: =+VLOOKUP(C9,Tabla1[[#All],[Ticker]:[Nombre]],4,FALSE) -> EWZS US Equity | G9: =+_xll.BDP($F9,"Name") -> ISHARES MSCI BRAZIL SMALL-CA | H9: 4422 | I9: 13.713 | J9: =+Tabla2[[#This Row],[Q]]*Tabla2[[#This Row],[P]] -> 60638.886 | K9: 45932EWZS4422 | L9: =+Tabla2[[#This Row],[Q]]*Tabla2[[#This Row],[P]]-VLOOKUP(Tabla2[[#This Row],[Cod_ope]],Tabla1[[Cod_Ope]:[Monto compra]],4,) -> 853.446
A10: 45971 | B10: 39592 | C10: PLTR | D10: =+VLOOKUP(C10,Tabla1[[#All],[Ticker]:[Nombre]],2,FALSE) -> US69608A1088 | E10: =+VLOOKUP(C10,Tabla1[[#All],[Ticker]:[Nombre]],3,FALSE) -> USD | F10: =+VLOOKUP(C10,Tabla1[[#All],[Ticker]:[Nombre]],4,FALSE) -> PLTR US Equity | G10: =+_xll.BDP($F10,"Name") -> PALANTIR TECHNOLOGIES INC-A | H10: 434 | I10: 191.08 | J10: =+Tabla2[[#This Row],[Q]]*Tabla2[[#This Row],[P]] -> 82928.72 | K10: 45967PLTR434 | L10: =+Tabla2[[#This Row],[Q]]*Tabla2[[#This Row],[P]]-VLOOKUP(Tabla2[[#This Row],[Cod_ope]],Tabla1[[Cod_Ope]:[Monto compra]],4,) -> 2938.18
A11: 45971 | B11: 39592 | C11: PLTR | D11: =+VLOOKUP(C11,Tabla1[[#All],[Ticker]:[Nombre]],2,FALSE) -> US69608A1088 | E11: =+VLOOKUP(C11,Tabla1[[#All],[Ticker]:[Nombre]],3,FALSE) -> USD | F11: =+VLOOKUP(C11,Tabla1[[#All],[Ticker]:[Nombre]],4,FALSE) -> PLTR US Equity | G11: =+_xll.BDP($F11,"Name") -> PALANTIR TECHNOLOGIES INC-A | H11: 117 | I11: 191.08 | J11: =+Tabla2[[#This Row],[Q]]*Tabla2[[#This Row],[P]] -> 22356.36 | K11: 45968PLTR117 | L11: =+Tabla2[[#This Row],[Q]]*Tabla2[[#This Row],[P]]-VLOOKUP(Tabla2[[#This Row],[Cod_ope]],Tabla1[[Cod_Ope]:[Monto compra]],4,) -> 2465.19
A12: 45995 | B12: 39592 | C12: ITUB | D12: =+VLOOKUP(C12,Tabla1[[#All],[Ticker]:[Nombre]],2,FALSE) -> US4655621062 | E12: =+VLOOKUP(C12,Tabla1[[#All],[Ticker]:[Nombre]],3,FALSE) -> USD | F12: =+VLOOKUP(C12,Tabla1[[#All],[Ticker]:[Nombre]],4,FALSE) -> ITUB US Equity | G12: =+_xll.BDP($F12,"Name") -> ITAU UNIBANCO H-SPON PRF ADR | H12: 5705 | I12: 8.0701 | J12: =+Tabla2[[#This Row],[Q]]*Tabla2[[#This Row],[P]] -> 46039.921 | K12: 45912ITUB5705 | L12: =+Tabla2[[#This Row],[Q]]*Tabla2[[#This Row],[P]]-VLOOKUP(Tabla2[[#This Row],[Cod_ope]],Tabla1[[Cod_Ope]:[Monto compra]],4,) -> 6171.669
A13: 45995 | B13: 39592 | C13: BVN | D13: =+VLOOKUP(C13,Tabla1[[#All],[Ticker]:[Nombre]],2,FALSE) -> US2044481040 | E13: =+VLOOKUP(C13,Tabla1[[#All],[Ticker]:[Nombre]],3,FALSE) -> USD | F13: =+VLOOKUP(C13,Tabla1[[#All],[Ticker]:[Nombre]],4,FALSE) -> BVN us Equity | G13: =+_xll.BDP($F13,"Name") -> CIA DE MINAS BUENAVENTUR-ADR | H13: 2612 | I13: 25.12 | J13: =+Tabla2[[#This Row],[Q]]*Tabla2[[#This Row],[P]] -> 65613.44 | K13: 45951BVN2612 | L13: =+Tabla2[[#This Row],[Q]]*Tabla2[[#This Row],[P]]-VLOOKUP(Tabla2[[#This Row],[Cod_ope]],Tabla1[[Cod_Ope]:[Monto compra]],4,) -> 5746.4
... A48: 46091 | B48: 39592 | C48: KORU | D48: =+VLOOKUP(C48,Tabla1[[#All],[Ticker]:[Nombre]],2,FALSE) -> US25461A3876 | E48: =+VLOOKUP(C48,Tabla1[[#All],[Ticker]:[Nombre]],3,FALSE) -> USD | F48: =+VLOOKUP(C48,Tabla1[[#All],[Ticker]:[Nombre]],4,FALSE) -> KORU US Equity | G48: =+_xll.BDP($F48,"Name") -> DIREXION DLY M SK BULL 3X-UI | H48: 260 | I48: 410.2168 | J48: =+Tabla2[[#This Row],[Q]]*Tabla2[[#This Row],[P]] -> 106656.37 | K48: 46091KORU260 | L48: =+Tabla2[[#This Row],[Q]]*Tabla2[[#This Row],[P]]-VLOOKUP(Tabla2[[#This Row],[Cod_ope]],Tabla1[[Cod_Ope]:[Monto compra]],4,) -> 7515.69

Sheet Cerradas
A1: Stock | B1: Q | C1: Precio Promedio C | D1: P venta | E1: P&L % Realizado
A2: {=+_xlfn.UNIQUE(_xlfn._xlws.FILTER(Tabla1[Identificador],Tabla1[Stock]="out",))} -> ITUB US Equity | B2: =SUMIFS( Tabla1[Q], Tabla1[Identificador],A2, Tabla1[Stock],"out" ) -> 5705 | C2: {=SUMPRODUCT( (Tabla1[Identificador]=A2)* (Tabla1[Stock]="out")* Tabla1[Q]* Tabla1[P] ) /SUMIFS( Tabla1[Q], Tabla1[Identificador],A2, Tabla1[Stock],"out" )} -> 6.9883 | D2: {=SUMPRODUCT( (Tabla2[Identificador]=A2)* Tabla2[Q]* Tabla2[P] ) /SUMIFS( Tabla2[Q], Tabla2[Identificador],A2)} -> 8.0701 | E2: =+(D2*B2)/(B2*C2)-1 -> 0.1548016
A3: PLTR US Equity | B3: =SUMIFS( Tabla1[Q], Tabla1[Identificador],A3, Tabla1[Stock],"out" ) -> 5721 | C3: {=SUMPRODUCT( (Tabla1[Identificador]=A3)* (Tabla1[Stock]="out")* Tabla1[Q]* Tabla1[P] ) /SUMIFS( Tabla1[Q], Tabla1[Identificador],A3, Tabla1[Stock],"out" )} -> 155.21545 | D3: {=SUMPRODUCT( (Tabla2[Identificador]=A3)* Tabla2[Q]* Tabla2[P] ) /SUMIFS( Tabla2[Q], Tabla2[Identificador],A3)} -> 162.69036 | E3: =+(D3*B3)/(B3*C3)-1 -> 0.048158251
A4: SPY US Equity | B4: =SUMIFS( Tabla1[Q], Tabla1[Identificador],A4, Tabla1[Stock],"out" ) -> 316 | C4: {=SUMPRODUCT( (Tabla1[Identificador]=A4)* (Tabla1[Stock]="out")* Tabla1[Q]* Tabla1[P] ) /SUMIFS( Tabla1[Q], Tabla1[Identificador],A4, Tabla1[Stock],"out" )} -> 661.36362 | D4: {=SUMPRODUCT( (Tabla2[Identificador]=A4)* Tabla2[Q]* Tabla2[P] ) /SUMIFS( Tabla2[Q], Tabla2[Identificador],A4)} -> 685.79176 | E4: =+(D4*B4)/(B4*C4)-1 -> 0.036936014
A5: XPEV US Equity | B5: =SUMIFS( Tabla1[Q], Tabla1[Identificador],A5, Tabla1[Stock],"out" ) -> 2500 | C5: {=SUMPRODUCT( (Tabla1[Identificador]=A5)* (Tabla1[Stock]="out")* Tabla1[Q]* Tabla1[P] ) /SUMIFS( Tabla1[Q], Tabla1[Identificador],A5, Tabla1[Stock],"out" )} -> 21.957373 | D5: {=SUMPRODUCT( (Tabla2[Identificador]=A5)* Tabla2[Q]* Tabla2[P] ) /SUMIFS( Tabla2[Q], Tabla2[Identificador],A5)} -> 27.74 | E5: =+(D5*B5)/(B5*C5)-1 -> 0.26335696
A6: EWP US Equity | B6: =SUMIFS( Tabla1[Q], Tabla1[Identificador],A6, Tabla1[Stock],"out" ) -> 1031 | C6: {=SUMPRODUCT( (Tabla1[Identificador]=A6)* (Tabla1[Stock]="out")* Tabla1[Q]* Tabla1[P] ) /SUMIFS( Tabla1[Q], Tabla1[Identificador],A6, Tabla1[Stock],"out" )} -> 48.40709 | D6: {=SUMPRODUCT( (Tabla2[Identificador]=A6)* Tabla2[Q]* Tabla2[P] ) /SUMIFS( Tabla2[Q], Tabla2[Identificador],A6)} -> 55.0301 | E6: =+(D6*B6)/(B6*C6)-1 -> 0.13681901
A7: EWZ US Equity | B7: =SUMIFS( Tabla1[Q], Tabla1[Identificador],A7, Tabla1[Stock],"out" ) -> 16212 | C7: {=SUMPRODUCT( (Tabla1[Identificador]=A7)* (Tabla1[Stock]="out")* Tabla1[Q]* Tabla1[P] ) /SUMIFS( Tabla1[Q], Tabla1[Identificador],A7, Tabla1[Stock],"out" )} -> 35.038813 | D7: {=SUMPRODUCT( (Tabla2[Identificador]=A7)* Tabla2[Q]* Tabla2[P] ) /SUMIFS( Tabla2[Q], Tabla2[Identificador],A7)} -> 36.959812 | E7: =+(D7*B7)/(B7*C7)-1 -> 0.054824869
